Workbook

Sheet README
A1: Fantasy Life 2027 — Draft Research
A2: Built 2026-10-22 for the Oct 25, 2026 draft. Regenerate: python3 draft_guide/build_workbook.py (data in draft_guide/data/*.json).
A4: How to read it
A5: Master = top-15 per category by expected league points (EV). Draft Board = every candidate across all 15 categories ranked by VOR.
A6: EV = E[rank points among the 13 drafted picks] (Monte Carlo on mu/sd) + E[bonus] (ladder × probabilities; live formula on the Assumptions tab).
A7: VOR = EV − EV of the replacement pick (Nth best in the category; N on Assumptions). Risk-adj VOR subtracts λ × SD of rank points.
A8: Yellow confidence cell = C (estimate) or ladder probabilities inferred from the title price. A = exchange/book price seen; B = article reporting odds.
A10: Timeline (league year 2027)
A11: NFL 2026 and NCAAF 2026 are in progress (current records matter); NBA/NHL/NCAAB 2026-27 are starting; MLB/MLS/NASCAR/Golf/Tennis/Stock/Actor/Actress/Musician/Country are calendar 2027.
A12: Oscars (Mar 2027) honour 2026 films and Grammys (Feb 2027) honour Aug 2025–Aug 2026 music → awards bonuses are priced from awards-season odds; Actor/Actress BASELINE uses 2027 releases.
A13: Country = IMF October 2026 WEO (published Oct 13) 2027 growth, pulled from api.imf.org — final for the draft.
A15: Assumptions to confirm
... A46: Refresh: see .claude/commands/fl-draft-prep.md — new prices go in draft_guide/raw/*.json, run kalshi_overlay.py, edit data/*.json, rebuild.

Sheet Master
A1: Top 15 (EV) → | B1: NFL | C1: NBA | D1: MLB | E1: NHL | F1: NCAAF | G1: NCAAB | H1: Tennis | I1: Golf | J1: NASCAR | K1: MLS | L1: Actor | M1: Actress | N1: Musician | O1: Country | P1: Stock
A2: #1 | B2: San Francisco 49ers Kalshi 9.5% · EV 17.6 · [Todd] | C2: Oklahoma City Thunder Kalshi 21.5% · EV 17.5 · [Feder] | D2: Los Angeles Dodgers · EV 12.7 · [Wu] | E2: Carolina Hurricanes Kalshi 9.5% · EV 13.9 · [Jamzee] | F2: Georgia Kalshi 16.5% · EV 16.9 · [Theo] | G2: Florida +600 · EV 14.9 · [Wu] | H2: Jannik Sinner +100 AO 2027 (pre-injury) · EV 11.5 · [Buckley] | I2: Scottie Scheffler · EV 11.7 · [Wu] | J2: Kyle Larson 2026 title: Kalshi 42.0% · EV 14.5 · [Molmen] | K2: Nashville SC 2026 Cup: Kalshi 18.0% · EV 10.1 | L2: Ryan Gosling · EV 9.6 | M2: Julianne Moore · EV 12.1 | N2: Ella Langley Grammy EV 10.8 (raw 12.8, P(cap) 50%) · EV 20.1 | O2: Iraq IMF Oct-2026 2027: 19.0% · EV 10.8 | P2: MSTR (Long) · EV 7.1
A3: #2 | B3: Kansas City Chiefs Kalshi 9.5% · EV 14.8 · [Shep] | C3: San Antonio Spurs Kalshi 21.5% · EV 15.8 · [Wu] | D3: Milwaukee Brewers · EV 11.6 · [Buckley] | E3: Tampa Bay Lightning Kalshi 5.5% · EV 13.4 · [Fryar] | F3: Notre Dame Kalshi 12.5% · EV 15.5 · [Feder] | G3: Duke +600 · EV 14.7 · [Jens] | H3: Elena Rybakina +300 AO 2027 · EV 10.8 | I3: Rory McIlroy · EV 11.1 · [Molmen] | J3: Denny Hamlin 2026 title: Kalshi 28.0% · EV 12.5 · [Theo] | K3: Vancouver Whitecaps FC 2026 Cup: Kalshi 23.5% · EV 10.1 · [Feder] | L3: John Malkovich · EV 9.2 | M3: Kristen Bell · EV 9.1 | N3: Olivia Rodrigo Grammy EV 9.4 (raw 10.3, P(cap) 31%) · EV 18.0 · [Todd] | O3: Qatar IMF Oct-2026 2027: 18.8% · EV 10.8 | P3: COIN (Long) · EV 7.1 · [Tim]
A4: #3 | B4: Buffalo Bills Kalshi 10.5% · EV 14.1 · [Jens] | C4: Philadelphia 76ers Kalshi 12.5% · EV 12.8 | D4: New York Yankees · EV 11.2 · [Jens] | E4: Edmonton Oilers Kalshi 8.5% · EV 13.1 · [Buckley] | F4: Miami (FL) Kalshi 14.5% · EV 15.4 · [Wu] | G4: UConn +1300 · EV 11.7 · [Fryar] | H4: Aryna Sabalenka +175 to +185 AO 2027 · EV 10.6 · [Fryar] | I4: Matt Fitzpatrick · EV 10.4 | J4: Christopher Bell 2026 title: Kalshi 10.5% · EV 11.2 · [Wu] | K4: Inter Miami CF 2026 Cup: Kalshi 16.5% · EV 9.3 · [Theo] | L4: Aaron Pierre · EV 9.1 | M4: Anne Hathaway · EV 8.0 · [Korch] | N4: Olivia Dean Grammy EV 8.5 (raw 9.2, P(cap) 23%) · EV 15.8 | O4: Guyana IMF Oct-2026 2027: 16.8% · EV 10.1 · [Korch] | P4: AMD (Long) · EV 7.1
A5: #4 | B5: Minnesota Vikings Kalshi 3.5% · EV 12.5 | C5: New York Knicks Kalshi 8.5% · EV 12.4 · [Buckley] | D5: Atlanta Braves · EV 10.5 · [Todd] | E5: Colorado Avalanche Kalshi 12.5% · EV 12.3 · [Korch] | F5: Ohio State Kalshi 12.5% · EV 15.1 · [Mitchell] | G5: Illinois +1300 · EV 11.7 | H5: Carlos Alcaraz +150 AO 2027 · EV 10.4 · [Todd] | I5: Cameron Young · EV 9.8 | J5: Joey Logano 2026 title: Kalshi 5.5% · EV 10.4 · [Jamzee] | K5: St. Louis City SC 2026 Cup: Kalshi 5.5% · EV 8.4 | L5: Skyler Gisondo · EV 8.9 | M5: Hailee Steinfeld · EV 7.4 | N5: Bruno Mars Grammy EV 7.0 (raw 7.3, P(cap) 11%) · EV 15.1 | O5: Kuwait IMF Oct-2026 2027: 17.1% · EV 10.1 | P5: TTWO (Long) · EV 7.1 · [Molmen]
A6: #5 | B6: Baltimore Ravens Kalshi 7.5% · EV 11.7 · [Wu] | C6: Minnesota Timberwolves Kalshi 6.5% · EV 11.2 · [Todd] | D6: Tampa Bay Rays · EV 10.4 | E6: Florida Panthers Kalshi 10.5% · EV 11.7 · [Todd] | F6: Texas Kalshi 3.5% · EV 12.3 | G6: Michigan +1600 · EV 10.9 · [Jamzee] | H6: Alexander Zverev +700 AO 2027 · EV 10.1 · [Theo] | I6: Wyndham Clark · EV 9.3 | J6: Ryan Blaney 2026 title: Kalshi 5.5% · EV 9.9 · [Fryar] | K6: FC Dallas 2026 Cup: Kalshi 4.5% · EV 8.4 | L6: Matt Damon · EV 7.7 · [Molmen] | M6: Lauren Vélez · EV 7.3 | N6: Taylor Swift Grammy EV 7.4 (raw 7.7, P(cap) 13%) · EV 15.1 · [Molmen] | O6: Sudan IMF Oct-2026 2027: 15.0% · EV 8.8 | P6: SMCI (Long) · EV 7.0 · [Korch]
A7: #6 | B7: Jacksonville Jaguars Kalshi 6.5% · EV 11.3 | C7: Boston Celtics Kalshi 4.5% · EV 10.9 · [Shep] | D7: Chicago Cubs · EV 9.9 · [Tim] | E7: Vegas Golden Knights Kalshi 7.5% · EV 10.8 · [Tim] | F7: Indiana Kalshi 7.5% · EV 11.9 · [Korch] | G7: Michigan State +2200 · EV 9.9 | H7: Jessica Pegula · EV 7.7 · [Korch] | I7: Russell Henley · EV 8.8 · [Jens] | J7: William Byron 2026 title: Kalshi 0.5% · EV 8.8 · [Korch] | K7: New England Revolution 2026 Cup: Kalshi 3.5% · EV 8.3 | L7: Andrew Scott · EV 7.1 | M7: Kimiko Glenn · EV 7.3 | N7: Rosalía Grammy EV 6.6 (raw 6.8, P(cap) 9%) · EV 11.2 | O7: Bahrain IMF Oct-2026 2027: 13.9% · EV 8.7 | P7: TSLA (Short) · EV 7.0 · [Shep]
A8: #7 | B8: Chicago Bears Kalshi 4.5% · EV 10.8 | C8: Toronto Raptors Kalshi 2.5% · EV 9.6 | D8: San Diego Padres · EV 9.9 · [Theo] | E8: Minnesota Wild Kalshi 6.5% · EV 10.6 | F8: Alabama Kalshi 4.5% · EV 10.7 · [Jamzee] | G8: Houston +2500 · EV 9.7 · [Theo] | H8: Ben Shelton · EV 7.5 | I8: Tommy Fleetwood · EV 8.4 · [Korch] | J8: Chase Briscoe 2026 title: Kalshi 3.5% · EV 7.1 · [Jens] | K8: Chicago Fire FC 2026 Cup: Kalshi 4.5% · EV 8.1 | L8: Josh Gad · EV 6.9 | M8: Adria Arjona · EV 7.2 | N8: Harry Styles Grammy EV 3.5 (raw 3.5, P(cap) 1%) · EV 10.7 | O8: Uganda IMF Oct-2026 2027: 9.9% · EV 6.8 | P8: RKLB (Long) · EV 7.0
A9: #8 | B9: Denver Broncos Kalshi 3.5% · EV 10.2 · [Molmen] | C9: Miami Heat Kalshi 6.5% · EV 9.5 | D9: Philadelphia Phillies · EV 9.9 · [Mitchell] | E9: Utah Mammoth Kalshi 3.0% · EV 9.9 | F9: BYU Kalshi 3.5% · EV 8.4 · [Tim] | G9: Arizona +2500 · EV 9.7 | H9: Coco Gauff · EV 7.5 · [Wu] | I9: Chris Gotterup · EV 7.9 | J9: Chase Elliott 2026 title: Kalshi 1.0% · EV 7.0 · [Todd] | K9: Los Angeles FC 2026 Cup: Kalshi 5.5% · EV 8.1 · [Buckley] | L9: Brian Tyree Henry · EV 6.9 | M9: Amy Adams · EV 6.9 | N9: Ariana Grande Grammy EV 2.7 (raw 2.7, P(cap) 0%) · EV 10.7 | O9: Saudi Arabia IMF Oct-2026 2027: 7.9% · EV 4.6 | P9: HOOD (Long) · EV 7.0
A10: #9 | B10: New England Patriots Kalshi 2.5% · EV 9.5 · [Feder] | C10: Los Angeles Lakers Kalshi 3.5% · EV 9.2 · [Theo] | D10: Boston Red Sox · EV 9.6 | E10: Washington Capitals Kalshi 5.5% · EV 9.5 · [Feder] | F10: Ole Miss Kalshi 4.5% · EV 8.2 · [Todd] | G10: Kansas +4000 · EV 7.7 · [Shep] | H10: Mirra Andreeva · EV 7.0 | I10: Sam Burns · EV 7.4 | J10: Tyler Reddick 2026 title: Kalshi 2.0% · EV 6.9 · [Feder] | K10: Houston Dynamo FC 2026 Cup: Kalshi 3.5% · EV 8.1 | L10: Matt Berry · EV 6.7 | M10: Inde Navarrette · EV 6.8 | N10: Raye Grammy EV 5.8 (raw 5.9, P(cap) 6%) · EV 10.4 | O10: Guinea IMF Oct-2026 2027: 7.8% · EV 4.4 · [Todd] | P10: TSLA (Long) · EV 7.0
A11: #10 | B11: Cincinnati Bengals Kalshi 3.5% · EV 9.4 | C11: Detroit Pistons +2200 · EV 9.0 | D11: Arizona Diamondbacks · EV 9.0 | E11: Dallas Stars Kalshi 5.5% · EV 9.1 · [Mitchell] | F11: LSU Kalshi 4.5% · EV 7.9 | G11: Kentucky · EV 7.4 · [Feder] | H11: Felix Auger-Aliassime · EV 6.7 | I11: Xander Schauffele · EV 6.9 · [Tim] | J11: Shane van Gisbergen 2026 title: Kalshi 0.5% · EV 6.7 · [Mitchell] | K11: San Jose Earthquakes 2026 Cup: Kalshi 2.5% · EV 8.1 | L11: Jake Johnson · EV 6.5 | M11: Mia Goth · EV 6.8 | N11: BTS Grammy EV 2.6 · EV 9.9 · [Theo] | O11: Ethiopia IMF Oct-2026 2027: 7.8% · EV 4.3 | P11: SOFI (Long) · EV 7.0 · [Jens]
A12: #11 | B12: Detroit Lions +3500 · EV 9.1 · [Jamzee] | C12: Denver Nuggets Kalshi 2.5% · EV 8.7 · [Tim] | D12: Cleveland Guardians · EV 8.8 · [Fryar] | E12: Boston Bruins Kalshi +9900 · EV 8.6 · [Shep] | F12: Oregon Kalshi 2.0% · EV 6.4 · [Buckley] | G12: Purdue +6500 · EV 6.6 · [Korch] | H12: Daniil Medvedev · EV 6.2 · [Molmen] | I12: Collin Morikawa · EV 6.5 · [Buckley] | J12: Michael McDowell 2026 title: Kalshi 0.5% · EV 6.6 | K12: Charlotte FC 2026 Cup: Kalshi 2.5% · EV 7.9 · [Tim] | L12: Shameik Moore · EV 6.5 | M12: Rachel Brosnahan · EV 6.6 | N12: Morgan Wallen Grammy EV 0.8 · EV 9.2 | O12: United Arab Emirates IMF Oct-2026 2027: 7.7% · EV 4.2 | P12: IONQ (Long) · EV 7.0
... A16: #15 | B16: Houston Texans +4500 · EV 6.7 | C16: Portland Trail Blazers · EV 7.1 | D16: New York Mets · EV 8.6 · [Feder] | E16: San Jose Sharks Kalshi 4.5% · EV 7.3 | F16: Tennessee Kalshi 1.5% · EV 4.2 | G16: Texas Tech · EV 6.4 | H16: Novak Djokovic +1600 AO 2027 · EV 5.1 · [Shep] | I16: Jon Rahm · EV 5.1 · [Shep] | J16: Riley Herbst 2026 title: Kalshi 0.5% · EV 6.6 | K16: Orlando City SC 2026 Cup: Kalshi 0.5% · EV 7.4 · [Shep] | L16: Daniel Kaluuya · EV 6.4 | M16: Milly Alcock · EV 6.5 | N16: Justin Bieber Grammy EV 0.3 · EV 7.6 · [Fryar] | O16: Rwanda IMF Oct-2026 2027: 7.2% · EV 3.6 | P16: LULU (Long) · EV 7.0 · [Wu]

Sheet Rosters
A1: Player | B1: NFL | C1: NBA | D1: MLB | E1: NHL | F1: NCAAF | G1: NCAAB | H1: Tennis | I1: Golf | J1: NASCAR | K1: MLS | L1: Actor | M1: Actress | N1: Musician | O1: Country | P1: Stock | Q1: Best keeper (by VOR)
A2: Tim | B2: Seattle Seahawks | C2: Denver Nuggets | D2: Chicago Cubs | E2: Vegas Golden Knights | F2: BYU | G2: St. John's | H2: Madison Keys | I2: Xander Schauffele | J2: Bubba Wallace | K2: Charlotte FC | L2: Sean Penn | M2: Ariana Grande | N2: Kendrick Lamar | O2: Netherlands | P2: COIN (Long) | Q2: Vegas Golden Knights (NHL, VOR 0.3)
A3: Wu | B3: Baltimore Ravens | C3: San Antonio Spurs | D3: Los Angeles Dodgers | E3: New Jersey Devils | F3: Miami (FL) | G3: Florida | H3: Coco Gauff | I3: Scottie Scheffler | J3: Christopher Bell | K3: Minnesota United FC | L3: Wagner Moura | M3: Zendaya | N3: FKA Twigs | O3: United States | P3: LULU (Long) | Q3: San Antonio Spurs (NBA, VOR 6.2)
A4: Jens | B4: Buffalo Bills | C4: Cleveland Cavaliers | D4: New York Yankees | E4: Toronto Maple Leafs | F4: Georgia Tech | G4: Duke | H4: Jasmine Paolini | I4: Russell Henley | J4: Chase Briscoe | K4: San Diego FC | L4: George Clooney | M4: Amanda Seyfried | N4: Sabrina Carpenter | O4: Germany | P4: SOFI (Long) | Q4: Duke (NCAAB, VOR 5.0)
A5: Todd | B5: San Francisco 49ers | C5: Minnesota Timberwolves | D5: Atlanta Braves | E5: Florida Panthers | F5: Ole Miss | G5: UCLA | H5: Carlos Alcaraz | I5: Patrick Cantlay | J5: Chase Elliott | K5: New York Red Bulls | L5: Leonardo DiCaprio | M5: Teyana Taylor | N5: Olivia Rodrigo | O5: Guinea | P5: NVDA (Long) | Q5: Olivia Rodrigo (Musician, VOR 7.3)
A6: Mitchell | B6: Los Angeles Rams | C6: Golden State Warriors | D6: Philadelphia Phillies | E6: Dallas Stars | F6: Ohio State | G6: Alabama | H6: Taylor Fritz | I6: J.J. Spaun | J6: Shane van Gisbergen | K6: Philadelphia Union | L6: Pedro Pascal | M6: Charlize Theron | N6: Bad Bunny | O6: South Sudan | P6: CVNA (Short) | Q6: Ohio State (NCAAF, VOR 4.4)
A7: Shep | B7: Kansas City Chiefs | C7: Boston Celtics | D7: Houston Astros | E7: Boston Bruins | F7: Michigan | G7: Kansas | H7: Novak Djokovic | I7: Jon Rahm | J7: Daniel Suarez | K7: Orlando City SC | L7: Jeremy Allen White | M7: Tessa Thompson | N7: Drake | O7: France | P7: TSLA (Short) | Q7: Kansas City Chiefs (NFL, VOR 4.0)
A8: Theo | B8: Indianapolis Colts | C8: Los Angeles Lakers | D8: San Diego Padres | E8: Detroit Red Wings | F8: Georgia | G8: Houston | H8: Alexander Zverev | I8: Justin Thomas | J8: Denny Hamlin | K8: Inter Miami CF | L8: Dwayne Johnson | M8: Sydney Sweeney | N8: BTS | O8: Switzerland | P8: CMG (Long) | Q8: Georgia (NCAAF, VOR 6.2)
A9: Feder | B9: New England Patriots | C9: Oklahoma City Thunder | D9: New York Mets | E9: Washington Capitals | F9: Notre Dame | G9: Kentucky | H9: Iga Swiatek | I9: Bryson DeChambeau | J9: Tyler Reddick | K9: Vancouver Whitecaps FC | L9: Tom Holland | M9: Cynthia Erivo | N9: Lady Gaga | O9: Brazil | P9: PLTR (Long) | Q9: Oklahoma City Thunder (NBA, VOR 7.9)
A10: Fryar | B10: Green Bay Packers | C10: Los Angeles Clippers | D10: Cleveland Guardians | E10: Tampa Bay Lightning | F10: Texas A&M | G10: UConn | H10: Aryna Sabalenka | I10: Viktor Hovland | J10: Ryan Blaney | K10: Columbus Crew | L10: Chris Hemsworth | M10: Florence Pugh | N10: Justin Bieber | O10: Norway | P10: AVGO (Long) | Q10: Aryna Sabalenka (Tennis, VOR 3.0)
A11: Korch | B11: Philadelphia Eagles | C11: Houston Rockets | D11: Toronto Blue Jays | E11: Colorado Avalanche | F11: Indiana | G11: Purdue | H11: Jessica Pegula | I11: Tommy Fleetwood | J11: William Byron | K11: FC Cincinnati | L11: Jon Bernthal | M11: Anne Hathaway | N11: SZA | O11: Guyana | P11: SMCI (Long) | Q11: Guyana (Country, VOR 3.3)
A12: Molmen | B12: Denver Broncos | C12: Milwaukee Bucks | D12: Texas Rangers | E12: New York Rangers | F12: Texas Tech | G12: North Carolina | H12: Daniil Medvedev | I12: Rory McIlroy | J12: Kyle Larson | K12: LA Galaxy | L12: Matt Damon | M12: Jessie Buckley | N12: Taylor Swift | O12: Argentina | P12: TTWO (Long) | Q12: Kyle Larson (NASCAR, VOR 7.5)
... A14: Buckley | B14: Tampa Bay Buccaneers | C14: New York Knicks | D14: Milwaukee Brewers | E14: Edmonton Oilers | F14: Oregon | G14: Louisville | H14: Jannik Sinner | I14: Collin Morikawa | J14: Ross Chastain | K14: Los Angeles FC | L14: Robert Pattinson | M14: Anya Taylor-Joy | N14: Beyoncé | O14: Canada | P14: NEE (Long) | Q14: Jannik Sinner (Tennis, VOR 4.0)
A15: Source: data/rosters.json (2026-league draft). Gold = that player's highest-VOR pick (keeper candidate). Keeper rules not modelled: owned players stay ranked on the board.
A16: Value over replacement (VOR) of each current pick — live link to the category tabs
A17: Tim | B17: ='NFL'!N16 | C17: ='NBA'!N15 | D17: ='MLB'!N10 | E17: ='NHL'!N10 | F17: ='NCAAF'!N12 | G17: ='NCAAB'!N26 | H17: ='Tennis'!N29 | I17: ='Golf'!N14 | J17: ='NASCAR'!N23 | K17: ='MLS'!N15 | L17: ='Actor'!N97 | M17: ='Actress'!N92 | N17: ='Musician'!N21 | O17: ='Country'!N61 | P17: ='Stock'!N6
A18: Wu | B18: ='NFL'!N9 | C18: ='NBA'!N6 | D18: ='MLB'!N5 | E18: ='NHL'!N17 | F18: ='NCAAF'!N7 | G18: ='NCAAB'!N5 | H18: ='Tennis'!N12 | I18: ='Golf'!N5 | J18: ='NASCAR'!N7 | K18: ='MLS'!N26 | L18: ='Actor'!N88 | M18: ='Actress'!N21 | N18: ='Musician'!N34 | O18: ='Country'!N57 | P18: ='Stock'!N19
A19: Jens | B19: ='NFL'!N7 | C19: ='NBA'!N18 | D19: ='MLB'!N7 | E19: ='NHL'!N23 | F19: ='NCAAF'!N28 | G19: ='NCAAB'!N6 | H19: ='Tennis'!N28 | I19: ='Golf'!N10 | J19: ='NASCAR'!N11 | K19: ='MLS'!N24 | L19: ='Actor'!N93 | M19: ='Actress'!N22 | N19: ='Musician'!N22 | O19: ='Country'!N63 | P19: ='Stock'!N14
A20: Todd | B20: ='NFL'!N5 | C20: ='NBA'!N9 | D20: ='MLB'!N8 | E20: ='NHL'!N9 | F20: ='NCAAF'!N13 | G20: ='NCAAB'!N34 | H20: ='Tennis'!N8 | I20: ='Golf'!N32 | J20: ='NASCAR'!N12 | K20: ='MLS'!N21 | L20: ='Actor'!N95 | M20: ='Actress'!N89 | N20: ='Musician'!N6 | O20: ='Country'!N13 | P20: ='Stock'!N22
A21: Mitchell | B21: ='NFL'!N18 | C21: ='NBA'!N27 | D21: ='MLB'!N12 | E21: ='NHL'!N14 | F21: ='NCAAF'!N8 | G21: ='NCAAB'!N18 | H21: ='Tennis'!N26 | I21: ='Golf'!N16 | J21: ='NASCAR'!N14 | K21: ='MLS'!N16 | L21: ='Actor'!N64 | M21: ='Actress'!N90 | N21: ='Musician'!N17 | O21: ='Country'!N18 | P21: ='Stock'!N18
A22: Shep | B22: ='NFL'!N6 | C22: ='NBA'!N10 | D22: ='MLB'!N20 | E22: ='NHL'!N15 | F22: ='NCAAF'!N25 | G22: ='NCAAB'!N13 | H22: ='Tennis'!N19 | I22: ='Golf'!N19 | J22: ='NASCAR'!N27 | K22: ='MLS'!N19 | L22: ='Actor'!N92 | M22: ='Actress'!N87 | N22: ='Musician'!N16 | O22: ='Country'!N65 | P22: ='Stock'!N10
A23: Theo | B23: ='NFL'!N30 | C23: ='NBA'!N13 | D23: ='MLB'!N11 | E23: ='NHL'!N34 | F23: ='NCAAF'!N5 | G23: ='NCAAB'!N11 | H23: ='Tennis'!N9 | I23: ='Golf'!N31 | J23: ='NASCAR'!N6 | K23: ='MLS'!N7 | L23: ='Actor'!N96 | M23: ='Actress'!N84 | N23: ='Musician'!N14 | O23: ='Country'!N64 | P23: ='Stock'!N23
A24: Feder | B24: ='NFL'!N13 | C24: ='NBA'!N5 | D24: ='MLB'!N19 | E24: ='NHL'!N13 | F24: ='NCAAF'!N6 | G24: ='NCAAB'!N14 | H24: ='Tennis'!N20 | I24: ='Golf'!N41 | J24: ='NASCAR'!N13 | K24: ='MLS'!N6 | L24: ='Actor'!N89 | M24: ='Actress'!N54 | N24: ='Musician'!N25 | O24: ='Country'!N59 | P24: ='Stock'!N27
A25: Fryar | B25: ='NFL'!N17 | C25: ='NBA'!N29 | D25: ='MLB'!N15 | E25: ='NHL'!N6 | F25: ='NCAAF'!N27 | G25: ='NCAAB'!N7 | H25: ='Tennis'!N7 | I25: ='Golf'!N17 | J25: ='NASCAR'!N9 | K25: ='MLS'!N30 | L25: ='Actor'!N94 | M25: ='Actress'!N88 | N25: ='Musician'!N19 | O25: ='Country'!N62 | P25: ='Stock'!N29
A26: Korch | B26: ='NFL'!N29 | C26: ='NBA'!N16 | D26: ='MLB'!N17 | E26: ='NHL'!N8 | F26: ='NCAAF'!N10 | G26: ='NCAAB'!N15 | H26: ='Tennis'!N10 | I26: ='Golf'!N11 | J26: ='NASCAR'!N10 | K26: ='MLS'!N23 | L26: ='Actor'!N98 | M26: ='Actress'!N7 | N26: ='Musician'!N24 | O26: ='Country'!N7 | P26: ='Stock'!N9
A27: Molmen | B27: ='NFL'!N12 | C27: ='NBA'!N33 | D27: ='MLB'!N22 | E27: ='NHL'!N22 | F27: ='NCAAF'!N16 | G27: ='NCAAB'!N24 | H27: ='Tennis'!N15 | I27: ='Golf'!N6 | J27: ='NASCAR'!N5 | K27: ='MLS'!N18 | L27: ='Actor'!N9 | M27: ='Actress'!N91 | N27: ='Musician'!N9 | O27: ='Country'!N56 | P27: ='Stock'!N8
A28: Jamzee | B28: ='NFL'!N15 | C28: ='NBA'!N22 | D28: ='MLB'!N23 | E28: ='NHL'!N5 | F28: ='NCAAF'!N11 | G28: ='NCAAB'!N9 | H28: ='Tennis'!N27 | I28: ='Golf'!N22 | J28: ='NASCAR'!N8 | K28: ='MLS'!N17 | L28: ='Actor'!N67 | M28: ='Actress'!N64 | N28: ='Musician'!N23 | O28: ='Country'!N60 | P28: ='Stock'!N26
A29: Buckley | B29: ='NFL'!N32 | C29: ='NBA'!N8 | D29: ='MLB'!N6 | E29: ='NHL'!N7 | F29: ='NCAAF'!N15 | G29: ='NCAAB'!N16 | H29: ='Tennis'!N5 | I29: ='Golf'!N15 | J29: ='NASCAR'!N20 | K29: ='MLS'!N12 | L29: ='Actor'!N41 | M29: ='Actress'!N41 | N29: ='Musician'!N26 | O29: ='Country'!N58 | P29: ='Stock'!N30

Sheet My Draft (slot 13)
A1: Korch — 2027 draft plan from the last slot
A2: Korch picks 13th (last) in every odd round and 1st in every even round; the keeper round also runs in draft order, so with no keeper the first three picks are back-to-back (keeper-round #13, R1 #13, R2 #14). Later pairs: 39/40, 65/66, 91/92, 117/118, 143/144, 169/170.
A3: Simulated 80 drafts per option (draft_sim.py, as of 2026-10-22). Assumed order: Shep, Jens, Todd, Feder, Tim, Molmen, Theo, Buckley, Mitchell, Jamzee, Fryar, Wu, Korch
A5: 1. Keep or draft? Recommendation: NO KEEPER
A6: Option | B6: Expected 2027 EV (dropoff drafting) | C6: SD | D6: Expected EV (best-available drafting)
A7: No keeper | B7: 157.5 | C7: 3.1 | D7: 154.9
A8: Keep Colorado Avalanche | B8: 152.9 | C8: 3.5 | D8: 150.3
A9: Keep Indiana | B9: 152.1 | C9: 2.7 | D9: 148.8
A10: Keep Guyana | B10: 151.5 | C10: 3.3 | D10: 150
A11: No keeper wins in the simulation (157.5 vs 152.9 keeping the Avalanche, 152.1 Indiana, 151.5 Guyana; sd ~3). Keeping uses the keeper-round pick on a player you could replace later; not keeping turns it into a free pick at #13, right before your R1/R2 turn.
A12: The Avalanche slid to 12.3 (4th in NHL) behind the Hurricanes 13.9, Lightning 13.4 and Oilers 13.1 (Oct 22 refresh). The sim now has Jamzee keeping Carolina and Fryar keeping Tampa Bay, so NHL thins out, but Golden Knights 10.8, Panthers 11.7 (Todd keeps Rodrigo) and Wild 10.6 still last to about R5. Keeping Colorado costs ~4.6 pts vs a free premium pick.
A13: Guyana is no longer the clear #1 Country: the IMF October 2026 WEO puts Iraq (19.0%), Qatar (18.8%) and Kuwait (17.1%) ahead of it for 2027 (16.8%), with Sudan 15.0% and Bahrain 13.9% close behind. Six live options, and Country goes late (median R10).
A14: What usually falls to #13 in the keeper round (Oct 22 refresh): the San Francisco 49ers (NFL #1, 17.6; Kalshi Super Bowl price now 17.5%). Todd owns them but keeps Rodrigo. Otherwise a top Musician (Langley 20.1 / Dean 15.8, both unowned). NCAAF goes at R1/R2: Texas fell again to 12.3 (title 3.5%), so Notre Dame 15.5 / Miami 15.4 are the targets if their owners keep elsewhere.
A16: 2. Round by round (no keeper, dropoff drafting): how often each category is the right pick, and who it usually is
A17: Round | B17: Overall pick | C17: Most common pick | D17: Also | E17: Also
A18: Keeper | B18: keeper rd #13 | C18: NFL 80% (San Francisco 49ers, Denver Broncos) | D18: Musician 20% (Morgan Wallen, BTS)
A19: R1 | B19: 13 | C19: NCAAB 41% (Florida, UConn) | D19: NCAAF 36% (Texas, Notre Dame) | E19: NASCAR 21% (Kyle Larson, Denny Hamlin)
A20: R2 | B20: 14 | C20: NCAAF 64% (Texas, Notre Dame) | D20: NCAAB 21% (Florida, UConn) | E20: NBA 5% (Minnesota Timberwolves, Boston Celtics)
A21: R3 | B21: 39 | C21: NASCAR 70% (Kyle Larson, Denny Hamlin) | D21: MLB 10% (Los Angeles Dodgers, Chicago Cubs) | E21: NCAAB 7% (Florida, UConn)
A22: R4 | B22: 40 | C22: NBA 39% (Minnesota Timberwolves, Boston Celtics) | D22: MLB 17% (Los Angeles Dodgers, Chicago Cubs) | E22: Golf 15% (Russell Henley, Xander Schauffele)
A23: R5 | B23: 65 | C23: NHL 38% (Vegas Golden Knights, Minnesota Wild) | D23: Tennis 23% (Elena Rybakina, Aryna Sabalenka) | E23: Country 7% (Sudan, Guyana)
A24: R6 | B24: 66 | C24: MLS 28% (Nashville SC, St. Louis City SC) | D24: NHL 24% (Vegas Golden Knights, Minnesota Wild) | E24: Tennis 16% (Elena Rybakina, Aryna Sabalenka)
A25: R7 | B25: 91 | C25: MLB 35% (Los Angeles Dodgers, Chicago Cubs) | D25: Musician 26% (Morgan Wallen, BTS) | E25: Country 12% (Sudan, Guyana)
A26: R8 | B26: 92 | C26: Country 56% (Sudan, Guyana) | D26: Golf 26% (Russell Henley, Xander Schauffele) | E26: Musician 6% (Morgan Wallen, BTS)
A27: R9 | B27: 117 | C27: Musician 28% (Morgan Wallen, BTS) | D27: NBA 25% (Minnesota Timberwolves, Boston Celtics) | E27: MLB 17% (Los Angeles Dodgers, Chicago Cubs)
A28: R10 | B28: 118 | C28: MLS 30% (Nashville SC, St. Louis City SC) | D28: Actor 19% (Josh Gad, Aaron Pierre) | E28: Musician 11% (Morgan Wallen, BTS)
A29: R11 | B29: 143 | C29: Actress 33% (Hailee Steinfeld, Lauren Vélez) | D29: MLS 26% (Nashville SC, St. Louis City SC) | E29: Tennis 17% (Elena Rybakina, Aryna Sabalenka)
A30: R12 | B30: 144 | C30: Actress 41% (Hailee Steinfeld, Lauren Vélez) | D30: Golf 20% (Russell Henley, Xander Schauffele) | E30: Tennis 17% (Elena Rybakina, Aryna Sabalenka)
... A32: R14 | B32: 170 | C32: Actor 53% (Josh Gad, Aaron Pierre) | D32: Golf 17% (Russell Henley, Xander Schauffele) | E32: Stock 14% (MSTR (Long), COIN (Long))
A33: Names in brackets are the players you most often end up with in that category across all rounds (for the keeper-round Musician case that means the best one left: Langley/Dean/Mars if they are still there).
A34: Rule of thumb: take the scarce team categories (NCAAF, NCAAB, NBA, NFL) at your early turns; let NASCAR, MLS, Actor, Actress and Stock come to you — the field ignores them until the middle or the end.
A36: 3. Value picks
A37: NASCAR | B37: Kyle Larson / Denny Hamlin | C37: #1/#2 NASCAR (14.5 / 12.5). Nobody drafted NASCAR before pick 63 last year; in the sim Larson is still there at your R1/R3 turn most of the time.
A38: NCAAF | B38: Notre Dame / Miami (FL), then Texas | C38: Notre Dame 15.5 (Feder keeps OKC) and Miami 15.4 (Wu keeps the Spurs) are the realistic R1/R2 targets; Texas (12.3, unowned) is the fallback after its title odds fell to 3.5%.
A39: NCAAB | B39: Florida | C39: #1 NCAAB (14.9). Wu owns it but should keep the Spurs instead.
A40: NBA | B40: Philadelphia 76ers | C40: #3 NBA (12.8), unowned. NBA gets stripped fast; this is the realistic upside after OKC/SAS are kept.
A41: NFL | B41: San Francisco 49ers, then Vikings / Jaguars | C41: 49ers 17.6 (NFL #1; Todd keeps Rodrigo, so the 49ers are in the pool) = keeper-round target. Fallback: Vikings 12.5 / Jaguars 11.3, unowned, last to about R5.
A42: NHL | B42: Golden Knights / Panthers / Wild | C42: 10.6-11.7 EV and last to about R5; Carolina and Tampa Bay are likely kept.
A43: Tennis | B43: Elena Rybakina | C43: #2 Tennis (10.8), unowned. Tennis is overpriced early, so wait and take what is left.
A44: Golf | B44: Matt Fitzpatrick / Cameron Young | C44: Unowned 9.8-10.4 EV. Golf is overpriced early.
A45: MLS | B45: Nashville / St. Louis / Vancouver | C45: The field barely drafts MLS until R7+; the best club is free to about R6.
A46: Country | B46: Iraq / Qatar / Kuwait (then Guyana, Sudan, Bahrain) | C46: IMF Oct-2026 WEO 2027 growth 17-19% after the 2026 war contraction; nobody owns them and Country goes late. Wide error bars — they are rebound forecasts.
A48: 4. Sleepers
A49: Country | B49: Bahrain / Sudan | C49: IMF Oct-2026: Bahrain 13.9%, Sudan 15.0% for 2027 — the fifth/sixth-best Country options, usually still there late.
A50: Actor | B50: Aaron Pierre / Skyler Gisondo | C50: Starfighter + Man of Tomorrow (Superman) cast lists; real box-office draws the field ignores.
A51: Actor / Actress | B51: Josh Gad / Kristen Bell | C51: Frozen 3 (Nov 24, 2027). Bell also has Sonic 4.
A52: Actress | B52: Hailee Steinfeld | C52: Top-5 box-office actress on the 2027 slate with no Oscar buzz to inflate her price.
A53: NCAAB | B53: Illinois / Michigan State | C53: Top-6 NCAAB EV, never drafted early.
A54: MLB | B54: Tampa Bay Rays | C54: Unowned, #5 MLB EV, just won a playoff series.
A55: Musician | B55: Olivia Dean / Bruno Mars | C55: Big Grammy EV without Ella Langley's price; Dean has no chart carry-over, so the field may let her slide.
A57: 5. Don't pay for these early
A58: Tennis: 7 gone by R1 last year and returned 2.8 pts less than the round average. Take what is left around R6-R11.
A59: Golf: returned 1.7 pts under the round average.
A60: Stock: pure luck; take it in R13.
A61: Oscar-driven actors/actresses (Julianne Moore, John Malkovich): the field overpays for Oscar buzz; their 2027 box office is small.
A62: Country for bonus reasons: 2027 has no Olympics/World Cup, so the 13-pt Country bonuses from 2026 will not repeat.
A64: 6. How the other 12 draft (2025 draft) and what they will likely keep
A65: Shep | B65: Kept the Chiefs (1.0 pts). Tennis R1, Music R2. Worst early returns in the league (7.4/pick R0-4). Likely keeps the Chiefs again. | C65: keeps Kansas City Chiefs ~100%
A66: Jens | B66: Kept the Bills. Team sports early, Country too early (Germany, 5 pts), weak late (4.5/pick R8+). Likely keeps Duke. | C66: keeps Duke ~100%
A67: Feder | B67: Kept OKC. Tennis R1 (Swiatek bust), Music R2 (Gaga). Leaves NASCAR to the end. Will keep OKC. | C67: keeps Oklahoma City Thunder ~100%
A68: Todd | B68: Kept Alcaraz. NHL R1 (Panthers bust), team sports early, late Music hit (Rodrigo). Likely keeps Rodrigo. | C68: keeps Olivia Rodrigo ~100%
A69: Tim | B69: No keeper. Stars early (Kendrick first, Nuggets, NHL, Golf); weakest late picks (4.6/pick R8+). Coin flip to keep the Seahawks. | C69: keeps Vegas Golden Knights ~11%
A70: Theo | B70: Kept Houston. Tennis R1 (Zverev hit), NCAAF/NFL early, NASCAR R6 (Hamlin hit). Will keep Georgia. | C70: keeps Georgia ~100%
A71: Mitchell | B71: Kept Ohio State. Music R1 (Bad Bunny 23 pts), MLS early (R3), Country last (South Sudan hit). Will keep Ohio State. | C71: keeps Ohio State ~100%
A72: Molmen | B72: Kept Taylor Swift. Individual-sports specialist: Tennis, Golf, Actress, Country, NASCAR, MLS all by R6; punts team sports (Bucks/Rangers 1 pt). Likely keeps Swift, which leaves Larson in the pool. | C72: keeps Taylor Swift ~100%
A73: Jamzee | B73: No keeper. NFL/NHL/NCAAF early, Actor R3 (Chalamet bust), great late hits (Michigan R7, Spain R9). Coin flip on Alabama. | C73: keeps Carolina Hurricanes ~99%
A74: Buckley | B74: Kept Sinner. Team sports early, Music R6 (Beyonce bust). Coin flip between the Oilers/Knicks/Sinner. | C74: keeps Edmonton Oilers ~100%
A75: Fryar | B75: Kept Sabalenka. NFL/NCAAF early, Country R3 (Norway hit). Coin flip on UConn. | C75: keeps Tampa Bay Lightning ~99%
A76: Wu | B76: No keeper. MLB/Golf first, best late drafter after you (Spurs R14, USA R7). Should keep the Spurs; picks right before you. | C76: keeps San Antonio Spurs ~96%
A78: 7. Why you won 2026
A79: +31.7 pts over the category averages.
A80: No keeper = an extra premium pick: Indiana at the keeper-round slot scored 26 (+14.9 vs the NCAAF average).
A81: Scarce team categories early: Avalanche R2 (+9.5), Purdue R4 (+4.1).
A82: Individual/award categories late, after the field had moved on: Hathaway R6 (+2.5), Fleetwood R7 (+2.2), Bernthal R9 (+3.9).
A83: Some luck at the end: SZA R14 (Grammy 13-pt bonus, +4.9), SMCI R13 (+5.0).
A84: Leaks to fix: Blue Jays R5 (-6.4), Byron R8 (-3.0), FC Cincinnati R10 (-2.5), Rockets R3 (-2.1).
A85: Best late-round returns in the league: 10.1 pts/pick from R8 on (everyone else 4.5-9.1).

Sheet Draft Plan
A1: Category | B1: 2026: 1st pick # | C1: 2026: median rd | D1: 2026: gone by R2 / R4 / R7 | E1: 2026: avg projected final | F1: 2026: surplus vs slot | G1: 2027 best EV | H1: EV left @R2 | I1: EV left @R4 | J1: EV left @R7 | K1: Cost to wait: R2 | L1: R4 | M1: R7 | N1: Free until round (<=1 pt) | O1: Read
A2: NFL | B2: 9 | C2: 3 | D2: 7 / 10 / 10 | E2: 10.7 | F2: -1 | G2: 17.6 | H2: 10.2 | I2: 9.1 | J2: 9.1 | K2: 7.4 | L2: 8.5 | M2: 8.5 | N2: 0 | O2: TAKE EARLY (R1-2): by R1 the field has taken 5 and the best left is 11.3 vs 17.6
A3: NBA | B3: 1 | C3: 4 | D3: 4 / 9 / 11 | E3: 11.1 | F3: -0.2 | G3: 17.5 | H3: 11.2 | I3: 9 | J3: 8.4 | K3: 6.2 | L3: 8.5 | M3: 9.1 | N3: 0 | O3: TAKE EARLY (R1-2): by R1 the field has taken 4 and the best left is 11.2 vs 17.5
A4: MLB | B4: 30 | C4: 6 | D4: 1 / 4 / 8 | E4: 10.4 | F4: 0.8 | G4: 12.7 | H4: 11.6 | I4: 10.4 | J4: 9.6 | K4: 1.2 | L4: 2.3 | M4: 3.2 | N4: 0 | O4: FLEXIBLE: within 1 pt through R0; by R5 you still get most of it
A5: NHL | B5: 4 | C5: 7 | D5: 4 / 6 / 8 | E5: 10 | F5: -0.6 | G5: 13.9 | H5: 11.7 | I5: 10.6 | J5: 9.5 | K5: 2.2 | L5: 3.3 | M5: 4.4 | N5: 1 | O5: TAKE BY R2: from R3 the best left drops 3+ pts below the top
A6: NCAAF | B6: 14 | C6: 3 | D6: 7 / 9 / 10 | E6: 11.1 | F6: -0.1 | G6: 16.9 | H6: 8.4 | I6: 7.9 | J6: 6.4 | K6: 8.5 | L6: 9 | M6: 10.4 | N6: 0 | O6: TAKE EARLY (R1-2): by R2 the field has taken 7 and the best left is 8.4 vs 16.9
A7: NCAAB | B7: 24 | C7: 7 | D7: 2 / 6 / 9 | E7: 10.3 | F7: 0.1 | G7: 14.9 | H7: 11.7 | I7: 9.7 | J7: 7.4 | K7: 3.2 | L7: 5.2 | M7: 7.5 | N7: 1 | O7: TAKE EARLY (R1-2): by R2 the field has taken 2 and the best left is 11.7 vs 14.9
A8: Tennis | B8: 6 | C8: 6 | D8: 7 / 8 / 10 | E8: 9 | F8: -2.9 | G8: 11.5 | H8: 7.5 | I8: 7 | J8: 6.2 | K8: 4 | L8: 4.5 | M8: 5.4 | N8: 0 | O8: TAKE EARLY (R1-2): by R1 the field has taken 7 and the best left is 7.5 vs 11.5
A9: Golf | B9: 2 | C9: 7 | D9: 2 / 3 / 7 | E9: 7.8 | F9: -1.8 | G9: 11.7 | H9: 10.4 | I9: 9.8 | J9: 7.9 | K9: 1.3 | L9: 1.9 | M9: 3.8 | N9: 1 | O9: FLEXIBLE: within 1 pt through R1; by R5 you still get most of it
A10: NASCAR | B10: 63 | C10: 8 | D10: 0 / 0 / 6 | E10: 9.7 | F10: 0.8 | G10: 14.5 | H10: 14.5 | I10: 14.5 | J10: 7.1 | K10: 0 | L10: 0 | M10: 7.5 | N10: 4 | O10: WAIT: the field leaves it alone until ~R5; the best player is free through R4
A11: MLS | B11: 31 | C11: 10 | D11: 0 / 1 / 5 | E11: 9.7 | F11: 1.3 | G11: 10.1 | H11: 10.1 | I11: 10.1 | J11: 8.3 | K11: 0 | L11: 0.1 | M11: 1.9 | N11: 6 | O11: WAIT: the field leaves it alone until ~R7; the best player is free through R6
A12: Actor | B12: 38 | C12: 8 | D12: 0 / 1 / 5 | E12: 8.6 | F12: -0.6 | G12: 9.6 | H12: 9.6 | I12: 9.2 | J12: 7.1 | K12: 0 | L12: 0.4 | M12: 2.6 | N12: 4 | O12: WAIT: the field leaves it alone until ~R5; the best player is free through R4
A13: Actress | B13: 37 | C13: 8 | D13: 0 / 1 / 5 | E13: 8.5 | F13: -0.5 | G13: 12.1 | H13: 12.1 | I13: 9.1 | J13: 7.3 | K13: 0 | L13: 3 | M13: 4.8 | N13: 2 | O13: TAKE BY R2: from R3 the best left drops 3+ pts below the top
... A16: Stock | B16: 158 | C16: 13 | D16: 0 / 0 / 0 | E16: 7 | F16: -1 | G16: 7.1 | H16: 7.1 | I16: 7.1 | J16: 7.1 | K16: 0 | L16: 0 | M16: 0 | N16: 14 | O16: COIN FLIP: take last, no edge
A18: How to read: assumes the field strips each category in order of 2027 EV at the pace it did in the 2025 draft (keeper round + snake). 'EV left @Rk' = best player still there after the 2026-style number of teams are gone by round k.
A19: Free until round = last round where the best player left is within 1 pt of the best on the board. WAIT = the field leaves the category alone; TAKE EARLY = it strips it fast.
A20: 2026 payoff: projected final = current points + projected remaining (MLS / NASCAR / MLB bonuses are not realised yet). Surplus = projected final minus the average pick in that round.
A21: Caveats: Country's 2026 surplus is the Olympics/World Cup bonus (13 pts) which does not exist in 2027. Musician surplus is the Feb-2026 Grammy bonus (repeats in Feb 2027). Per-pick surplus is mostly luck; category averages are the signal.
A22: The field does not draft by my EV order (it overweights Grammy/Oscar names), so Musician/Actor/Actress availability is approximate. Keepers may change who is already gone before round 1.

Sheet Draft Board
A1: Rank | B1: Category | C1: Candidate | D1: Owned by | E1: E[total] | F1: VOR | G1: Risk-adj VOR | H1: Tier in category | I1: Odds / price | J1: Detail | K1: Conf | L1: Source | M1: As of | N1: Plan | O1: Conf-adj VOR
A2: 1 | B2: Musician | C2: Ella Langley | D2: — free | E2: ='Musician'!M5 | F2: ='Musician'!N5 | G2: ='Musician'!O5 | H2: 1 | I2: Grammy EV 10.8 (raw 12.8, P(cap) 50%) | J2: 2026 raw 128; charting now: Choosin' Texas (#2); Be Her (#13); Loving Life Again (#16); carry-over 9.0 + new hits 8.9 (lambda 1.10, P(~0) 12%) | K2: C | L2: 2027 Hot 100 baseline = my estimate; Grammy: Kalshi KXGRAM*-69 prices (A) + estimates for other categories (C) | M2: 2026-10-08 | N2: Good but the field reaches for it: let it come to you | O2: ='Musician'!Y5
A3: 2 | B3: NBA | C3: Oklahoma City Thunder | D3: Feder | E3: ='NBA'!M5 | F3: ='NBA'!N5 | G3: ='NBA'!O5 | H3: 1 | I3: Kalshi 21.5% | J3: West; win total 62.5 | K3: A | L3: KXNBA-27 exchange mid-price, pulled 2026-10-08; p(final)=KXNBAEAST/KXNBAWEST-27 Kalshi mid | league_sim.py: full-schedule + real playoff bracket Monte Carlo, ratings fitted to Kalshi | M3: 2026-10-08 | O3: ='NBA'!Y5
A4: 3 | B4: NFL | C4: San Francisco 49ers | D4: Todd | E4: ='NFL'!M5 | F4: ='NFL'!N5 | G4: ='NFL'!O5 | H4: 1 | I4: Kalshi 9.5% | J4: 4-0, NFC West | K4: A | L4: KXSB-27 exchange mid-price, pulled 2026-10-08; p(final)=KXNFLAFCCHAMP/KXNFLNFCCHAMP-27 Kalshi mid | league_sim.py: full-schedule + real playoff bracket Monte Carlo, ratings fitted to Kalshi | M4: 2026-10-08 | O4: ='NFL'!Y5
A5: 4 | B5: NASCAR | C5: Kyle Larson | D5: Molmen | E5: ='NASCAR'!M5 | F5: ='NASCAR'!N5 | G5: ='NASCAR'!O5 | H5: 1 | I5: 2026 title: Kalshi 42.0% | J5: 2,318 pts, leads Chase after Las Vegas | K5: C | L5: User-supplied final Cup standings 2021-2026(proj.), recency-weighted (decay 0.65/yr, nascar_model.py) for drivers in the table; others = field prior blended with 2026 Kalshi title price (shrunk). No 2027 market exists. | M5: 2026-10-08 | N5: low confidence: far-out event | O5: ='NASCAR'!Y5
A6: 5 | B6: Musician | C6: Olivia Rodrigo | D6: Todd | E6: ='Musician'!M6 | F6: ='Musician'!N6 | G6: ='Musician'!O6 | H6: 1 | I6: Grammy EV 9.4 (raw 10.3, P(cap) 31%) | J6: 2026 raw 17; charting now: Drop Dead (#23); The Cure (#22); Stupid Song (#8); carry-over 6.1 + new hits 8.9 (lambda 1.10, P(~0) 17%) | K6: C | L6: 2027 Hot 100 baseline = my estimate; Grammy: Kalshi KXGRAM*-69 prices (A) + estimates for other categories (C) | M6: 2026-10-08 | N6: Good but the field reaches for it: let it come to you | O6: ='Musician'!Y6
A7: 6 | B7: NBA | C7: San Antonio Spurs | D7: Wu | E7: ='NBA'!M6 | F7: ='NBA'!N6 | G7: ='NBA'!O6 | H7: 1 | I7: Kalshi 21.5% | J7: West; win total 59.5 | K7: A | L7: KXNBA-27 exchange mid-price, pulled 2026-10-08; p(final)=KXNBAEAST/KXNBAWEST-27 Kalshi mid | league_sim.py: full-schedule + real playoff bracket Monte Carlo, ratings fitted to Kalshi | M7: 2026-10-08 | O7: ='NBA'!Y6
A8: 7 | B8: NCAAF | C8: Georgia | D8: Theo | E8: ='NCAAF'!M5 | F8: ='NCAAF'!N5 | G8: ='NCAAF'!O5 | H8: 1 | I8: Kalshi 16.5% | J8: AP #2, 5-0, SEC | K8: A | L8: KXNCAAF-27 exchange mid-price, pulled 2026-10-22 | M8: 2026-10-22 | O8: ='NCAAF'!Y5
A9: 8 | B9: NCAAB | C9: Florida | D9: Wu | E9: ='NCAAB'!M5 | F9: ='NCAAB'!N5 | G9: ='NCAAB'!O5 | H9: 1 | I9: +600 | K9: B | L9: CBS Sports title odds 2026-08-04 | M9: 2026-10-08 | N9: low confidence: far-out event | O9: ='NCAAB'!Y5
A10: 9 | B10: NCAAF | C10: Notre Dame | D10: Feder | E10: ='NCAAF'!M6 | F10: ='NCAAF'!N6 | G10: ='NCAAF'!O6 | H10: 1 | I10: Kalshi 12.5% | J10: AP #3, 5-0, Ind | K10: A | L10: KXNCAAF-27 exchange mid-price, pulled 2026-10-22 | M10: 2026-10-22 | O10: ='NCAAF'!Y6
A11: 10 | B11: NCAAF | C11: Miami (FL) | D11: Wu | E11: ='NCAAF'!M7 | F11: ='NCAAF'!N7 | G11: ='NCAAF'!O7 | H11: 1 | I11: Kalshi 14.5% | J11: AP #4, 5-0, ACC | K11: A | L11: KXNCAAF-27 exchange mid-price, pulled 2026-10-22 | M11: 2026-10-22 | O11: ='NCAAF'!Y7
A12: 11 | B12: NASCAR | C12: Denny Hamlin | D12: Theo | E12: ='NASCAR'!M6 | F12: ='NASCAR'!N6 | G12: ='NASCAR'!O6 | H12: 1 | I12: 2026 title: Kalshi 28.0% | J12: 2,278 pts (2nd) | K12: C | L12: User-supplied final Cup standings 2021-2026(proj.), recency-weighted (decay 0.65/yr, nascar_model.py) for drivers in the table; others = field prior blended with 2026 Kalshi title price (shrunk). No 2027 market exists. | M12: 2026-10-08 | N12: low confidence: far-out event | O12: ='NASCAR'!Y6
A13: 12 | B13: NCAAB | C13: Duke | D13: Jens | E13: ='NCAAB'!M6 | F13: ='NCAAB'!N6 | G13: ='NCAAB'!O6 | H13: 1 | I13: +600 | K13: B | L13: CBS Sports title odds 2026-08-04 | M13: 2026-10-08 | N13: low confidence: far-out event | O13: ='NCAAB'!Y6
A14: 13 | B14: NCAAF | C14: Ohio State | D14: Mitchell | E14: ='NCAAF'!M8 | F14: ='NCAAF'!N8 | G14: ='NCAAF'!O8 | H14: 2 | I14: Kalshi 12.5% | J14: AP #5, 4-1, Big Ten | K14: A | L14: KXNCAAF-27 exchange mid-price, pulled 2026-10-22 | M14: 2026-10-22 | O14: ='NCAAF'!Y8
A15: 14 | B15: Musician | C15: Olivia Dean | D15: — free | E15: ='Musician'!M7 | F15: ='Musician'!N7 | G15: ='Musician'!O7 | H15: 1 | I15: Grammy EV 8.5 (raw 9.2, P(cap) 23%) | J15: 2026 raw 61; charting now: none charting; carry-over 0.0 + new hits 9.0 (lambda 1.10, P(~0) 33%) | K15: C | L15: 2027 Hot 100 baseline = my estimate; Grammy: Kalshi KXGRAM*-69 prices (A) + estimates for other categories (C) | M15: 2026-10-08 | N15: Good but the field reaches for it: let it come to you | O15: ='Musician'!Y7
A16: 15 | B16: Country | C16: Iraq | D16: — free | E16: ='Country'!M5 | F16: ='Country'!N5 | G16: ='Country'!O5 | H16: 1 | I16: IMF Oct-2026 2027: 19.0% | J16: IMF Oct-2026: 2025 -0.414, 2026 -16.02, 2027 18.986 | war/rebound path: very wide forecast error | K16: A | L16: IMF World Economic Outlook, October 2026 (published 2026-10-13), api.imf.org SDMX dataflow IMF.RES/WEO NGDP_RPCH, pulled via Actions runner | M16: 2026-10-13 | O16: ='Country'!Y5
A17: 16 | B17: NFL | C17: Kansas City Chiefs | D17: Shep | E17: ='NFL'!M6 | F17: ='NFL'!N6 | G17: ='NFL'!O6 | H17: 1 | I17: Kalshi 9.5% | J17: 4-0, AFC West | K17: A | L17: KXSB-27 exchange mid-price, pulled 2026-10-08; p(final)=KXNFLAFCCHAMP/KXNFLNFCCHAMP-27 Kalshi mid | league_sim.py: full-schedule + real playoff bracket Monte Carlo, ratings fitted to Kalshi | M17: 2026-10-08 | O17: ='NFL'!Y6
A18: 17 | B18: Country | C18: Qatar | D18: — free | E18: ='Country'!M6 | F18: ='Country'!N6 | G18: ='Country'!O6 | H18: 1 | I18: IMF Oct-2026 2027: 18.8% | J18: IMF Oct-2026: 2025 1.808, 2026 -15.583, 2027 18.755 | war/rebound path: very wide forecast error | K18: A | L18: IMF World Economic Outlook, October 2026 (published 2026-10-13), api.imf.org SDMX dataflow IMF.RES/WEO NGDP_RPCH, pulled via Actions runner | M18: 2026-10-13 | O18: ='Country'!Y6
A19: 18 | B19: Actress | C19: Julianne Moore | D19: — free | E19: ='Actress'!M5 | F19: ='Actress'!N5 | G19: ='Actress'!O5 | H19: 1 | J19: no 2027 film found in Wikipedia's cast lists | K19: C | L19: Wikipedia 'List of American films of 2027' casts (Actions-runner pull 2026-10-08) x comp-based box office/RT estimates; cast lists are billed leads only (cameos not captured) | M19: 2026-10-08 | N19: Good but the field reaches for it: let it come to you | O19: ='Actress'!Y5
A20: 19 | B20: Tennis | C20: Jannik Sinner | D20: Buckley | E20: ='Tennis'!M5 | F20: ='Tennis'!N5 | G20: ='Tennis'!O5 | H20: 1 | I20: +100 AO 2027 (pre-injury) | J20: ATP 1 (2026-10-08) | K20: B | L20: ATP rank from league standings pull (A) / WTA via Olympics.com Oct 5; AO odds VegasInsider/Johnnybet Oct 2026; probabilities = agent estimates | M20: 2026-10-08 | O20: ='Tennis'!Y5
A21: 20 | B21: Musician | C21: Bruno Mars | D21: — free | E21: ='Musician'!M8 | F21: ='Musician'!N8 | G21: ='Musician'!O8 | H21: 2 | I21: Grammy EV 7.0 (raw 7.3, P(cap) 11%) | J21: 2026 raw 34; charting now: I Just Might (#11); Risk It All (#14); carry-over 2.9 + new hits 8.9 (lambda 1.10, P(~0) 24%) | K21: C | L21: 2027 Hot 100 baseline = my estimate; Grammy: Kalshi KXGRAM*-69 prices (A) + estimates for other categories (C) | M21: 2026-10-08 | N21: Good but the field reaches for it: let it come to you | O21: ='Musician'!Y8
A22: 21 | B22: Musician | C22: Taylor Swift | D22: Molmen | E22: ='Musician'!M9 | F22: ='Musician'!N9 | G22: ='Musician'!O9 | H22: 2 | I22: Grammy EV 7.4 (raw 7.7, P(cap) 13%) | J22: 2026 raw 61; charting now: Patient Zero (#1); carry-over 1.6 + new hits 8.8 (lambda 1.10, P(~0) 27%) | K22: C | L22: 2027 Hot 100 baseline = my estimate; Grammy: Kalshi KXGRAM*-69 prices (A) + estimates for other categories (C) | M22: 2026-10-08 | N22: Good but the field reaches for it: let it come to you | O22: ='Musician'!Y9
A23: 22 | B23: Country | C23: Guyana | D23: Korch | E23: ='Country'!M7 | F23: ='Country'!N7 | G23: ='Country'!O7 | H23: 1 | I23: IMF Oct-2026 2027: 16.8% | J23: IMF Oct-2026: 2025 19.31, 2026 22.325, 2027 16.789 | commodity-driven: wide forecast error | K23: A | L23: IMF World Economic Outlook, October 2026 (published 2026-10-13), api.imf.org SDMX dataflow IMF.RES/WEO NGDP_RPCH, pulled via Actions runner | M23: 2026-10-13 | O23: ='Country'!Y7
A24: 23 | B24: NFL | C24: Buffalo Bills | D24: Jens | E24: ='NFL'!M7 | F24: ='NFL'!N7 | G24: ='NFL'!O7 | H24: 1 | I24: Kalshi 10.5% | J24: 3-1, AFC East | K24: A | L24: KXSB-27 exchange mid-price, pulled 2026-10-08; p(final)=KXNFLAFCCHAMP/KXNFLNFCCHAMP-27 Kalshi mid | league_sim.py: full-schedule + real playoff bracket Monte Carlo, ratings fitted to Kalshi | M24: 2026-10-08 | O24: ='NFL'!Y7
A25: 24 | B25: NASCAR | C25: Christopher Bell | D25: Wu | E25: ='NASCAR'!M7 | F25: ='NASCAR'!N7 | G25: ='NASCAR'!O7 | H25: 1 | I25: 2026 title: Kalshi 10.5% | J25: 2,263 pts (3rd) | K25: C | L25: User-supplied final Cup standings 2021-2026(proj.), recency-weighted (decay 0.65/yr, nascar_model.py) for drivers in the table; others = field prior blended with 2026 Kalshi title price (shrunk). No 2027 market exists. | M25: 2026-10-08 | N25: low confidence: far-out event | O25: ='NASCAR'!Y7
A26: 25 | B26: NHL | C26: Carolina Hurricanes | D26: Jamzee | E26: ='NHL'!M5 | F26: ='NHL'!N5 | G26: ='NHL'!O5 | H26: 1 | I26: Kalshi 9.5% | J26: East | K26: A | L26: KXNHL-27 exchange mid-price, pulled 2026-10-08; p(final)=KXNHLEAST/KXNHLWEST-27 Kalshi mid | league_sim.py: full-schedule + real playoff bracket Monte Carlo, ratings fitted to Kalshi | M26: 2026-10-08 | O26: ='NHL'!Y5
A27: 26 | B27: Country | C27: Kuwait | D27: — free | E27: ='Country'!M8 | F27: ='Country'!N8 | G27: ='Country'!O8 | H27: 2 | I27: IMF Oct-2026 2027: 17.1% | J27: IMF Oct-2026: 2025 2.732, 2026 -16.74, 2027 17.125 | war/rebound path: very wide forecast error | K27: A | L27: IMF World Economic Outlook, October 2026 (published 2026-10-13), api.imf.org SDMX dataflow IMF.RES/WEO NGDP_RPCH, pulled via Actions runner | M27: 2026-10-13 | O27: ='Country'!Y8
A28: 27 | B28: NBA | C28: Philadelphia 76ers | D28: — free | E28: ='NBA'!M7 | F28: ='NBA'!N7 | G28: ='NBA'!O7 | H28: 1 | I28: Kalshi 12.5% | J28: East; win total 50.5 | K28: A | L28: KXNBA-27 exchange mid-price, pulled 2026-10-08; p(final)=KXNBAEAST/KXNBAWEST-27 Kalshi mid | league_sim.py: full-schedule + real playoff bracket Monte Carlo, ratings fitted to Kalshi | M28: 2026-10-08 | O28: ='NBA'!Y7
A29: 28 | B29: Tennis | C29: Elena Rybakina | D29: — free | E29: ='Tennis'!M6 | F29: ='Tennis'!N6 | G29: ='Tennis'!O6 | H29: 1 | I29: +300 AO 2027 | J29: WTA 1 (2026-10-08) | K29: B | L29: ATP rank from league standings pull (A) / WTA via Olympics.com Oct 5; AO odds VegasInsider/Johnnybet Oct 2026; probabilities = agent estimates | M29: 2026-10-08 | O29: ='Tennis'!Y6
A30: 29 | B30: NBA | C30: New York Knicks | D30: Buckley | E30: ='NBA'!M8 | F30: ='NBA'!N8 | G30: ='NBA'!O8 | H30: 2 | I30: Kalshi 8.5% | J30: East; win total 52.5 | K30: A | L30: KXNBA-27 exchange mid-price, pulled 2026-10-08; p(final)=KXNBAEAST/KXNBAWEST-27 Kalshi mid | league_sim.py: full-schedule + real playoff bracket Monte Carlo, ratings fitted to Kalshi | M30: 2026-10-08 | O30: ='NBA'!Y8
A31: 30 | B31: NHL | C31: Tampa Bay Lightning | D31: Fryar | E31: ='NHL'!M6 | F31: ='NHL'!N6 | G31: ='NHL'!O6 | H31: 1 | I31: Kalshi 5.5% | J31: East | K31: A | L31: KXNHL-27 exchange mid-price, pulled 2026-10-08; p(final)=KXNHLEAST/KXNHLWEST-27 Kalshi mid | league_sim.py: full-schedule + real playoff bracket Monte Carlo, ratings fitted to Kalshi | M31: 2026-10-08 | O31: ='NHL'!Y6
A32: 31 | B32: Tennis | C32: Aryna Sabalenka | D32: Fryar | E32: ='Tennis'!M7 | F32: ='Tennis'!N7 | G32: ='Tennis'!O7 | H32: 1 | I32: +175 to +185 AO 2027 | J32: WTA 2 (2026-10-08) | K32: B | L32: ATP rank from league standings pull (A) / WTA via Olympics.com Oct 5; AO odds VegasInsider/Johnnybet Oct 2026; probabilities = agent estimates | M32: 2026-10-08 | O32: ='Tennis'!Y7
A33: 32 | B33: Tennis | C33: Carlos Alcaraz | D33: Todd | E33: ='Tennis'!M8 | F33: ='Tennis'!N8 | G33: ='Tennis'!O8 | H33: 2 | I33: +150 AO 2027 | J33: ATP 3 (2026-10-08) | K33: B | L33: ATP rank from league standings pull (A) / WTA via Olympics.com Oct 5; AO odds VegasInsider/Johnnybet Oct 2026; probabilities = agent estimates | M33: 2026-10-08 | O33: ='Tennis'!Y8
A34: 33 | B34: Golf | C34: Scottie Scheffler | D34: Wu | E34: ='Golf'!M5 | F34: ='Golf'!N5 | G34: ='Golf'!O5 | H34: 1 | J34: OWGR 1 (2026-10-08) | K34: C | L34: OWGR rank from league standings pull (A); major-win probabilities = model (rank-weighted share of 4 majors) | M34: 2026-10-08 | O34: ='Golf'!Y5
A35: 34 | B35: NASCAR | C35: Joey Logano | D35: Jamzee | E35: ='NASCAR'!M8 | F35: ='NASCAR'!N8 | G35: ='NASCAR'!O8 | H35: 2 | I35: 2026 title: Kalshi 5.5% | J35: 2,247 pts (4th) | K35: C | L35: User-supplied final Cup standings 2021-2026(proj.), recency-weighted (decay 0.65/yr, nascar_model.py) for drivers in the table; others = field prior blended with 2026 Kalshi title price (shrunk). No 2027 market exists. | M35: 2026-10-08 | N35: low confidence: far-out event | O35: ='NASCAR'!Y8
A36: 35 | B36: NHL | C36: Edmonton Oilers | D36: Buckley | E36: ='NHL'!M7 | F36: ='NHL'!N7 | G36: ='NHL'!O7 | H36: 1 | I36: Kalshi 8.5% | J36: West | K36: A | L36: KXNHL-27 exchange mid-price, pulled 2026-10-08; p(final)=KXNHLEAST/KXNHLWEST-27 Kalshi mid | league_sim.py: full-schedule + real playoff bracket Monte Carlo, ratings fitted to Kalshi | M36: 2026-10-08 | O36: ='NHL'!Y7
A37: 36 | B37: Tennis | C37: Alexander Zverev | D37: Theo | E37: ='Tennis'!M9 | F37: ='Tennis'!N9 | G37: ='Tennis'!O9 | H37: 2 | I37: +700 AO 2027 | J37: ATP 2 (2026-10-08) | K37: B | L37: ATP rank from league standings pull (A) / WTA via Olympics.com Oct 5; AO odds VegasInsider/Johnnybet Oct 2026; probabilities = agent estimates | M37: 2026-10-08 | O37: ='Tennis'!Y9
A38: 37 | B38: NASCAR | C38: Ryan Blaney | D38: Fryar | E38: ='NASCAR'!M9 | F38: ='NASCAR'!N9 | G38: ='NASCAR'!O9 | H38: 2 | I38: 2026 title: Kalshi 5.5% | J38: 2,238 pts (5th) | K38: C | L38: User-supplied final Cup standings 2021-2026(proj.), recency-weighted (decay 0.65/yr, nascar_model.py) for drivers in the table; others = field prior blended with 2026 Kalshi title price (shrunk). No 2027 market exists. | M38: 2026-10-08 | N38: low confidence: far-out event | O38: ='NASCAR'!Y9
A39: 38 | B39: MLB | C39: Los Angeles Dodgers | D39: Wu | E39: ='MLB'!M5 | F39: ='MLB'!N5 | G39: ='MLB'!O5 | H39: 1 | J39: 2026: 100-62 (.6173) | K39: C | L39: 2026 win% from league standings (A); title prob = model estimate — no 2027 World Series odds posted | M39: 2026-10-08 | N39: low confidence: far-out event | O39: ='MLB'!Y5
A40: 39 | B40: Golf | C40: Rory McIlroy | D40: Molmen | E40: ='Golf'!M6 | F40: ='Golf'!N6 | G40: ='Golf'!O6 | H40: 1 | J40: OWGR 2 (2026-10-08) | K40: C | L40: OWGR rank from league standings pull (A); major-win probabilities = model (rank-weighted share of 4 majors) | M40: 2026-10-08 | O40: ='Golf'!Y6
A41: 40 | B41: Country | C41: Sudan | D41: — free | E41: ='Country'!M9 | F41: ='Country'!N9 | G41: ='Country'!O9 | H41: 2 | I41: IMF Oct-2026 2027: 15.0% | J41: IMF Oct-2026: 2025 n/a, 2026 7.0, 2027 15.0 | war/rebound path: very wide forecast error | K41: A | L41: IMF World Economic Outlook, October 2026 (published 2026-10-13), api.imf.org SDMX dataflow IMF.RES/WEO NGDP_RPCH, pulled via Actions runner | M41: 2026-10-13 | O41: ='Country'!Y9
A42: 41 | B42: Country | C42: Bahrain | D42: — free | E42: ='Country'!M10 | F42: ='Country'!N10 | G42: ='Country'!O10 | H42: 2 | I42: IMF Oct-2026 2027: 13.9% | J42: IMF Oct-2026: 2025 3.481, 2026 -11.262, 2027 13.941 | war/rebound path: very wide forecast error | K42: A | L42: IMF World Economic Outlook, October 2026 (published 2026-10-13), api.imf.org SDMX dataflow IMF.RES/WEO NGDP_RPCH, pulled via Actions runner | M42: 2026-10-13 | O42: ='Country'!Y10
A43: 42 | B43: NFL | C43: Minnesota Vikings | D43: — free | E43: ='NFL'!M8 | F43: ='NFL'!N8 | G43: ='NFL'!O8 | H43: 2 | I43: Kalshi 3.5% | J43: 4-0, NFC North | K43: A | L43: KXSB-27 exchange mid-price, pulled 2026-10-08; p(final)=KXNFLAFCCHAMP/KXNFLNFCCHAMP-27 Kalshi mid | league_sim.py: full-schedule + real playoff bracket Monte Carlo, ratings fitted to Kalshi | M43: 2026-10-08 | O43: ='NFL'!Y8
A44: 43 | B44: NHL | C44: Colorado Avalanche | D44: Korch | E44: ='NHL'!M8 | F44: ='NHL'!N8 | G44: ='NHL'!O8 | H44: 2 | I44: Kalshi 12.5% | J44: West | K44: A | L44: KXNHL-27 exchange mid-price, pulled 2026-10-08; p(final)=KXNHLEAST/KXNHLWEST-27 Kalshi mid | league_sim.py: full-schedule + real playoff bracket Monte Carlo, ratings fitted to Kalshi | M44: 2026-10-08 | O44: ='NHL'!Y8
A45: 44 | B45: NCAAB | C45: UConn | D45: Fryar | E45: ='NCAAB'!M7 | F45: ='NCAAB'!N7 | G45: ='NCAAB'!O7 | H45: 1 | I45: +1300 | K45: B | L45: CBS Sports title odds 2026-08-04 | M45: 2026-10-08 | N45: low confidence: far-out event | O45: ='NCAAB'!Y7
A46: 45 | B46: NCAAB | C46: Illinois | D46: — free | E46: ='NCAAB'!M8 | F46: ='NCAAB'!N8 | G46: ='NCAAB'!O8 | H46: 2 | I46: +1300 | K46: B | L46: CBS Sports title odds 2026-08-04 | M46: 2026-10-08 | N46: low confidence: far-out event | O46: ='NCAAB'!Y8
A47: 46 | B47: NBA | C47: Minnesota Timberwolves | D47: Todd | E47: ='NBA'!M9 | F47: ='NBA'!N9 | G47: ='NBA'!O9 | H47: 2 | I47: Kalshi 6.5% | J47: West; win total 48.5 | K47: A | L47: KXNBA-27 exchange mid-price, pulled 2026-10-08; p(final)=KXNBAEAST/KXNBAWEST-27 Kalshi mid | league_sim.py: full-schedule + real playoff bracket Monte Carlo, ratings fitted to Kalshi | M47: 2026-10-08 | O47: ='NBA'!Y9
A48: 47 | B48: NCAAF | C48: Texas | D48: — free | E48: ='NCAAF'!M9 | F48: ='NCAAF'!N9 | G48: ='NCAAF'!O9 | H48: 2 | I48: Kalshi 3.5% | J48: AP #1, 4-0, SEC | K48: A | L48: KXNCAAF-27 exchange mid-price, pulled 2026-10-22 | M48: 2026-10-22 | O48: ='NCAAF'!Y9
A49: 48 | B49: NBA | C49: Boston Celtics | D49: Shep | E49: ='NBA'!M10 | F49: ='NBA'!N10 | G49: ='NBA'!O10 | H49: 2 | I49: Kalshi 4.5% | J49: East; win total 51.5 | K49: A | L49: KXNBA-27 exchange mid-price, pulled 2026-10-08; p(final)=KXNBAEAST/KXNBAWEST-27 Kalshi mid | league_sim.py: full-schedule + real playoff bracket Monte Carlo, ratings fitted to Kalshi | M49: 2026-10-08 | O49: ='NBA'!Y10
A50: 49 | B50: Golf | C50: Matt Fitzpatrick | D50: — free | E50: ='Golf'!M7 | F50: ='Golf'!N7 | G50: ='Golf'!O7 | H50: 1 | J50: OWGR 3 (2026-10-08) | K50: C | L50: OWGR rank from league standings pull (A); major-win probabilities = model (rank-weighted share of 4 majors) | M50: 2026-10-08 | O50: ='Golf'!Y7
A51: 50 | B51: NCAAF | C51: Indiana | D51: Korch | E51: ='NCAAF'!M10 | F51: ='NCAAF'!N10 | G51: ='NCAAF'!O10 | H51: 2 | I51: Kalshi 7.5% | J51: AP #7, 5-0, Big Ten | K51: A | L51: KXNCAAF-27 exchange mid-price, pulled 2026-10-22 | M51: 2026-10-22 | O51: ='NCAAF'!Y10
A52: 51 | B52: MLS | C52: Nashville SC | D52: — free | E52: ='MLS'!M5 | F52: ='MLS'!N5 | G52: ='MLS'!O5 | H52: 1 | I52: 2026 Cup: Kalshi 18.0% | J52: 2026: 60 pts (as of 10-08; season ends Nov 7) | K52: C | L52: 2026 points (league standings, A) + Kalshi KXMLSCUP-26 price as strength proxy, shrunk 50% toward the field | M52: 2026-10-08 | N52: low confidence: far-out event | O52: ='MLS'!Y5
A53: 52 | B53: MLS | C53: Vancouver Whitecaps FC | D53: Feder | E53: ='MLS'!M6 | F53: ='MLS'!N6 | G53: ='MLS'!O6 | H53: 1 | I53: 2026 Cup: Kalshi 23.5% | J53: 2026: 50 pts (as of 10-08; season ends Nov 7) | K53: C | L53: 2026 points (league standings, A) + Kalshi KXMLSCUP-26 price as strength proxy, shrunk 50% toward the field | M53: 2026-10-08 | N53: low confidence: far-out event | O53: ='MLS'!Y6
A54: 53 | B54: NHL | C54: Florida Panthers | D54: Todd | E54: ='NHL'!M9 | F54: ='NHL'!N9 | G54: ='NHL'!O9 | H54: 2 | I54: Kalshi 10.5% | J54: East | K54: A | L54: KXNHL-27 exchange mid-price, pulled 2026-10-08; p(final)=KXNHLEAST/KXNHLWEST-27 Kalshi mid | league_sim.py: full-schedule + real playoff bracket Monte Carlo, ratings fitted to Kalshi | M54: 2026-10-08 | O54: ='NHL'!Y9
A55: 54 | B55: Actress | C55: Kristen Bell | D55: — free | E55: ='Actress'!M6 | F55: ='Actress'!N6 | G55: ='Actress'!O6 | H55: 1 | J55: Frozen 3 (Nov 24); Sonic the Hedgehog 4 (Mar 19) | K55: C | L55: Wikipedia 'List of American films of 2027' casts (Actions-runner pull 2026-10-08) x comp-based box office/RT estimates; cast lists are billed leads only (cameos not captured) | M55: 2026-10-08 | N55: Good but the field reaches for it: let it come to you | O55: ='Actress'!Y6
A56: 55 | B56: NASCAR | C56: William Byron | D56: Korch | E56: ='NASCAR'!M10 | F56: ='NASCAR'!N10 | G56: ='NASCAR'!O10 | H56: 2 | I56: 2026 title: Kalshi 0.5% | J56: 2026 Cup Series | K56: C | L56: User-supplied final Cup standings 2021-2026(proj.), recency-weighted (decay 0.65/yr, nascar_model.py) for drivers in the table; others = field prior blended with 2026 Kalshi title price (shrunk). No 2027 market exists. | M56: 2026-10-08 | N56: low confidence: far-out event | O56: ='NASCAR'!Y10
A57: 56 | B57: MLB | C57: Milwaukee Brewers | D57: Buckley | E57: ='MLB'!M6 | F57: ='MLB'!N6 | G57: ='MLB'!O6 | H57: 1 | J57: 2026: 103-59 (.6358) | K57: C | L57: 2026 win% from league standings (A); title prob = model estimate — no 2027 World Series odds posted | M57: 2026-10-08 | N57: low confidence: far-out event | O57: ='MLB'!Y6
A58: 57 | B58: NFL | C58: Baltimore Ravens | D58: Wu | E58: ='NFL'!M9 | F58: ='NFL'!N9 | G58: ='NFL'!O9 | H58: 2 | I58: Kalshi 7.5% | J58: 3-1, AFC North | K58: A | L58: KXSB-27 exchange mid-price, pulled 2026-10-08; p(final)=KXNFLAFCCHAMP/KXNFLNFCCHAMP-27 Kalshi mid | league_sim.py: full-schedule + real playoff bracket Monte Carlo, ratings fitted to Kalshi | M58: 2026-10-08 | O58: ='NFL'!Y9
A59: 58 | B59: NCAAB | C59: Michigan | D59: Jamzee | E59: ='NCAAB'!M9 | F59: ='NCAAB'!N9 | G59: ='NCAAB'!O9 | H59: 2 | I59: +1600 | K59: B | L59: CBS Sports title odds 2026-08-04 | M59: 2026-10-08 | N59: low confidence: far-out event | O59: ='NCAAB'!Y9
A60: 59 | B60: Golf | C60: Cameron Young | D60: — free | E60: ='Golf'!M8 | F60: ='Golf'!N8 | G60: ='Golf'!O8 | H60: 2 | J60: OWGR 4 (2026-10-08) | K60: C | L60: OWGR rank from league standings pull (A); major-win probabilities = model (rank-weighted share of 4 majors) | M60: 2026-10-08 | O60: ='Golf'!Y8
A61: 60 | B61: NFL | C61: Jacksonville Jaguars | D61: — free | E61: ='NFL'!M10 | F61: ='NFL'!N10 | G61: ='NFL'!O10 | H61: 2 | I61: Kalshi 6.5% | J61: 3-1, AFC South | K61: A | L61: KXSB-27 exchange mid-price, pulled 2026-10-08; p(final)=KXNFLAFCCHAMP/KXNFLNFCCHAMP-27 Kalshi mid | league_sim.py: full-schedule + real playoff bracket Monte Carlo, ratings fitted to Kalshi | M61: 2026-10-08 | O61: ='NFL'!Y10
A62: 61 | B62: MLB | C62: New York Yankees | D62: Jens | E62: ='MLB'!M7 | F62: ='MLB'!N7 | G62: ='MLB'!O7 | H62: 1 | J62: 2026: 94-68 (.5776) | K62: C | L62: 2026 win% from league standings (A); title prob = model estimate — no 2027 World Series odds posted | M62: 2026-10-08 | N62: low confidence: far-out event | O62: ='MLB'!Y7
A63: 62 | B63: MLS | C63: Inter Miami CF | D63: Theo | E63: ='MLS'!M7 | F63: ='MLS'!N7 | G63: ='MLS'!O7 | H63: 1 | I63: 2026 Cup: Kalshi 16.5% | J63: 2026: 46 pts (as of 10-08; season ends Nov 7) | K63: C | L63: 2026 points (league standings, A) + Kalshi KXMLSCUP-26 price as strength proxy, shrunk 50% toward the field | M63: 2026-10-08 | N63: low confidence: far-out event | O63: ='MLS'!Y7
A64: 63 | B64: NHL | C64: Vegas Golden Knights | D64: Tim | E64: ='NHL'!M10 | F64: ='NHL'!N10 | G64: ='NHL'!O10 | H64: 2 | I64: Kalshi 7.5% | J64: West | K64: A | L64: KXNHL-27 exchange mid-price, pulled 2026-10-08; p(final)=KXNHLEAST/KXNHLWEST-27 Kalshi mid | league_sim.py: full-schedule + real playoff bracket Monte Carlo, ratings fitted to Kalshi | M64: 2026-10-08 | O64: ='NHL'!Y10
A65: 64 | B65: Golf | C65: Wyndham Clark | D65: — free | E65: ='Golf'!M9 | F65: ='Golf'!N9 | G65: ='Golf'!O9 | H65: 2 | J65: OWGR 5 (2026-10-08) | K65: C | L65: OWGR rank from league standings pull (A); major-win probabilities = model (rank-weighted share of 4 majors) | M65: 2026-10-08 | O65: ='Golf'!Y9
A66: 65 | B66: NFL | C66: Chicago Bears | D66: — free | E66: ='NFL'!M11 | F66: ='NFL'!N11 | G66: ='NFL'!O11 | H66: 2 | I66: Kalshi 4.5% | J66: 3-1, NFC North | K66: A | L66: KXSB-27 exchange mid-price, pulled 2026-10-08; p(final)=KXNFLAFCCHAMP/KXNFLNFCCHAMP-27 Kalshi mid | league_sim.py: full-schedule + real playoff bracket Monte Carlo, ratings fitted to Kalshi | M66: 2026-10-08 | O66: ='NFL'!Y11
A67: 66 | B67: NBA | C67: Toronto Raptors | D67: — free | E67: ='NBA'!M11 | F67: ='NBA'!N11 | G67: ='NBA'!O11 | H67: 2 | I67: Kalshi 2.5% | J67: East; win total 45.5 | K67: A | L67: KXNBA-27 exchange mid-price, pulled 2026-10-08; p(final)=KXNBAEAST/KXNBAWEST-27 Kalshi mid | league_sim.py: full-schedule + real playoff bracket Monte Carlo, ratings fitted to Kalshi | M67: 2026-10-08 | O67: ='NBA'!Y11
A68: 67 | B68: NHL | C68: Minnesota Wild | D68: — free | E68: ='NHL'!M11 | F68: ='NHL'!N11 | G68: ='NHL'!O11 | H68: 2 | I68: Kalshi 6.5% | J68: West | K68: A | L68: KXNHL-27 exchange mid-price, pulled 2026-10-08; p(final)=KXNHLEAST/KXNHLWEST-27 Kalshi mid | league_sim.py: full-schedule + real playoff bracket Monte Carlo, ratings fitted to Kalshi | M68: 2026-10-08 | O68: ='NHL'!Y11
A69: 68 | B69: NCAAF | C69: Alabama | D69: Jamzee | E69: ='NCAAF'!M11 | F69: ='NCAAF'!N11 | G69: ='NCAAF'!O11 | H69: 2 | I69: Kalshi 4.5% | J69: AP #6, 5-0, SEC | K69: A | L69: KXNCAAF-27 exchange mid-price, pulled 2026-10-22 | M69: 2026-10-22 | O69: ='NCAAF'!Y11
A70: 69 | B70: Country | C70: Uganda | D70: — free | E70: ='Country'!M11 | F70: ='Country'!N11 | G70: ='Country'!O11 | H70: 2 | I70: IMF Oct-2026 2027: 9.9% | J70: IMF Oct-2026: 2025 6.695, 2026 6.164, 2027 9.86 | K70: A | L70: IMF World Economic Outlook, October 2026 (published 2026-10-13), api.imf.org SDMX dataflow IMF.RES/WEO NGDP_RPCH, pulled via Actions runner | M70: 2026-10-13 | O70: ='Country'!Y11
A71: 70 | B71: NCAAB | C71: Michigan State | D71: — free | E71: ='NCAAB'!M10 | F71: ='NCAAB'!N10 | G71: ='NCAAB'!O10 | H71: 2 | I71: +2200 | K71: B | L71: CBS Sports title odds 2026-08-04 | M71: 2026-10-08 | N71: low confidence: far-out event | O71: ='NCAAB'!Y10
A72: 71 | B72: Actress | C72: Anne Hathaway | D72: Korch | E72: ='Actress'!M7 | F72: ='Actress'!N7 | G72: ='Actress'!O7 | H72: 1 | J72: Alone at Dawn (Dec 25) | K72: C | L72: Wikipedia 'List of American films of 2027' casts (Actions-runner pull 2026-10-08) x comp-based box office/RT estimates; cast lists are billed leads only (cameos not captured) | M72: 2026-10-08 | N72: Good but the field reaches for it: let it come to you | O72: ='Actress'!Y7
A73: 72 | B73: MLB | C73: Atlanta Braves | D73: Todd | E73: ='MLB'!M8 | F73: ='MLB'!N8 | G73: ='MLB'!O8 | H73: 2 | J73: 2026: 94-68 (.5802) | K73: C | L73: 2026 win% from league standings (A); title prob = model estimate — no 2027 World Series odds posted | M73: 2026-10-08 | N73: low confidence: far-out event | O73: ='MLB'!Y8
A74: 73 | B74: NBA | C74: Miami Heat | D74: — free | E74: ='NBA'!M12 | F74: ='NBA'!N12 | G74: ='NBA'!O12 | H74: 3 | I74: Kalshi 6.5% | J74: East; win total 46.5 | K74: A | L74: KXNBA-27 exchange mid-price, pulled 2026-10-08; p(final)=KXNBAEAST/KXNBAWEST-27 Kalshi mid | league_sim.py: full-schedule + real playoff bracket Monte Carlo, ratings fitted to Kalshi | M74: 2026-10-08 | O74: ='NBA'!Y12
A75: 74 | B75: MLB | C75: Tampa Bay Rays | D75: — free | E75: ='MLB'!M9 | F75: ='MLB'!N9 | G75: ='MLB'!O9 | H75: 2 | J75: 2026: 98-64 (.6049) | K75: C | L75: 2026 win% from league standings (A); title prob = model estimate — no 2027 World Series odds posted | M75: 2026-10-08 | N75: low confidence: far-out event | O75: ='MLB'!Y9
A76: 75 | B76: NCAAB | C76: Houston | D76: Theo | E76: ='NCAAB'!M11 | F76: ='NCAAB'!N11 | G76: ='NCAAB'!O11 | H76: 2 | I76: +2500 | K76: B | L76: CBS Sports title odds 2026-08-04 | M76: 2026-10-08 | N76: low confidence: far-out event | O76: ='NCAAB'!Y11
A77: 76 | B77: NCAAB | C77: Arizona | D77: — free | E77: ='NCAAB'!M12 | F77: ='NCAAB'!N12 | G77: ='NCAAB'!O12 | H77: 3 | I77: +2500 | K77: B | L77: CBS Sports title odds 2026-08-04 | M77: 2026-10-08 | N77: low confidence: far-out event | O77: ='NCAAB'!Y12
A78: 77 | B78: Actor | C78: Ryan Gosling | D78: — free | E78: ='Actor'!M5 | F78: ='Actor'!N5 | G78: ='Actor'!O5 | H78: 1 | J78: Starfighter (May 28); Avengers: Secret Wars (Dec 17) | K78: C | L78: Wikipedia 'List of American films of 2027' casts (Actions-runner pull 2026-10-08) x comp-based box office/RT estimates; cast lists are billed leads only (cameos not captured) | M78: 2026-10-08 | N78: Good but the field reaches for it: let it come to you | O78: ='Actor'!Y5
A79: 78 | B79: Musician | C79: Rosalía | D79: — free | E79: ='Musician'!M10 | F79: ='Musician'!N10 | G79: ='Musician'!O10 | H79: 2 | I79: Grammy EV 6.6 (raw 6.8, P(cap) 9%) | J79: 2026 raw 0; charting now: none charting; carry-over 0.0 + new hits 1.2 (lambda 0.15, P(~0) 86%) | K79: C | L79: 2027 Hot 100 baseline = my estimate; Grammy: Kalshi KXGRAM*-69 prices (A) + estimates for other categories (C) | M79: 2026-10-08 | N79: Good but the field reaches for it: let it come to you | O79: ='Musician'!Y10
A80: 79 | B80: NBA | C80: Los Angeles Lakers | D80: Theo | E80: ='NBA'!M13 | F80: ='NBA'!N13 | G80: ='NBA'!O13 | H80: 3 | I80: Kalshi 3.5% | J80: West; win total 46.5 | K80: A | L80: KXNBA-27 exchange mid-price, pulled 2026-10-08; p(final)=KXNBAEAST/KXNBAWEST-27 Kalshi mid | league_sim.py: full-schedule + real playoff bracket Monte Carlo, ratings fitted to Kalshi | M80: 2026-10-08 | O80: ='NBA'!Y13
A81: 80 | B81: Golf | C81: Russell Henley | D81: Jens | E81: ='Golf'!M10 | F81: ='Golf'!N10 | G81: ='Golf'!O10 | H81: 2 | J81: OWGR 6 (2026-10-08) | K81: C | L81: OWGR rank from league standings pull (A); major-win probabilities = model (rank-weighted share of 4 majors) | M81: 2026-10-08 | O81: ='Golf'!Y10
A82: 81 | B82: MLS | C82: St. Louis City SC | D82: — free | E82: ='MLS'!M8 | F82: ='MLS'!N8 | G82: ='MLS'!O8 | H82: 2 | I82: 2026 Cup: Kalshi 5.5% | J82: 2026: 47 pts (as of 10-08; season ends Nov 7) | K82: C | L82: 2026 points (league standings, A) + Kalshi KXMLSCUP-26 price as strength proxy, shrunk 50% toward the field | M82: 2026-10-08 | N82: low confidence: far-out event | O82: ='MLS'!Y8
A83: 82 | B83: MLS | C83: FC Dallas | D83: — free | E83: ='MLS'!M9 | F83: ='MLS'!N9 | G83: ='MLS'!O9 | H83: 2 | I83: 2026 Cup: Kalshi 4.5% | J83: 2026: 47 pts (as of 10-08; season ends Nov 7) | K83: C | L83: 2026 points (league standings, A) + Kalshi KXMLSCUP-26 price as strength proxy, shrunk 50% toward the field | M83: 2026-10-08 | N83: low confidence: far-out event | O83: ='MLS'!Y9
A84: 83 | B84: NBA | C84: Detroit Pistons | D84: — free | E84: ='NBA'!M14 | F84: ='NBA'!N14 | G84: ='NBA'!O14 | H84: 3 | I84: +2200 | J84: East; win total 49.5 | K84: A | L84: FanDuel ~2026-10-07; Polymarket via Covers; BetMGM win totals; p(final)=KXNBAEAST/KXNBAWEST-27 Kalshi mid | league_sim.py: full-schedule + real playoff bracket Monte Carlo, ratings fitted to Kalshi | M84: 2026-10-08 | O84: ='NBA'!Y14
A85: 84 | B85: NFL | C85: Denver Broncos | D85: Molmen | E85: ='NFL'!M12 | F85: ='NFL'!N12 | G85: ='NFL'!O12 | H85: 3 | I85: Kalshi 3.5% | J85: 2-2, AFC West | K85: A | L85: KXSB-27 exchange mid-price, pulled 2026-10-08; p(final)=KXNFLAFCCHAMP/KXNFLNFCCHAMP-27 Kalshi mid | league_sim.py: full-schedule + real playoff bracket Monte Carlo, ratings fitted to Kalshi | M85: 2026-10-08 | O85: ='NFL'!Y12
A86: 85 | B86: Tennis | C86: Jessica Pegula | D86: Korch | E86: ='Tennis'!M10 | F86: ='Tennis'!N10 | G86: ='Tennis'!O10 | H86: 2 | J86: WTA 3 (2026-10-08) | K86: C | L86: ATP rank from league standings pull (A) / WTA via Olympics.com Oct 5; AO odds VegasInsider/Johnnybet Oct 2026; probabilities = agent estimates | M86: 2026-10-08 | O86: ='Tennis'!Y10
A87: 86 | B87: MLS | C87: New England Revolution | D87: — free | E87: ='MLS'!M10 | F87: ='MLS'!N10 | G87: ='MLS'!O10 | H87: 2 | I87: 2026 Cup: Kalshi 3.5% | J87: 2026: 46 pts (as of 10-08; season ends Nov 7) | K87: C | L87: 2026 points (league standings, A) + Kalshi KXMLSCUP-26 price as strength proxy, shrunk 50% toward the field | M87: 2026-10-08 | N87: low confidence: far-out event | O87: ='MLS'!Y10
A88: 87 | B88: Actress | C88: Hailee Steinfeld | D88: — free | E88: ='Actress'!M8 | F88: ='Actress'!N8 | G88: ='Actress'!O8 | H88: 2 | J88: Spider-Man: Beyond the Spider-Verse (Jun 18) | K88: C | L88: Wikipedia 'List of American films of 2027' casts (Actions-runner pull 2026-10-08) x comp-based box office/RT estimates; cast lists are billed leads only (cameos not captured) | M88: 2026-10-08 | N88: Good but the field reaches for it: let it come to you | O88: ='Actress'!Y8
A89: 88 | B89: NHL | C89: Utah Mammoth | D89: — free | E89: ='NHL'!M12 | F89: ='NHL'!N12 | G89: ='NHL'!O12 | H89: 3 | I89: Kalshi 3.0% | J89: West | K89: A | L89: KXNHL-27 exchange mid-price, pulled 2026-10-08; p(final)=KXNHLEAST/KXNHLWEST-27 Kalshi mid | league_sim.py: full-schedule + real playoff bracket Monte Carlo, ratings fitted to Kalshi | M89: 2026-10-08 | O89: ='NHL'!Y12
A90: 89 | B90: Actor | C90: John Malkovich | D90: — free | E90: ='Actor'!M6 | F90: ='Actor'!N6 | G90: ='Actor'!O6 | H90: 1 | J90: no 2027 film found in Wikipedia's cast lists | K90: C | L90: Wikipedia 'List of American films of 2027' casts (Actions-runner pull 2026-10-08) x comp-based box office/RT estimates; cast lists are billed leads only (cameos not captured) | M90: 2026-10-08 | N90: Good but the field reaches for it: let it come to you | O90: ='Actor'!Y6
A91: 90 | B91: Stock | C91: MSTR (Long) | D91: — free | E91: ='Stock'!M5 | F91: ='Stock'!N5 | G91: ='Stock'!O5 | H91: 1 | J91: levered BTC proxy | K91: C | L91: my estimate: sector view + typical vol; no price data pulled (verify quotes before drafting) | M91: 2026-10-08 | N91: coin flip: take last, no edge | O91: ='Stock'!Y5
A92: 91 | B92: Stock | C92: COIN (Long) | D92: Tim | E92: ='Stock'!M6 | F92: ='Stock'!N6 | G92: ='Stock'!O6 | H92: 1 | J92: BTC-cycle beta | K92: C | L92: my estimate: sector view + typical vol; no price data pulled (verify quotes before drafting) | M92: 2026-10-08 | N92: coin flip: take last, no edge | O92: ='Stock'!Y6
A93: 92 | B93: Stock | C93: AMD (Long) | D93: — free | E93: ='Stock'!M7 | F93: ='Stock'!N7 | G93: ='Stock'!O7 | H93: 1 | J93: MI400/Helios ramp 2H26-27 | K93: C | L93: my estimate: sector view + typical vol; no price data pulled (verify quotes before drafting) | M93: 2026-10-08 | N93: coin flip: take last, no edge | O93: ='Stock'!Y7
A94: 93 | B94: Stock | C94: TTWO (Long) | D94: Molmen | E94: ='Stock'!M8 | F94: ='Stock'!N8 | G94: ='Stock'!O8 | H94: 2 | J94: owned; no price data pulled | K94: C | L94: added because a league member currently owns this pick (draft_picks_2026.py); not in the first-pass pool, so figures are placeholders (conf C) | M94: 2026-10-08 | N94: coin flip: take last, no edge | O94: ='Stock'!Y8
A95: 94 | B95: Stock | C95: SMCI (Long) | D95: Korch | E95: ='Stock'!M9 | F95: ='Stock'!N9 | G95: ='Stock'!O9 | H95: 2 | J95: high-variance AI servers | K95: C | L95: my estimate: sector view + typical vol; no price data pulled (verify quotes before drafting) | M95: 2026-10-08 | N95: coin flip: take last, no edge | O95: ='Stock'!Y9
A96: 95 | B96: MLB | C96: Chicago Cubs | D96: Tim | E96: ='MLB'!M10 | F96: ='MLB'!N10 | G96: ='MLB'!O10 | H96: 2 | J96: 2026: 89-73 (.5494) | K96: C | L96: 2026 win% from league standings (A); title prob = model estimate — no 2027 World Series odds posted | M96: 2026-10-08 | N96: low confidence: far-out event | O96: ='MLB'!Y10
A97: 96 | B97: Stock | C97: TSLA (Short) | D97: Shep | E97: ='Stock'!M10 | F97: ='Stock'!N10 | G97: ='Stock'!O10 | H97: 2 | J97: squeeze risk | K97: C | L97: my estimate: sector view + typical vol; no price data pulled (verify quotes before drafting) | M97: 2026-10-08 | N97: coin flip: take last, no edge | O97: ='Stock'!Y10
A98: 97 | B98: MLB | C98: San Diego Padres | D98: Theo | E98: ='MLB'!M11 | F98: ='MLB'!N11 | G98: ='MLB'!O11 | H98: 2 | J98: 2026: 91-71 (.5617) | K98: C | L98: 2026 win% from league standings (A); title prob = model estimate — no 2027 World Series odds posted | M98: 2026-10-08 | N98: low confidence: far-out event | O98: ='MLB'!Y11
A99: 98 | B99: Tennis | C99: Ben Shelton | D99: — free | E99: ='Tennis'!M11 | F99: ='Tennis'!N11 | G99: ='Tennis'!O11 | H99: 2 | J99: ATP 4 (2026-10-08) | K99: C | L99: ATP rank from league standings pull (A) / WTA via Olympics.com Oct 5; AO odds VegasInsider/Johnnybet Oct 2026; probabilities = agent estimates | M99: 2026-10-08 | O99: ='Tennis'!Y11
A100: 99 | B100: Golf | C100: Tommy Fleetwood | D100: Korch | E100: ='Golf'!M11 | F100: ='Golf'!N11 | G100: ='Golf'!O11 | H100: 2 | J100: OWGR 7 (2026-10-08) | K100: C | L100: OWGR rank from league standings pull (A); major-win probabilities = model (rank-weighted share of 4 majors) | M100: 2026-10-08 | O100: ='Golf'!Y11
...

Sheet Assumptions
A1: Category | B1: Champion | C1: Lost final | D1: Lost semi | E1: Lost quarter | F1: Lost round 1 | G1: Replacement rank N | H1: Bonus cap | I1: Replacement EV (Nth best / best left after the field's picks) | J1: Field award overweight w | K1: Field takes first M
A2: NFL | B2: 13 | C2: 9 | D2: 6.5 | E2: 4 | F2: 2.5 | G2: 7 | H2: 13 | I2: =LARGE('NFL'!$M$5:$M$36,MIN(G2,COUNT('NFL'!$M$5:$M$36)))
A3: NBA | B3: 13 | C3: 9 | D3: 6.5 | E3: 4 | F3: 2.5 | G3: 7 | H3: 13 | I3: =LARGE('NBA'!$M$5:$M$34,MIN(G3,COUNT('NBA'!$M$5:$M$34)))
A4: MLB | B4: 13 | C4: 9 | D4: 6.5 | E4: 4 | F4: 2.5 | G4: 7 | H4: 13 | I4: =LARGE('MLB'!$M$5:$M$34,MIN(G4,COUNT('MLB'!$M$5:$M$34)))
A5: NHL | B5: 13 | C5: 9 | D5: 6.5 | E5: 4 | F5: 2.5 | G5: 7 | H5: 13 | I5: =LARGE('NHL'!$M$5:$M$36,MIN(G5,COUNT('NHL'!$M$5:$M$36)))
A6: NCAAF | B6: 13 | C6: 9 | D6: 6.5 | E6: 4 | F6: 2.5 | G6: 7 | H6: 13 | I6: =LARGE('NCAAF'!$M$5:$M$32,MIN(G6,COUNT('NCAAF'!$M$5:$M$32)))
A7: NCAAB | B7: 13 | C7: 9 | D7: 6.5 | E7: 4 | F7: 2.5 | G7: 7 | H7: 13 | I7: =LARGE('NCAAB'!$M$5:$M$34,MIN(G7,COUNT('NCAAB'!$M$5:$M$34)))
A8: Tennis | G8: 7 | H8: 13 | I8: =LARGE('Tennis'!$M$5:$M$29,MIN(G8,COUNT('Tennis'!$M$5:$M$29)))
A9: Golf | G9: 7 | H9: 13 | I9: =LARGE('Golf'!$M$5:$M$44,MIN(G9,COUNT('Golf'!$M$5:$M$44)))
A10: NASCAR | G10: 7 | H10: 13 | I10: =LARGE('NASCAR'!$M$5:$M$28,MIN(G10,COUNT('NASCAR'!$M$5:$M$28)))
A11: MLS | B11: 13 | C11: 9 | D11: 6.5 | E11: 0 | F11: 0 | G11: 7 | H11: 13 | I11: =LARGE('MLS'!$M$5:$M$34,MIN(G11,COUNT('MLS'!$M$5:$M$34)))
A12: Actor | G12: 7 | H12: 13 | I12: =MAX(LARGE('Actor'!$M$5:$M$98,MIN(G12,COUNT('Actor'!$M$5:$M$98))),SUMPRODUCT(MAX(('Actor'!$W$5:$W$98>K12)*'Actor'!$M$5:$M$98))) | J12: 2 | K12: 8
A13: Actress | G13: 7 | H13: 13 | I13: =MAX(LARGE('Actress'!$M$5:$M$92,MIN(G13,COUNT('Actress'!$M$5:$M$92))),SUMPRODUCT(MAX(('Actress'!$W$5:$W$92>K13)*'Actress'!$M$5:$M$92))) | J13: 2 | K13: 8
A14: Musician | G14: 7 | H14: 13 | I14: =MAX(LARGE('Musician'!$M$5:$M$36,MIN(G14,COUNT('Musician'!$M$5:$M$36))),SUMPRODUCT(MAX(('Musician'!$W$5:$W$36>K14)*'Musician'!$M$5:$M$36))) | J14: 2 | K14: 8
A15: Country | G15: 7 | H15: 13 | I15: =LARGE('Country'!$M$5:$M$65,MIN(G15,COUNT('Country'!$M$5:$M$65)))
A16: Stock | G16: 7 | H16: 13 | I16: =LARGE('Stock'!$M$5:$M$30,MIN(G16,COUNT('Stock'!$M$5:$M$30)))
A19: Other inputs
A20: Tennis slam win pts | B20: 4
A21: Tennis slam runner-up pts | B21: 2.5
A22: Golf major win pts | B22: 6
A23: Golf major runner-up pts | B23: 2.5
A24: NASCAR avg pts for finishing 2nd-5th | B24: 4.5
A25: Risk aversion λ (Risk-adj VOR = VOR − λ·SD of rank pts) | B25: 0
A26: Confidence haircut, grade B (pts off VOR) | B26: 0.3
A27: Confidence haircut, grade C (pts off VOR) | B27: 0.8
A30: Certainty adjustments applied to data/*.json before the model (v2)
A31: Category | B31: sd multiplier | C31: mu shrink to field | D31: title-prob shrink to uniform | E31: Why
A32: NFL | B32: 1 | C32: 0 | D32: 0 | E32: season in progress, Kalshi-priced
A33: NBA | B33: 1 | C33: 0 | D33: 0 | E33: opens Oct 20, Kalshi-priced
A34: MLB | B34: 2 | C34: 0.5 | D34: 0.5 | E34: calendar 2027, no 2027 market; year-to-year win% persistence is weak
A35: NHL | B35: 1 | C35: 0 | D35: 0 | E35: season started, Kalshi-priced
A36: NCAAF | B36: 1 | C36: 0 | D36: 0 | E36: season in progress, Kalshi-priced
A37: NCAAB | B37: 1.6 | C37: 0.3 | D37: 0.25 | E37: season not started; tournament chaos
A38: Tennis | B38: 1 | C38: 0 | D38: 0 | E38: rankings sticky; slams stable at the top
A39: Golf | B39: 1 | C39: 0 | D39: 0 | E39: OWGR is sticky; majors are stable at the top
A40: NASCAR | B40: 2 | C40: 0.4 | D40: 0.3 | E40: calendar 2027, no 2027 market; probabilities now recency-weighted from 2021-26 final standings (lighter p shrink)
A41: MLS | B41: 2 | C41: 0.5 | D41: 0.5 | E41: calendar 2027, no 2027 market; playoff-driven
A42: Actor | B42: 1 | C42: 0 | D42: 0 | E42: see Market overweight
A43: Actress | B43: 1 | C43: 0 | D43: 0 | E43: see Market overweight
... A45: Country | B45: 1 | C45: 0 | D45: 0 | E45: IMF-published growth, small sd
A46: Stock | B46: flat | C46: flat | D46: - | E46: pure luck: mu and sd forced equal for all picks
A48: These are applied in Python (edit CERT in build_workbook.py and rebuild); the Excel cells above are the live ones.

Sheet NFL
A1: NFL — 2027 draft research (EV model; see README)
A2: As of 2026-10-22. Sorted by E[total]. Yellow = inferred / low-confidence (C).
A4: Candidate | B4: Detail | C4: Odds / price | D4: p(champ) | E4: p(final) | F4: p(semi) | G4: p(quarter) | H4: p(rd 1) | I4: mu | J4: sd | K4: E[rank pts] (MC) | L4: E[bonus] | M4: E[total] | N4: VOR | O4: Risk-adj VOR | P4: Tier | Q4: SD rank pts | R4: Source | S4: As of | T4: Conf | U4: Notes | V4: Field draft score | W4: Field rank | X4: Owner | Y4: Conf-adj VOR
A5: San Francisco 49ers | B5: 4-0, NFC West | C5: Kalshi 9.5% | D5: 0.142 | E5: 0.2631 | F5: 0.4592 | G5: 0.815 | H5: 0.97 | I5: 0.7361 | J5: 0.0948 | K5: 11.609 | L5: =Assumptions!$B$2*D5+Assumptions!$C$2*(E5-D5)+Assumptions!$D$2*(F5-E5)+Assumptions!$E$2*(G5-F5)+Assumptions!$F$2*(H5-G5) | M5: =K5+MIN(L5,Assumptions!$H$2) | N5: =M5-Assumptions!$I$2 | O5: =N5-Assumptions!$B$25*Q5 | P5: 1 | Q5: 2.1 | R5: KXSB-27 exchange mid-price, pulled 2026-10-08; p(final)=KXNFLAFCCHAMP/KXNFLNFCCHAMP-27 Kalshi mid | league_sim.py: full-schedule + real playoff bracket Monte Carlo, ratings fitted to Kalshi | S5: 2026-10-08 | T5: A | U5: [sim: playoffs 98%, rd2 82%, conf final 46%] | X5: Todd | Y5: =N5-IF(T5="C",Assumptions!$B$27,IF(T5="B",Assumptions!$B$26,0))
A6: Kansas City Chiefs | B6: 4-0, AFC West | C6: Kalshi 9.5% | D6: 0.0927 | E6: 0.1787 | F6: 0.3441 | G6: 0.6405 | H6: 0.9026 | I6: 0.6664 | J6: 0.1012 | K6: 9.906 | L6: =Assumptions!$B$2*D6+Assumptions!$C$2*(E6-D6)+Assumptions!$D$2*(F6-E6)+Assumptions!$E$2*(G6-F6)+Assumptions!$F$2*(H6-G6) | M6: =K6+MIN(L6,Assumptions!$H$2) | N6: =M6-Assumptions!$I$2 | O6: =N6-Assumptions!$B$25*Q6 | P6: 1 | Q6: 3.046 | R6: KXSB-27 exchange mid-price, pulled 2026-10-08; p(final)=KXNFLAFCCHAMP/KXNFLNFCCHAMP-27 Kalshi mid | league_sim.py: full-schedule + real playoff bracket Monte Carlo, ratings fitted to Kalshi | S6: 2026-10-08 | T6: A | U6: [sim: playoffs 90%, rd2 64%, conf final 34%] | X6: Shep | Y6: =N6-IF(T6="C",Assumptions!$B$27,IF(T6="B",Assumptions!$B$26,0))
A7: Buffalo Bills | B7: 3-1, AFC East | C7: Kalshi 10.5% | D7: 0.0931 | E7: 0.1829 | F7: 0.3331 | G7: 0.6 | H7: 0.883 | I7: 0.6488 | J7: 0.0977 | K7: 9.362 | L7: =Assumptions!$B$2*D7+Assumptions!$C$2*(E7-D7)+Assumptions!$D$2*(F7-E7)+Assumptions!$E$2*(G7-F7)+Assumptions!$F$2*(H7-G7) | M7: =K7+MIN(L7,Assumptions!$H$2) | N7: =M7-Assumptions!$I$2 | O7: =N7-Assumptions!$B$25*Q7 | P7: 1 | Q7: 3.148 | R7: KXSB-27 exchange mid-price, pulled 2026-10-08; p(final)=KXNFLAFCCHAMP/KXNFLNFCCHAMP-27 Kalshi mid | league_sim.py: full-schedule + real playoff bracket Monte Carlo, ratings fitted to Kalshi | S7: 2026-10-08 | T7: A | U7: lost to Patriots wk4 [sim: playoffs 88%, rd2 60%, conf final 33%] | X7: Jens | Y7: =N7-IF(T7="C",Assumptions!$B$27,IF(T7="B",Assumptions!$B$26,0))
A8: Minnesota Vikings | B8: 4-0, NFC North | C8: Kalshi 3.5% | D8: 0.0367 | E8: 0.0824 | F8: 0.2107 | G8: 0.4878 | H8: 0.8366 | I8: 0.634 | J8: 0.1012 | K8: 8.825 | L8: =Assumptions!$B$2*D8+Assumptions!$C$2*(E8-D8)+Assumptions!$D$2*(F8-E8)+Assumptions!$E$2*(G8-F8)+Assumptions!$F$2*(H8-G8) | M8: =K8+MIN(L8,Assumptions!$H$2) | N8: =M8-Assumptions!$I$2 | O8: =N8-Assumptions!$B$25*Q8 | P8: 2 | Q8: 3.329 | R8: KXSB-27 exchange mid-price, pulled 2026-10-08; p(final)=KXNFLAFCCHAMP/KXNFLNFCCHAMP-27 Kalshi mid | league_sim.py: full-schedule + real playoff bracket Monte Carlo, ratings fitted to Kalshi | S8: 2026-10-08 | T8: A | U8: [sim: playoffs 84%, rd2 49%, conf final 21%] | Y8: =N8-IF(T8="C",Assumptions!$B$27,IF(T8="B",Assumptions!$B$26,0))
A9: Baltimore Ravens | B9: 3-1, AFC North | C9: Kalshi 7.5% | D9: 0.065 | E9: 0.1229 | F9: 0.243 | G9: 0.4693 | H9: 0.7598 | I9: 0.6027 | J9: 0.0944 | K9: 7.878 | L9: =Assumptions!$B$2*D9+Assumptions!$C$2*(E9-D9)+Assumptions!$D$2*(F9-E9)+Assumptions!$E$2*(G9-F9)+Assumptions!$F$2*(H9-G9) | M9: =K9+MIN(L9,Assumptions!$H$2) | N9: =M9-Assumptions!$I$2 | O9: =N9-Assumptions!$B$25*Q9 | P9: 2 | Q9: 3.362 | R9: KXSB-27 exchange mid-price, pulled 2026-10-08; p(final)=KXNFLAFCCHAMP/KXNFLNFCCHAMP-27 Kalshi mid | league_sim.py: full-schedule + real playoff bracket Monte Carlo, ratings fitted to Kalshi | S9: 2026-10-08 | T9: A | U9: [sim: playoffs 76%, rd2 47%, conf final 24%] | X9: Wu | Y9: =N9-IF(T9="C",Assumptions!$B$27,IF(T9="B",Assumptions!$B$26,0))
A10: Jacksonville Jaguars | B10: 3-1, AFC South | C10: Kalshi 6.5% | D10: 0.0542 | E10: 0.1191 | F10: 0.2299 | G10: 0.4532 | H10: 0.7823 | I10: 0.5928 | J10: 0.0958 | K10: 7.572 | L10: =Assumptions!$B$2*D10+Assumptions!$C$2*(E10-D10)+Assumptions!$D$2*(F10-E10)+Assumptions!$E$2*(G10-F10)+Assumptions!$F$2*(H10-G10) | M10: =K10+MIN(L10,Assumptions!$H$2) | N10: =M10-Assumptions!$I$2 | O10: =N10-Assumptions!$B$25*Q10 | P10: 2 | Q10: 3.463 | R10: KXSB-27 exchange mid-price, pulled 2026-10-08; p(final)=KXNFLAFCCHAMP/KXNFLNFCCHAMP-27 Kalshi mid | league_sim.py: full-schedule + real playoff bracket Monte Carlo, ratings fitted to Kalshi | S10: 2026-10-08 | T10: A | U10: books disagree (+1100 to +2200) [sim: playoffs 78%, rd2 45%, conf final 23%] | Y10: =N10-IF(T10="C",Assumptions!$B$27,IF(T10="B",Assumptions!$B$26,0))
A11: Chicago Bears | B11: 3-1, NFC North | C11: Kalshi 4.5% | D11: 0.0656 | E11: 0.1239 | F11: 0.2376 | G11: 0.4333 | H11: 0.7029 | I11: 0.5829 | J11: 0.0971 | K11: 7.237 | L11: =Assumptions!$B$2*D11+Assumptions!$C$2*(E11-D11)+Assumptions!$D$2*(F11-E11)+Assumptions!$E$2*(G11-F11)+Assumptions!$F$2*(H11-G11) | M11: =K11+MIN(L11,Assumptions!$H$2) | N11: =M11-Assumptions!$I$2 | O11: =N11-Assumptions!$B$25*Q11 | P11: 2 | Q11: 3.466 | R11: KXSB-27 exchange mid-price, pulled 2026-10-08; p(final)=KXNFLAFCCHAMP/KXNFLNFCCHAMP-27 Kalshi mid | league_sim.py: full-schedule + real playoff bracket Monte Carlo, ratings fitted to Kalshi | S11: 2026-10-08 | T11: A | U11: [sim: playoffs 70%, rd2 43%, conf final 24%] | Y11: =N11-IF(T11="C",Assumptions!$B$27,IF(T11="B",Assumptions!$B$26,0))
A12: Denver Broncos | B12: 2-2, AFC West | C12: Kalshi 3.5% | D12: 0.0395 | E12: 0.0846 | F12: 0.1795 | G12: 0.3723 | H12: 0.685 | I12: 0.5797 | J12: 0.0965 | K12: 7.105 | L12: =Assumptions!$B$2*D12+Assumptions!$C$2*(E12-D12)+Assumptions!$D$2*(F12-E12)+Assumptions!$E$2*(G12-F12)+Assumptions!$F$2*(H12-G12) | M12: =K12+MIN(L12,Assumptions!$H$2) | N12: =M12-Assumptions!$I$2 | O12: =N12-Assumptions!$B$25*Q12 | P12: 3 | Q12: 3.462 | R12: KXSB-27 exchange mid-price, pulled 2026-10-08; p(final)=KXNFLAFCCHAMP/KXNFLNFCCHAMP-27 Kalshi mid | league_sim.py: full-schedule + real playoff bracket Monte Carlo, ratings fitted to Kalshi | S12: 2026-10-08 | T12: A | U12: [sim: playoffs 68%, rd2 37%, conf final 18%] | X12: Molmen | Y12: =N12-IF(T12="C",Assumptions!$B$27,IF(T12="B",Assumptions!$B$26,0))
A13: New England Patriots | B13: 2-2, AFC East | C13: Kalshi 2.5% | D13: 0.0478 | E13: 0.09 | F13: 0.1757 | G13: 0.351 | H13: 0.6252 | I13: 0.5619 | J13: 0.0973 | K13: 6.545 | L13: =Assumptions!$B$2*D13+Assumptions!$C$2*(E13-D13)+Assumptions!$D$2*(F13-E13)+Assumptions!$E$2*(G13-F13)+Assumptions!$F$2*(H13-G13) | M13: =K13+MIN(L13,Assumptions!$H$2) | N13: =M13-Assumptions!$I$2 | O13: =N13-Assumptions!$B$25*Q13 | P13: 3 | Q13: 3.45 | R13: KXSB-27 exchange mid-price, pulled 2026-10-08; p(final)=KXNFLAFCCHAMP/KXNFLNFCCHAMP-27 Kalshi mid | league_sim.py: full-schedule + real playoff bracket Monte Carlo, ratings fitted to Kalshi | S13: 2026-10-08 | T13: A | U13: beat Bills wk4 [sim: playoffs 63%, rd2 35%, conf final 18%] | X13: Feder | Y13: =N13-IF(T13="C",Assumptions!$B$27,IF(T13="B",Assumptions!$B$26,0))
A14: Cincinnati Bengals | B14: 2-2, AFC North | C14: Kalshi 3.5% | D14: 0.0345 | E14: 0.0729 | F14: 0.1661 | G14: 0.3374 | H14: 0.6204 | I14: 0.5644 | J14: 0.0997 | K14: 6.57 | L14: =Assumptions!$B$2*D14+Assumptions!$C$2*(E14-D14)+Assumptions!$D$2*(F14-E14)+Assumptions!$E$2*(G14-F14)+Assumptions!$F$2*(H14-G14) | M14: =K14+MIN(L14,Assumptions!$H$2) | N14: =M14-Assumptions!$I$2 | O14: =N14-Assumptions!$B$25*Q14 | P14: 3 | Q14: 3.522 | R14: KXSB-27 exchange mid-price, pulled 2026-10-08; p(final)=KXNFLAFCCHAMP/KXNFLNFCCHAMP-27 Kalshi mid | league_sim.py: full-schedule + real playoff bracket Monte Carlo, ratings fitted to Kalshi | S14: 2026-10-08 | T14: A | U14: [sim: playoffs 62%, rd2 34%, conf final 17%] | Y14: =N14-IF(T14="C",Assumptions!$B$27,IF(T14="B",Assumptions!$B$26,0))
A15: Detroit Lions | B15: 2-2, NFC North | C15: +3500 | D15: 0.0377 | E15: 0.0776 | F15: 0.161 | G15: 0.3395 | H15: 0.5926 | I15: 0.5574 | J15: 0.1009 | K15: 6.347 | L15: =Assumptions!$B$2*D15+Assumptions!$C$2*(E15-D15)+Assumptions!$D$2*(F15-E15)+Assumptions!$E$2*(G15-F15)+Assumptions!$F$2*(H15-G15) | M15: =K15+MIN(L15,Assumptions!$H$2) | N15: =M15-Assumptions!$I$2 | O15: =N15-Assumptions!$B$25*Q15 | P15: 3 | Q15: 3.493 | R15: estimate; p(final)=KXNFLAFCCHAMP/KXNFLNFCCHAMP-27 Kalshi mid | league_sim.py: full-schedule + real playoff bracket Monte Carlo, ratings fitted to Kalshi | S15: 2026-10-08 | T15: A | U15: [sim: playoffs 59%, rd2 34%, conf final 16%] | X15: Jamzee | Y15: =N15-IF(T15="C",Assumptions!$B$27,IF(T15="B",Assumptions!$B$26,0))
A16: Seattle Seahawks | B16: 3-1, NFC West | C16: Kalshi 8.5% | D16: 0.0553 | E16: 0.1055 | F16: 0.1918 | G16: 0.346 | H16: 0.5649 | I16: 0.5467 | J16: 0.0942 | K16: 5.96 | L16: =Assumptions!$B$2*D16+Assumptions!$C$2*(E16-D16)+Assumptions!$D$2*(F16-E16)+Assumptions!$E$2*(G16-F16)+Assumptions!$F$2*(H16-G16) | M16: =K16+MIN(L16,Assumptions!$H$2) | N16: =M16-Assumptions!$I$2 | O16: =N16-Assumptions!$B$25*Q16 | P16: 3 | Q16: 3.387 | R16: KXSB-27 exchange mid-price, pulled 2026-10-08; p(final)=KXNFLAFCCHAMP/KXNFLNFCCHAMP-27 Kalshi mid | league_sim.py: full-schedule + real playoff bracket Monte Carlo, ratings fitted to Kalshi | S16: 2026-10-08 | T16: A | U16: defending Super Bowl champion [sim: playoffs 56%, rd2 35%, conf final 19%] | X16: Tim | Y16: =N16-IF(T16="C",Assumptions!$B$27,IF(T16="B",Assumptions!$B$26,0))
A17: Green Bay Packers | B17: 2-2, NFC North | C17: +3500 | D17: 0.0285 | E17: 0.0624 | F17: 0.1389 | G17: 0.2916 | H17: 0.5489 | I17: 0.5448 | J17: 0.0962 | K17: 5.804 | L17: =Assumptions!$B$2*D17+Assumptions!$C$2*(E17-D17)+Assumptions!$D$2*(F17-E17)+Assumptions!$E$2*(G17-F17)+Assumptions!$F$2*(H17-G17) | M17: =K17+MIN(L17,Assumptions!$H$2) | N17: =M17-Assumptions!$I$2 | O17: =N17-Assumptions!$B$25*Q17 | P17: 3 | Q17: 3.419 | R17: estimate | league_sim.py: full-schedule + real playoff bracket Monte Carlo, ratings fitted to Kalshi | S17: 2026-10-08 | T17: A | U17: [sim: playoffs 55%, rd2 29%, conf final 14%] | X17: Fryar | Y17: =N17-IF(T17="C",Assumptions!$B$27,IF(T17="B",Assumptions!$B$26,0))
A18: Los Angeles Rams | B18: 2-2, NFC West | C18: Kalshi 11.5% | D18: 0.0648 | E18: 0.1126 | F18: 0.1799 | G18: 0.2948 | H18: 0.445 | I18: 0.5159 | J18: 0.0937 | K18: 4.989 | L18: =Assumptions!$B$2*D18+Assumptions!$C$2*(E18-D18)+Assumptions!$D$2*(F18-E18)+Assumptions!$E$2*(G18-F18)+Assumptions!$F$2*(H18-G18) | M18: =K18+MIN(L18,Assumptions!$H$2) | N18: =M18-Assumptions!$I$2 | O18: =N18-Assumptions!$B$25*Q18 | P18: 4 | Q18: 3.114 | R18: KXSB-27 exchange mid-price, pulled 2026-10-08; p(final)=KXNFLAFCCHAMP/KXNFLNFCCHAMP-27 Kalshi mid | league_sim.py: full-schedule + real playoff bracket Monte Carlo, ratings fitted to Kalshi | S18: 2026-10-08 | T18: A | U18: [sim: playoffs 44%, rd2 29%, conf final 18%] | X18: Mitchell | Y18: =N18-IF(T18="C",Assumptions!$B$27,IF(T18="B",Assumptions!$B$26,0))
A19: Houston Texans | B19: 0-4, AFC South | C19: +4500 | D19: 0.0326 | E19: 0.0649 | F19: 0.1197 | G19: 0.2316 | H19: 0.4206 | I19: 0.5045 | J19: 0.0946 | K19: 4.673 | L19: =Assumptions!$B$2*D19+Assumptions!$C$2*(E19-D19)+Assumptions!$D$2*(F19-E19)+Assumptions!$E$2*(G19-F19)+Assumptions!$F$2*(H19-G19) | M19: =K19+MIN(L19,Assumptions!$H$2) | N19: =M19-Assumptions!$I$2 | O19: =N19-Assumptions!$B$25*Q19 | P19: 4 | Q19: 3.126 | R19: ESPN/ABC7 Super Bowl LXI board ~2026-10-05; prediction-market avg 2026-10-07 (defirate); p(final)=KXNFLAFCCHAMP/KXNFLNFCCHAMP-27 Kalshi mid | league_sim.py: full-schedule + real playoff bracket Monte Carlo, ratings fitted to Kalshi | S19: 2026-10-08 | T19: A | U19: preseason +1800 | price superseded by Kalshi field; p rescaled [sim: playoffs 42%, rd2 23%, conf final 12%] | Y19: =N19-IF(T19="C",Assumptions!$B$27,IF(T19="B",Assumptions!$B$26,0))
A20: Carolina Panthers | B20: 2-2, NFC South | C20: +10000 | D20: 0.0144 | E20: 0.0351 | F20: 0.0907 | G20: 0.226 | H20: 0.523 | I20: 0.4968 | J20: 0.1013 | K20: 4.488 | L20: =Assumptions!$B$2*D20+Assumptions!$C$2*(E20-D20)+Assumptions!$D$2*(F20-E20)+Assumptions!$E$2*(G20-F20)+Assumptions!$F$2*(H20-G20) | M20: =K20+MIN(L20,Assumptions!$H$2) | N20: =M20-Assumptions!$I$2 | O20: =N20-Assumptions!$B$25*Q20 | P20: 4 | Q20: 3.155 | R20: estimate | league_sim.py: full-schedule + real playoff bracket Monte Carlo, ratings fitted to Kalshi | S20: 2026-10-08 | T20: A | U20: [sim: playoffs 52%, rd2 23%, conf final 9%] | Y20: =N20-IF(T20="C",Assumptions!$B$27,IF(T20="B",Assumptions!$B$26,0))
A21: Pittsburgh Steelers | B21: 2-2, AFC North | C21: +6500 | D21: 0.0088 | E21: 0.0229 | F21: 0.0615 | G21: 0.165 | H21: 0.4044 | I21: 0.5116 | J21: 0.0945 | K21: 4.898 | L21: =Assumptions!$B$2*D21+Assumptions!$C$2*(E21-D21)+Assumptions!$D$2*(F21-E21)+Assumptions!$E$2*(G21-F21)+Assumptions!$F$2*(H21-G21) | M21: =K21+MIN(L21,Assumptions!$H$2) | N21: =M21-Assumptions!$I$2 | O21: =N21-Assumptions!$B$25*Q21 | P21: 4 | Q21: 3.222 | R21: estimate | league_sim.py: full-schedule + real playoff bracket Monte Carlo, ratings fitted to Kalshi | S21: 2026-10-08 | T21: A | U21: [sim: playoffs 40%, rd2 16%, conf final 6%] | Y21: =N21-IF(T21="C",Assumptions!$B$27,IF(T21="B",Assumptions!$B$26,0))
A22: Dallas Cowboys | B22: 2-2, NFC East | C22: Kalshi 3.5% | D22: 0.0265 | E22: 0.0498 | F22: 0.1074 | G22: 0.2152 | H22: 0.4306 | I22: 0.4728 | J22: 0.0949 | K22: 3.849 | L22: =Assumptions!$B$2*D22+Assumptions!$C$2*(E22-D22)+Assumptions!$D$2*(F22-E22)+Assumptions!$E$2*(G22-F22)+Assumptions!$F$2*(H22-G22) | M22: =K22+MIN(L22,Assumptions!$H$2) | N22: =M22-Assumptions!$I$2 | O22: =N22-Assumptions!$B$25*Q22 | P22: 4 | Q22: 2.811 | R22: KXSB-27 exchange mid-price, pulled 2026-10-08; p(final)=KXNFLAFCCHAMP/KXNFLNFCCHAMP-27 Kalshi mid | league_sim.py: full-schedule + real playoff bracket Monte Carlo, ratings fitted to Kalshi | S22: 2026-10-08 | T22: A | U22: [sim: playoffs 43%, rd2 22%, conf final 11%] | Y22: =N22-IF(T22="C",Assumptions!$B$27,IF(T22="B",Assumptions!$B$26,0))
A23: Cleveland Browns | B23: 3-1, AFC North | C23: +7500 | D23: 0.0041 | E23: 0.0145 | F23: 0.0441 | G23: 0.1355 | H23: 0.352 | I23: 0.4978 | J23: 0.0945 | K23: 4.451 | L23: =Assumptions!$B$2*D23+Assumptions!$C$2*(E23-D23)+Assumptions!$D$2*(F23-E23)+Assumptions!$E$2*(G23-F23)+Assumptions!$F$2*(H23-G23) | M23: =K23+MIN(L23,Assumptions!$H$2) | N23: =M23-Assumptions!$I$2 | O23: =N23-Assumptions!$B$25*Q23 | P23: 4 | Q23: 3.123 | R23: estimate; p(final)=KXNFLAFCCHAMP/KXNFLNFCCHAMP-27 Kalshi mid | league_sim.py: full-schedule + real playoff bracket Monte Carlo, ratings fitted to Kalshi | S23: 2026-10-08 | T23: A | U23: [sim: playoffs 35%, rd2 14%, conf final 4%] | Y23: =N23-IF(T23="C",Assumptions!$B$27,IF(T23="B",Assumptions!$B$26,0))
A24: New York Giants | B24: 3-1, NFC East | C24: +15000 (stale?) | D24: 0.0044 | E24: 0.0127 | F24: 0.0398 | G24: 0.1288 | H24: 0.3946 | I24: 0.4666 | J24: 0.0914 | K24: 3.549 | L24: =Assumptions!$B$2*D24+Assumptions!$C$2*(E24-D24)+Assumptions!$D$2*(F24-E24)+Assumptions!$E$2*(G24-F24)+Assumptions!$F$2*(H24-G24) | M24: =K24+MIN(L24,Assumptions!$H$2) | N24: =M24-Assumptions!$I$2 | O24: =N24-Assumptions!$B$25*Q24 | P24: 4 | Q24: 2.689 | R24: Fox Sports ~10-06 | league_sim.py: full-schedule + real playoff bracket Monte Carlo, ratings fitted to Kalshi | S24: 2026-10-08 | T24: A | U24: price looks stale vs 3-1 record [sim: playoffs 39%, rd2 13%, conf final 4%] | Y24: =N24-IF(T24="C",Assumptions!$B$27,IF(T24="B",Assumptions!$B$26,0))
A25: Las Vegas Raiders | B25: 3-1, AFC West | C25: +6500 | D25: 0.008 | E25: 0.0166 | F25: 0.0415 | G25: 0.1009 | H25: 0.2286 | I25: 0.4594 | J25: 0.0971 | K25: 3.488 | L25: =Assumptions!$B$2*D25+Assumptions!$C$2*(E25-D25)+Assumptions!$D$2*(F25-E25)+Assumptions!$E$2*(G25-F25)+Assumptions!$F$2*(H25-G25) | M25: =K25+MIN(L25,Assumptions!$H$2) | N25: =M25-Assumptions!$I$2 | O25: =N25-Assumptions!$B$25*Q25 | P25: 4 | Q25: 2.768 | R25: estimate | league_sim.py: full-schedule + real playoff bracket Monte Carlo, ratings fitted to Kalshi | S25: 2026-10-08 | T25: A | U25: [sim: playoffs 23%, rd2 10%, conf final 4%] | Y25: =N25-IF(T25="C",Assumptions!$B$27,IF(T25="B",Assumptions!$B$26,0))
A26: New Orleans Saints | B26: 1-3, NFC South | C26: +25000 | D26: 0.0069 | E26: 0.0187 | F26: 0.0467 | G26: 0.1071 | H26: 0.2532 | I26: 0.4297 | J26: 0.0961 | K26: 2.81 | L26: =Assumptions!$B$2*D26+Assumptions!$C$2*(E26-D26)+Assumptions!$D$2*(F26-E26)+Assumptions!$E$2*(G26-F26)+Assumptions!$F$2*(H26-G26) | M26: =K26+MIN(L26,Assumptions!$H$2) | N26: =M26-Assumptions!$I$2 | O26: =N26-Assumptions!$B$25*Q26 | P26: 4 | Q26: 2.315 | R26: estimate | league_sim.py: full-schedule + real playoff bracket Monte Carlo, ratings fitted to Kalshi | S26: 2026-10-08 | T26: A | U26: [sim: playoffs 25%, rd2 11%, conf final 5%] | Y26: =N26-IF(T26="C",Assumptions!$B$27,IF(T26="B",Assumptions!$B$26,0))
A27: Atlanta Falcons | B27: 2-2, NFC South | C27: +10000 | D27: 0.0084 | E27: 0.0184 | F27: 0.0437 | G27: 0.1025 | H27: 0.2296 | I27: 0.4221 | J27: 0.0973 | K27: 2.663 | L27: =Assumptions!$B$2*D27+Assumptions!$C$2*(E27-D27)+Assumptions!$D$2*(F27-E27)+Assumptions!$E$2*(G27-F27)+Assumptions!$F$2*(H27-G27) | M27: =K27+MIN(L27,Assumptions!$H$2) | N27: =M27-Assumptions!$I$2 | O27: =N27-Assumptions!$B$25*Q27 | P27: 4 | Q27: 2.243 | R27: estimate; p(final)=KXNFLAFCCHAMP/KXNFLNFCCHAMP-27 Kalshi mid | league_sim.py: full-schedule + real playoff bracket Monte Carlo, ratings fitted to Kalshi | S27: 2026-10-08 | T27: A | U27: [sim: playoffs 23%, rd2 10%, conf final 4%] | Y27: =N27-IF(T27="C",Assumptions!$B$27,IF(T27="B",Assumptions!$B$26,0))
A28: New York Jets | B28: 1-3, AFC East | C28: +25000 | D28: 0.004 | E28: 0.0101 | F28: 0.0204 | G28: 0.045 | H28: 0.1036 | I28: 0.4069 | J28: 0.0956 | K28: 2.418 | L28: =Assumptions!$B$2*D28+Assumptions!$C$2*(E28-D28)+Assumptions!$D$2*(F28-E28)+Assumptions!$E$2*(G28-F28)+Assumptions!$F$2*(H28-G28) | M28: =K28+MIN(L28,Assumptions!$H$2) | N28: =M28-Assumptions!$I$2 | O28: =N28-Assumptions!$B$25*Q28 | P28: 4 | Q28: 2.072 | R28: estimate | league_sim.py: full-schedule + real playoff bracket Monte Carlo, ratings fitted to Kalshi | S28: 2026-10-08 | T28: A | U28: [sim: playoffs 10%, rd2 4%, conf final 2%] | Y28: =N28-IF(T28="C",Assumptions!$B$27,IF(T28="B",Assumptions!$B$26,0))
A29: Philadelphia Eagles | B29: 2-2, NFC East | C29: Kalshi 2.5% | D29: 0.0027 | E29: 0.0074 | F29: 0.0239 | G29: 0.0579 | H29: 0.1641 | I29: 0.3938 | J29: 0.095 | K29: 2.201 | L29: =Assumptions!$B$2*D29+Assumptions!$C$2*(E29-D29)+Assumptions!$D$2*(F29-E29)+Assumptions!$E$2*(G29-F29)+Assumptions!$F$2*(H29-G29) | M29: =K29+MIN(L29,Assumptions!$H$2) | N29: =M29-Assumptions!$I$2 | O29: =N29-Assumptions!$B$25*Q29 | P29: 4 | Q29: 1.866 | R29: KXSB-27 exchange mid-price, pulled 2026-10-08; p(final)=KXNFLAFCCHAMP/KXNFLNFCCHAMP-27 Kalshi mid | league_sim.py: full-schedule + real playoff bracket Monte Carlo, ratings fitted to Kalshi | S29: 2026-10-08 | T29: A | U29: [sim: playoffs 16%, rd2 6%, conf final 2%] | X29: Korch | Y29: =N29-IF(T29="C",Assumptions!$B$27,IF(T29="B",Assumptions!$B$26,0))
A30: Indianapolis Colts | B30: 2-2, AFC South | C30: +6500 | D30: 0.003 | E30: 0.0065 | F30: 0.0154 | G30: 0.0423 | H30: 0.1098 | I30: 0.4024 | J30: 0.095 | K30: 2.368 | L30: =Assumptions!$B$2*D30+Assumptions!$C$2*(E30-D30)+Assumptions!$D$2*(F30-E30)+Assumptions!$E$2*(G30-F30)+Assumptions!$F$2*(H30-G30) | M30: =K30+MIN(L30,Assumptions!$H$2) | N30: =M30-Assumptions!$I$2 | O30: =N30-Assumptions!$B$25*Q30 | P30: 4 | Q30: 2.101 | R30: estimate | league_sim.py: full-schedule + real playoff bracket Monte Carlo, ratings fitted to Kalshi | S30: 2026-10-08 | T30: A | U30: [sim: playoffs 11%, rd2 4%, conf final 2%] | X30: Theo | Y30: =N30-IF(T30="C",Assumptions!$B$27,IF(T30="B",Assumptions!$B$26,0))
A31: Washington Commanders | B31: 1-3, NFC East | C31: +15000 | D31: 0.0054 | E31: 0.0119 | F31: 0.0265 | G31: 0.0606 | H31: 0.134 | I31: 0.3818 | J31: 0.0966 | K31: 2.013 | L31: =Assumptions!$B$2*D31+Assumptions!$C$2*(E31-D31)+Assumptions!$D$2*(F31-E31)+Assumptions!$E$2*(G31-F31)+Assumptions!$F$2*(H31-G31) | M31: =K31+MIN(L31,Assumptions!$H$2) | N31: =M31-Assumptions!$I$2 | O31: =N31-Assumptions!$B$25*Q31 | P31: 4 | Q31: 1.665 | R31: estimate | league_sim.py: full-schedule + real playoff bracket Monte Carlo, ratings fitted to Kalshi | S31: 2026-10-08 | T31: A | U31: [sim: playoffs 13%, rd2 6%, conf final 3%] | Y31: =N31-IF(T31="C",Assumptions!$B$27,IF(T31="B",Assumptions!$B$26,0))
A32: Tampa Bay Buccaneers | B32: 0-4, NFC South | C32: +20000 | D32: 0.0066 | E32: 0.0136 | F32: 0.0299 | G32: 0.0614 | H32: 0.1305 | I32: 0.3816 | J32: 0.0956 | K32: 1.986 | L32: =Assumptions!$B$2*D32+Assumptions!$C$2*(E32-D32)+Assumptions!$D$2*(F32-E32)+Assumptions!$E$2*(G32-F32)+Assumptions!$F$2*(H32-G32) | M32: =K32+MIN(L32,Assumptions!$H$2) | N32: =M32-Assumptions!$I$2 | O32: =N32-Assumptions!$B$25*Q32 | P32: 4 | Q32: 1.66 | R32: estimate | league_sim.py: full-schedule + real playoff bracket Monte Carlo, ratings fitted to Kalshi | S32: 2026-10-08 | T32: A | U32: [sim: playoffs 13%, rd2 6%, conf final 3%] | X32: Buckley | Y32: =N32-IF(T32="C",Assumptions!$B$27,IF(T32="B",Assumptions!$B$26,0))
A33: Arizona Cardinals | B33: 1-3, NFC West | C33: +15000 | D33: 0.0024 | E33: 0.0049 | F33: 0.0123 | G33: 0.0326 | H33: 0.0696 | I33: 0.3881 | J33: 0.0954 | K33: 2.06 | L33: =Assumptions!$B$2*D33+Assumptions!$C$2*(E33-D33)+Assumptions!$D$2*(F33-E33)+Assumptions!$E$2*(G33-F33)+Assumptions!$F$2*(H33-G33) | M33: =K33+MIN(L33,Assumptions!$H$2) | N33: =M33-Assumptions!$I$2 | O33: =N33-Assumptions!$B$25*Q33 | P33: 4 | Q33: 1.764 | R33: estimate | league_sim.py: full-schedule + real playoff bracket Monte Carlo, ratings fitted to Kalshi | S33: 2026-10-08 | T33: A | U33: [sim: playoffs 7%, rd2 3%, conf final 1%] | Y33: =N33-IF(T33="C",Assumptions!$B$27,IF(T33="B",Assumptions!$B$26,0))
A34: Miami Dolphins | B34: 0-4, AFC East | C34: +50000 | D34: 0.0018 | E34: 0.0047 | F34: 0.0105 | G34: 0.024 | H34: 0.0506 | I34: 0.3612 | J34: 0.1001 | K34: 1.864 | L34: =Assumptions!$B$2*D34+Assumptions!$C$2*(E34-D34)+Assumptions!$D$2*(F34-E34)+Assumptions!$E$2*(G34-F34)+Assumptions!$F$2*(H34-G34) | M34: =K34+MIN(L34,Assumptions!$H$2) | N34: =M34-Assumptions!$I$2 | O34: =N34-Assumptions!$B$25*Q34 | P34: 4 | Q34: 1.622 | R34: estimate | league_sim.py: full-schedule + real playoff bracket Monte Carlo, ratings fitted to Kalshi | S34: 2026-10-08 | T34: A | U34: [sim: playoffs 5%, rd2 2%, conf final 1%] | Y34: =N34-IF(T34="C",Assumptions!$B$27,IF(T34="B",Assumptions!$B$26,0))
A35: Tennessee Titans | B35: 0-4, AFC South | C35: +50000 | D35: 0.0014 | E35: 0.0049 | F35: 0.0097 | G35: 0.0211 | H35: 0.0499 | I35: 0.3538 | J35: 0.0957 | K35: 1.708 | L35: =Assumptions!$B$2*D35+Assumptions!$C$2*(E35-D35)+Assumptions!$D$2*(F35-E35)+Assumptions!$E$2*(G35-F35)+Assumptions!$F$2*(H35-G35) | M35: =K35+MIN(L35,Assumptions!$H$2) | N35: =M35-Assumptions!$I$2 | O35: =N35-Assumptions!$B$25*Q35 | P35: 4 | Q35: 1.449 | R35: estimate | league_sim.py: full-schedule + real playoff bracket Monte Carlo, ratings fitted to Kalshi | S35: 2026-10-08 | T35: A | U35: [sim: playoffs 5%, rd2 2%, conf final 1%] | Y35: =N35-IF(T35="C",Assumptions!$B$27,IF(T35="B",Assumptions!$B$26,0))
A36: Los Angeles Chargers | B36: 0-4, AFC West | C36: +10000 | D36: 0.0013 | E36: 0.0037 | F36: 0.0056 | G36: 0.011 | H36: 0.0222 | I36: 0.3349 | J36: 0.0958 | K36: 1.516 | L36: =Assumptions!$B$2*D36+Assumptions!$C$2*(E36-D36)+Assumptions!$D$2*(F36-E36)+Assumptions!$E$2*(G36-F36)+Assumptions!$F$2*(H36-G36) | M36: =K36+MIN(L36,Assumptions!$H$2) | N36: =M36-Assumptions!$I$2 | O36: =N36-Assumptions!$B$25*Q36 | P36: 4 | Q36: 1.146 | R36: ESPN/ABC7 Super Bowl LXI board ~2026-10-05; prediction-market avg 2026-10-07 (defirate) | league_sim.py: full-schedule + real playoff bracket Monte Carlo, ratings fitted to Kalshi | S36: 2026-10-08 | T36: A | U36: preseason +1700 | price superseded by Kalshi field; p rescaled [sim: playoffs 2%, rd2 1%, conf final 1%] | Y36: =N36-IF(T36="C",Assumptions!$B$27,IF(T36="B",Assumptions!$B$26,0))
A38: Replacement-level EV (Nth best)

Sheet NBA
A1: NBA — 2027 draft research (EV model; see README)
A2: As of 2026-10-22. Sorted by E[total]. Yellow = inferred / low-confidence (C).
A4: Candidate | B4: Detail | C4: Odds / price | D4: p(champ) | E4: p(final) | F4: p(semi) | G4: p(quarter) | H4: p(rd 1) | I4: mu | J4: sd | K4: E[rank pts] (MC) | L4: E[bonus] | M4: E[total] | N4: VOR | O4: Risk-adj VOR | P4: Tier | Q4: SD rank pts | R4: Source | S4: As of | T4: Conf | U4: Notes | V4: Field draft score | W4: Field rank | X4: Owner | Y4: Conf-adj VOR
A5: Oklahoma City Thunder | B5: West; win total 62.5 | C5: Kalshi 21.5% | D5: 0.2045 | E5: 0.3123 | F5: 0.4815 | G5: 0.7087 | H5: 0.97 | I5: 0.6137 | J5: 0.0536 | K5: 11.16 | L5: =Assumptions!$B$3*D5+Assumptions!$C$3*(E5-D5)+Assumptions!$D$3*(F5-E5)+Assumptions!$E$3*(G5-F5)+Assumptions!$F$3*(H5-G5) | M5: =K5+MIN(L5,Assumptions!$H$3) | N5: =M5-Assumptions!$I$3 | O5: =N5-Assumptions!$B$25*Q5 | P5: 1 | Q5: 2.395 | R5: KXNBA-27 exchange mid-price, pulled 2026-10-08; p(final)=KXNBAEAST/KXNBAWEST-27 Kalshi mid | league_sim.py: full-schedule + real playoff bracket Monte Carlo, ratings fitted to Kalshi | S5: 2026-10-08 | T5: A | U5: [sim: playoffs 99%, rd2 71%, conf final 48%] | X5: Feder | Y5: =N5-IF(T5="C",Assumptions!$B$27,IF(T5="B",Assumptions!$B$26,0))
A6: San Antonio Spurs | B6: West; win total 59.5 | C6: Kalshi 21.5% | D6: 0.1628 | E6: 0.253 | F6: 0.4209 | G6: 0.6616 | H6: 0.9597 | I6: 0.5883 | J6: 0.0546 | K6: 10.083 | L6: =Assumptions!$B$3*D6+Assumptions!$C$3*(E6-D6)+Assumptions!$D$3*(F6-E6)+Assumptions!$E$3*(G6-F6)+Assumptions!$F$3*(H6-G6) | M6: =K6+MIN(L6,Assumptions!$H$3) | N6: =M6-Assumptions!$I$3 | O6: =N6-Assumptions!$B$25*Q6 | P6: 1 | Q6: 2.878 | R6: KXNBA-27 exchange mid-price, pulled 2026-10-08; p(final)=KXNBAEAST/KXNBAWEST-27 Kalshi mid | league_sim.py: full-schedule + real playoff bracket Monte Carlo, ratings fitted to Kalshi | S6: 2026-10-08 | T6: A | U6: [sim: playoffs 96%, rd2 66%, conf final 42%] | X6: Wu | Y6: =N6-IF(T6="C",Assumptions!$B$27,IF(T6="B",Assumptions!$B$26,0))
A7: Philadelphia 76ers | B7: East; win total 50.5 | C7: Kalshi 12.5% | D7: 0.0829 | E7: 0.1645 | F7: 0.2954 | G7: 0.5164 | H7: 0.873 | I7: 0.559 | J7: 0.0552 | K7: 8.403 | L7: =Assumptions!$B$3*D7+Assumptions!$C$3*(E7-D7)+Assumptions!$D$3*(F7-E7)+Assumptions!$E$3*(G7-F7)+Assumptions!$F$3*(H7-G7) | M7: =K7+MIN(L7,Assumptions!$H$3) | N7: =M7-Assumptions!$I$3 | O7: =N7-Assumptions!$B$25*Q7 | P7: 1 | Q7: 3.35 | R7: KXNBA-27 exchange mid-price, pulled 2026-10-08; p(final)=KXNBAEAST/KXNBAWEST-27 Kalshi mid | league_sim.py: full-schedule + real playoff bracket Monte Carlo, ratings fitted to Kalshi | S7: 2026-10-08 | T7: A | U7: ESPN reports LeBron signing (unverified) [sim: playoffs 87%, rd2 52%, conf final 30%] | Y7: =N7-IF(T7="C",Assumptions!$B$27,IF(T7="B",Assumptions!$B$26,0))
A8: New York Knicks | B8: East; win total 52.5 | C8: Kalshi 8.5% | D8: 0.0877 | E8: 0.1787 | F8: 0.3103 | G8: 0.5215 | H8: 0.8491 | I8: 0.5517 | J8: 0.0548 | K8: 7.957 | L8: =Assumptions!$B$3*D8+Assumptions!$C$3*(E8-D8)+Assumptions!$D$3*(F8-E8)+Assumptions!$E$3*(G8-F8)+Assumptions!$F$3*(H8-G8) | M8: =K8+MIN(L8,Assumptions!$H$3) | N8: =M8-Assumptions!$I$3 | O8: =N8-Assumptions!$B$25*Q8 | P8: 2 | Q8: 3.434 | R8: KXNBA-27 exchange mid-price, pulled 2026-10-08; p(final)=KXNBAEAST/KXNBAWEST-27 Kalshi mid | league_sim.py: full-schedule + real playoff bracket Monte Carlo, ratings fitted to Kalshi | S8: 2026-10-08 | T8: A | U8: 2026 champion in this league's data [sim: playoffs 85%, rd2 52%, conf final 31%] | X8: Buckley | Y8: =N8-IF(T8="C",Assumptions!$B$27,IF(T8="B",Assumptions!$B$26,0))
A9: Minnesota Timberwolves | B9: West; win total 48.5 | C9: Kalshi 6.5% | D9: 0.0545 | E9: 0.1032 | F9: 0.2218 | G9: 0.4537 | H9: 0.8287 | I9: 0.5422 | J9: 0.0548 | K9: 7.436 | L9: =Assumptions!$B$3*D9+Assumptions!$C$3*(E9-D9)+Assumptions!$D$3*(F9-E9)+Assumptions!$E$3*(G9-F9)+Assumptions!$F$3*(H9-G9) | M9: =K9+MIN(L9,Assumptions!$H$3) | N9: =M9-Assumptions!$I$3 | O9: =N9-Assumptions!$B$25*Q9 | P9: 2 | Q9: 3.425 | R9: KXNBA-27 exchange mid-price, pulled 2026-10-08; p(final)=KXNBAEAST/KXNBAWEST-27 Kalshi mid | league_sim.py: full-schedule + real playoff bracket Monte Carlo, ratings fitted to Kalshi | S9: 2026-10-08 | T9: A | U9: [sim: playoffs 83%, rd2 45%, conf final 22%] | X9: Todd | Y9: =N9-IF(T9="C",Assumptions!$B$27,IF(T9="B",Assumptions!$B$26,0))
A10: Boston Celtics | B10: East; win total 51.5 | C10: Kalshi 4.5% | D10: 0.0634 | E10: 0.1378 | F10: 0.2507 | G10: 0.4434 | H10: 0.779 | I10: 0.5368 | J10: 0.054 | K10: 7.11 | L10: =Assumptions!$B$3*D10+Assumptions!$C$3*(E10-D10)+Assumptions!$D$3*(F10-E10)+Assumptions!$E$3*(G10-F10)+Assumptions!$F$3*(H10-G10) | M10: =K10+MIN(L10,Assumptions!$H$3) | N10: =M10-Assumptions!$I$3 | O10: =N10-Assumptions!$B$25*Q10 | P10: 2 | Q10: 3.477 | R10: KXNBA-27 exchange mid-price, pulled 2026-10-08; p(final)=KXNBAEAST/KXNBAWEST-27 Kalshi mid | league_sim.py: full-schedule + real playoff bracket Monte Carlo, ratings fitted to Kalshi | S10: 2026-10-08 | T10: A | U10: [sim: playoffs 78%, rd2 44%, conf final 25%] | X10: Shep | Y10: =N10-IF(T10="C",Assumptions!$B$27,IF(T10="B",Assumptions!$B$26,0))
A11: Toronto Raptors | B11: East; win total 45.5 | C11: Kalshi 2.5% | D11: 0.0374 | E11: 0.0906 | F11: 0.1806 | G11: 0.3644 | H11: 0.7145 | I11: 0.5264 | J11: 0.0547 | K11: 6.437 | L11: =Assumptions!$B$3*D11+Assumptions!$C$3*(E11-D11)+Assumptions!$D$3*(F11-E11)+Assumptions!$E$3*(G11-F11)+Assumptions!$F$3*(H11-G11) | M11: =K11+MIN(L11,Assumptions!$H$3) | N11: =M11-Assumptions!$I$3 | O11: =N11-Assumptions!$B$25*Q11 | P11: 2 | Q11: 3.499 | R11: KXNBA-27 exchange mid-price, pulled 2026-10-08; p(final)=KXNBAEAST/KXNBAWEST-27 Kalshi mid | league_sim.py: full-schedule + real playoff bracket Monte Carlo, ratings fitted to Kalshi | S11: 2026-10-08 | T11: A | U11: [sim: playoffs 71%, rd2 36%, conf final 18%] | Y11: =N11-IF(T11="C",Assumptions!$B$27,IF(T11="B",Assumptions!$B$26,0))
A12: Miami Heat | B12: East; win total 46.5 | C12: Kalshi 6.5% | D12: 0.044 | E12: 0.0986 | F12: 0.1886 | G12: 0.3708 | H12: 0.6994 | I12: 0.523 | J12: 0.0542 | K12: 6.252 | L12: =Assumptions!$B$3*D12+Assumptions!$C$3*(E12-D12)+Assumptions!$D$3*(F12-E12)+Assumptions!$E$3*(G12-F12)+Assumptions!$F$3*(H12-G12) | M12: =K12+MIN(L12,Assumptions!$H$3) | N12: =M12-Assumptions!$I$3 | O12: =N12-Assumptions!$B$25*Q12 | P12: 3 | Q12: 3.415 | R12: KXNBA-27 exchange mid-price, pulled 2026-10-08; p(final)=KXNBAEAST/KXNBAWEST-27 Kalshi mid | league_sim.py: full-schedule + real playoff bracket Monte Carlo, ratings fitted to Kalshi | S12: 2026-10-08 | T12: A | U12: [sim: playoffs 70%, rd2 37%, conf final 19%] | Y12: =N12-IF(T12="C",Assumptions!$B$27,IF(T12="B",Assumptions!$B$26,0))
A13: Los Angeles Lakers | B13: West; win total 46.5 | C13: Kalshi 3.5% | D13: 0.0294 | E13: 0.0674 | F13: 0.1611 | G13: 0.3564 | H13: 0.7246 | I13: 0.5224 | J13: 0.055 | K13: 6.17 | L13: =Assumptions!$B$3*D13+Assumptions!$C$3*(E13-D13)+Assumptions!$D$3*(F13-E13)+Assumptions!$E$3*(G13-F13)+Assumptions!$F$3*(H13-G13) | M13: =K13+MIN(L13,Assumptions!$H$3) | N13: =M13-Assumptions!$I$3 | O13: =N13-Assumptions!$B$25*Q13 | P13: 3 | Q13: 3.464 | R13: KXNBA-27 exchange mid-price, pulled 2026-10-08; p(final)=KXNBAEAST/KXNBAWEST-27 Kalshi mid | league_sim.py: full-schedule + real playoff bracket Monte Carlo, ratings fitted to Kalshi | S13: 2026-10-08 | T13: A | U13: [sim: playoffs 72%, rd2 36%, conf final 16%] | X13: Theo | Y13: =N13-IF(T13="C",Assumptions!$B$27,IF(T13="B",Assumptions!$B$26,0))
A14: Detroit Pistons | B14: East; win total 49.5 | C14: +2200 | D14: 0.0318 | E14: 0.079 | F14: 0.1671 | G14: 0.3369 | H14: 0.6786 | I14: 0.5209 | J14: 0.0542 | K14: 6.046 | L14: =Assumptions!$B$3*D14+Assumptions!$C$3*(E14-D14)+Assumptions!$D$3*(F14-E14)+Assumptions!$E$3*(G14-F14)+Assumptions!$F$3*(H14-G14) | M14: =K14+MIN(L14,Assumptions!$H$3) | N14: =M14-Assumptions!$I$3 | O14: =N14-Assumptions!$B$25*Q14 | P14: 3 | Q14: 3.455 | R14: FanDuel ~2026-10-07; Polymarket via Covers; BetMGM win totals; p(final)=KXNBAEAST/KXNBAWEST-27 Kalshi mid | league_sim.py: full-schedule + real playoff bracket Monte Carlo, ratings fitted to Kalshi | S14: 2026-10-08 | T14: A | U14: | price superseded by Kalshi field; p rescaled [sim: playoffs 68%, rd2 34%, conf final 17%] | Y14: =N14-IF(T14="C",Assumptions!$B$27,IF(T14="B",Assumptions!$B$26,0))
A15: Denver Nuggets | B15: West; win total 49.5 | C15: Kalshi 2.5% | D15: 0.031 | E15: 0.0614 | F15: 0.1462 | G15: 0.3292 | H15: 0.6894 | I15: 0.5174 | J15: 0.0553 | K15: 5.834 | L15: =Assumptions!$B$3*D15+Assumptions!$C$3*(E15-D15)+Assumptions!$D$3*(F15-E15)+Assumptions!$E$3*(G15-F15)+Assumptions!$F$3*(H15-G15) | M15: =K15+MIN(L15,Assumptions!$H$3) | N15: =M15-Assumptions!$I$3 | O15: =N15-Assumptions!$B$25*Q15 | P15: 3 | Q15: 3.432 | R15: KXNBA-27 exchange mid-price, pulled 2026-10-08; p(final)=KXNBAEAST/KXNBAWEST-27 Kalshi mid | league_sim.py: full-schedule + real playoff bracket Monte Carlo, ratings fitted to Kalshi | S15: 2026-10-08 | T15: A | U15: [sim: playoffs 69%, rd2 33%, conf final 15%] | X15: Tim | Y15: =N15-IF(T15="C",Assumptions!$B$27,IF(T15="B",Assumptions!$B$26,0))
A16: Houston Rockets | B16: West; win total 47.5 | C16: Kalshi 1.5% | D16: 0.025 | E16: 0.0539 | F16: 0.1411 | G16: 0.3225 | H16: 0.6776 | I16: 0.5151 | J16: 0.0542 | K16: 5.62 | L16: =Assumptions!$B$3*D16+Assumptions!$C$3*(E16-D16)+Assumptions!$D$3*(F16-E16)+Assumptions!$E$3*(G16-F16)+Assumptions!$F$3*(H16-G16) | M16: =K16+MIN(L16,Assumptions!$H$3) | N16: =M16-Assumptions!$I$3 | O16: =N16-Assumptions!$B$25*Q16 | P16: 3 | Q16: 3.399 | R16: KXNBA-27 exchange mid-price, pulled 2026-10-08; p(final)=KXNBAEAST/KXNBAWEST-27 Kalshi mid | league_sim.py: full-schedule + real playoff bracket Monte Carlo, ratings fitted to Kalshi | S16: 2026-10-08 | T16: A | U16: [sim: playoffs 68%, rd2 32%, conf final 14%] | X16: Korch | Y16: =N16-IF(T16="C",Assumptions!$B$27,IF(T16="B",Assumptions!$B$26,0))
A17: Indiana Pacers | B17: East; win total 44.5 | C17: Kalshi 1.5% | D17: 0.0213 | E17: 0.0584 | F17: 0.1331 | G17: 0.2871 | H17: 0.6179 | I17: 0.5114 | J17: 0.0553 | K17: 5.502 | L17: =Assumptions!$B$3*D17+Assumptions!$C$3*(E17-D17)+Assumptions!$D$3*(F17-E17)+Assumptions!$E$3*(G17-F17)+Assumptions!$F$3*(H17-G17) | M17: =K17+MIN(L17,Assumptions!$H$3) | N17: =M17-Assumptions!$I$3 | O17: =N17-Assumptions!$B$25*Q17 | P17: 3 | Q17: 3.389 | R17: KXNBA-27 exchange mid-price, pulled 2026-10-08; p(final)=KXNBAEAST/KXNBAWEST-27 Kalshi mid | league_sim.py: full-schedule + real playoff bracket Monte Carlo, ratings fitted to Kalshi | S17: 2026-10-08 | T17: A | U17: [sim: playoffs 62%, rd2 29%, conf final 13%] | Y17: =N17-IF(T17="C",Assumptions!$B$27,IF(T17="B",Assumptions!$B$26,0))
A18: Cleveland Cavaliers | B18: East; win total 47.5 | C18: Kalshi 2.5% | D18: 0.0199 | E18: 0.0548 | F18: 0.1264 | G18: 0.2739 | H18: 0.5835 | I18: 0.5076 | J18: 0.055 | K18: 5.236 | L18: =Assumptions!$B$3*D18+Assumptions!$C$3*(E18-D18)+Assumptions!$D$3*(F18-E18)+Assumptions!$E$3*(G18-F18)+Assumptions!$F$3*(H18-G18) | M18: =K18+MIN(L18,Assumptions!$H$3) | N18: =M18-Assumptions!$I$3 | O18: =N18-Assumptions!$B$25*Q18 | P18: 4 | Q18: 3.341 | R18: KXNBA-27 exchange mid-price, pulled 2026-10-08; p(final)=KXNBAEAST/KXNBAWEST-27 Kalshi mid | league_sim.py: full-schedule + real playoff bracket Monte Carlo, ratings fitted to Kalshi | S18: 2026-10-08 | T18: A | U18: [sim: playoffs 58%, rd2 27%, conf final 13%] | X18: Jens | Y18: =N18-IF(T18="C",Assumptions!$B$27,IF(T18="B",Assumptions!$B$26,0))
A19: Portland Trail Blazers | B19: West; win total 42.5 | D19: 0.0146 | E19: 0.0372 | F19: 0.0968 | G19: 0.2404 | H19: 0.5713 | I19: 0.4994 | J19: 0.0551 | K19: 4.875 | L19: =Assumptions!$B$3*D19+Assumptions!$C$3*(E19-D19)+Assumptions!$D$3*(F19-E19)+Assumptions!$E$3*(G19-F19)+Assumptions!$F$3*(H19-G19) | M19: =K19+MIN(L19,Assumptions!$H$3) | N19: =M19-Assumptions!$I$3 | O19: =N19-Assumptions!$B$25*Q19 | P19: 4 | Q19: 3.255 | R19: BetMGM win total; title price estimated; p(final)=KXNBAEAST/KXNBAWEST-27 Kalshi mid | league_sim.py: full-schedule + real playoff bracket Monte Carlo, ratings fitted to Kalshi | S19: 2026-10-08 | T19: A | U19: [sim: playoffs 57%, rd2 24%, conf final 10%] | Y19: =N19-IF(T19="C",Assumptions!$B$27,IF(T19="B",Assumptions!$B$26,0))
A20: Atlanta Hawks | B20: East; win total 43.5 | D20: 0.0152 | E20: 0.0396 | F20: 0.0976 | G20: 0.2289 | H20: 0.518 | I20: 0.4974 | J20: 0.055 | K20: 4.635 | L20: =Assumptions!$B$3*D20+Assumptions!$C$3*(E20-D20)+Assumptions!$D$3*(F20-E20)+Assumptions!$E$3*(G20-F20)+Assumptions!$F$3*(H20-G20) | M20: =K20+MIN(L20,Assumptions!$H$3) | N20: =M20-Assumptions!$I$3 | O20: =N20-Assumptions!$B$25*Q20 | P20: 4 | Q20: 3.166 | R20: BetMGM win total; title price estimated | league_sim.py: full-schedule + real playoff bracket Monte Carlo, ratings fitted to Kalshi | S20: 2026-10-08 | T20: A | U20: [sim: playoffs 52%, rd2 23%, conf final 10%] | Y20: =N20-IF(T20="C",Assumptions!$B$27,IF(T20="B",Assumptions!$B$26,0))
A21: Phoenix Suns | B21: West; win total 40.5 | D21: 0.0131 | E21: 0.0311 | F21: 0.0819 | G21: 0.2054 | H21: 0.4994 | I21: 0.4895 | J21: 0.0552 | K21: 4.3 | L21: =Assumptions!$B$3*D21+Assumptions!$C$3*(E21-D21)+Assumptions!$D$3*(F21-E21)+Assumptions!$E$3*(G21-F21)+Assumptions!$F$3*(H21-G21) | M21: =K21+MIN(L21,Assumptions!$H$3) | N21: =M21-Assumptions!$I$3 | O21: =N21-Assumptions!$B$25*Q21 | P21: 4 | Q21: 3.057 | R21: BetMGM win total; title price estimated | league_sim.py: full-schedule + real playoff bracket Monte Carlo, ratings fitted to Kalshi | S21: 2026-10-08 | T21: A | U21: [sim: playoffs 50%, rd2 21%, conf final 8%] | Y21: =N21-IF(T21="C",Assumptions!$B$27,IF(T21="B",Assumptions!$B$26,0))
A22: Orlando Magic | B22: East; win total 43.5 | C22: Kalshi 1.5% | D22: 0.014 | E22: 0.0382 | F22: 0.086 | G22: 0.205 | H22: 0.4606 | I22: 0.4888 | J22: 0.0548 | K22: 4.309 | L22: =Assumptions!$B$3*D22+Assumptions!$C$3*(E22-D22)+Assumptions!$D$3*(F22-E22)+Assumptions!$E$3*(G22-F22)+Assumptions!$F$3*(H22-G22) | M22: =K22+MIN(L22,Assumptions!$H$3) | N22: =M22-Assumptions!$I$3 | O22: =N22-Assumptions!$B$25*Q22 | P22: 4 | Q22: 3.062 | R22: KXNBA-27 exchange mid-price, pulled 2026-10-08; p(final)=KXNBAEAST/KXNBAWEST-27 Kalshi mid | league_sim.py: full-schedule + real playoff bracket Monte Carlo, ratings fitted to Kalshi | S22: 2026-10-08 | T22: A | U22: [sim: playoffs 46%, rd2 20%, conf final 9%] | X22: Jamzee | Y22: =N22-IF(T22="C",Assumptions!$B$27,IF(T22="B",Assumptions!$B$26,0))
A23: Dallas Mavericks | B23: West; win total 34.5 | D23: 0.0083 | E23: 0.0221 | F23: 0.0629 | G23: 0.165 | H23: 0.4098 | I23: 0.476 | J23: 0.0548 | K23: 3.705 | L23: =Assumptions!$B$3*D23+Assumptions!$C$3*(E23-D23)+Assumptions!$D$3*(F23-E23)+Assumptions!$E$3*(G23-F23)+Assumptions!$F$3*(H23-G23) | M23: =K23+MIN(L23,Assumptions!$H$3) | N23: =M23-Assumptions!$I$3 | O23: =N23-Assumptions!$B$25*Q23 | P23: 4 | Q23: 2.839 | R23: BetMGM win total; title price estimated | league_sim.py: full-schedule + real playoff bracket Monte Carlo, ratings fitted to Kalshi | S23: 2026-10-08 | T23: A | U23: [sim: playoffs 41%, rd2 16%, conf final 6%] | Y23: =N23-IF(T23="C",Assumptions!$B$27,IF(T23="B",Assumptions!$B$26,0))
A24: Washington Wizards | B24: East; win total 34.5 | D24: 0.0067 | E24: 0.0211 | F24: 0.0534 | G24: 0.1457 | H24: 0.3741 | I24: 0.4783 | J24: 0.0544 | K24: 3.774 | L24: =Assumptions!$B$3*D24+Assumptions!$C$3*(E24-D24)+Assumptions!$D$3*(F24-E24)+Assumptions!$E$3*(G24-F24)+Assumptions!$F$3*(H24-G24) | M24: =K24+MIN(L24,Assumptions!$H$3) | N24: =M24-Assumptions!$I$3 | O24: =N24-Assumptions!$B$25*Q24 | P24: 4 | Q24: 2.851 | R24: BetMGM win total; title price estimated | league_sim.py: full-schedule + real playoff bracket Monte Carlo, ratings fitted to Kalshi | S24: 2026-10-08 | T24: A | U24: [sim: playoffs 37%, rd2 15%, conf final 5%] | Y24: =N24-IF(T24="C",Assumptions!$B$27,IF(T24="B",Assumptions!$B$26,0))
A25: Charlotte Hornets | B25: East; win total 39.5 | D25: 0.0036 | E25: 0.0173 | F25: 0.0485 | G25: 0.1232 | H25: 0.3285 | I25: 0.4722 | J25: 0.0544 | K25: 3.569 | L25: =Assumptions!$B$3*D25+Assumptions!$C$3*(E25-D25)+Assumptions!$D$3*(F25-E25)+Assumptions!$E$3*(G25-F25)+Assumptions!$F$3*(H25-G25) | M25: =K25+MIN(L25,Assumptions!$H$3) | N25: =M25-Assumptions!$I$3 | O25: =N25-Assumptions!$B$25*Q25 | P25: 4 | Q25: 2.773 | R25: BetMGM win total; title price estimated | league_sim.py: full-schedule + real playoff bracket Monte Carlo, ratings fitted to Kalshi | S25: 2026-10-08 | T25: A | U25: [sim: playoffs 33%, rd2 12%, conf final 5%] | Y25: =N25-IF(T25="C",Assumptions!$B$27,IF(T25="B",Assumptions!$B$26,0))
A26: Utah Jazz | B26: West; win total 37.5 | D26: 0.0063 | E26: 0.0146 | F26: 0.0454 | G26: 0.13 | H26: 0.3606 | I26: 0.4694 | J26: 0.055 | K26: 3.465 | L26: =Assumptions!$B$3*D26+Assumptions!$C$3*(E26-D26)+Assumptions!$D$3*(F26-E26)+Assumptions!$E$3*(G26-F26)+Assumptions!$F$3*(H26-G26) | M26: =K26+MIN(L26,Assumptions!$H$3) | N26: =M26-Assumptions!$I$3 | O26: =N26-Assumptions!$B$25*Q26 | P26: 4 | Q26: 2.766 | R26: BetMGM win total; title price estimated; p(final)=KXNBAEAST/KXNBAWEST-27 Kalshi mid | league_sim.py: full-schedule + real playoff bracket Monte Carlo, ratings fitted to Kalshi | S26: 2026-10-08 | T26: A | U26: [sim: playoffs 36%, rd2 13%, conf final 5%] | Y26: =N26-IF(T26="C",Assumptions!$B$27,IF(T26="B",Assumptions!$B$26,0))
A27: Golden State Warriors | B27: West; win total 40.5 | D27: 0.0054 | E27: 0.015 | F27: 0.0451 | G27: 0.1326 | H27: 0.3566 | I27: 0.4692 | J27: 0.0544 | K27: 3.465 | L27: =Assumptions!$B$3*D27+Assumptions!$C$3*(E27-D27)+Assumptions!$D$3*(F27-E27)+Assumptions!$E$3*(G27-F27)+Assumptions!$F$3*(H27-G27) | M27: =K27+MIN(L27,Assumptions!$H$3) | N27: =M27-Assumptions!$I$3 | O27: =N27-Assumptions!$B$25*Q27 | P27: 4 | Q27: 2.787 | R27: BetMGM win total; title price estimated; p(final)=KXNBAEAST/KXNBAWEST-27 Kalshi mid | league_sim.py: full-schedule + real playoff bracket Monte Carlo, ratings fitted to Kalshi | S27: 2026-10-08 | T27: A | U27: [sim: playoffs 36%, rd2 13%, conf final 5%] | X27: Mitchell | Y27: =N27-IF(T27="C",Assumptions!$B$27,IF(T27="B",Assumptions!$B$26,0))
A28: Memphis Grizzlies | B28: West; win total 29.5 | D28: 0.0039 | E28: 0.009 | F28: 0.0296 | G28: 0.0929 | H28: 0.3071 | I28: 0.4612 | J28: 0.0542 | K28: 3.076 | L28: =Assumptions!$B$3*D28+Assumptions!$C$3*(E28-D28)+Assumptions!$D$3*(F28-E28)+Assumptions!$E$3*(G28-F28)+Assumptions!$F$3*(H28-G28) | M28: =K28+MIN(L28,Assumptions!$H$3) | N28: =M28-Assumptions!$I$3 | O28: =N28-Assumptions!$B$25*Q28 | P28: 4 | Q28: 2.512 | R28: BetMGM win total; title price estimated | league_sim.py: full-schedule + real playoff bracket Monte Carlo, ratings fitted to Kalshi | S28: 2026-10-08 | T28: A | U28: [sim: playoffs 31%, rd2 9%, conf final 3%] | Y28: =N28-IF(T28="C",Assumptions!$B$27,IF(T28="B",Assumptions!$B$26,0))
A29: Los Angeles Clippers | B29: West; win total 30.5 | D29: 0.0026 | E29: 0.0076 | F29: 0.0261 | G29: 0.0828 | H29: 0.252 | I29: 0.4531 | J29: 0.0548 | K29: 2.754 | L29: =Assumptions!$B$3*D29+Assumptions!$C$3*(E29-D29)+Assumptions!$D$3*(F29-E29)+Assumptions!$E$3*(G29-F29)+Assumptions!$F$3*(H29-G29) | M29: =K29+MIN(L29,Assumptions!$H$3) | N29: =M29-Assumptions!$I$3 | O29: =N29-Assumptions!$B$25*Q29 | P29: 4 | Q29: 2.295 | R29: BetMGM win total; title price estimated | league_sim.py: full-schedule + real playoff bracket Monte Carlo, ratings fitted to Kalshi | S29: 2026-10-08 | T29: A | U29: [sim: playoffs 25%, rd2 8%, conf final 3%] | X29: Fryar | Y29: =N29-IF(T29="C",Assumptions!$B$27,IF(T29="B",Assumptions!$B$26,0))
A30: New Orleans Pelicans | B30: West; win total 27.5 | D30: 0.0034 | E30: 0.0096 | F30: 0.0295 | G30: 0.0801 | H30: 0.2375 | I30: 0.4502 | J30: 0.0543 | K30: 2.652 | L30: =Assumptions!$B$3*D30+Assumptions!$C$3*(E30-D30)+Assumptions!$D$3*(F30-E30)+Assumptions!$E$3*(G30-F30)+Assumptions!$F$3*(H30-G30) | M30: =K30+MIN(L30,Assumptions!$H$3) | N30: =M30-Assumptions!$I$3 | O30: =N30-Assumptions!$B$25*Q30 | P30: 4 | Q30: 2.265 | R30: BetMGM win total; title price estimated | league_sim.py: full-schedule + real playoff bracket Monte Carlo, ratings fitted to Kalshi | S30: 2026-10-08 | T30: A | U30: [sim: playoffs 24%, rd2 8%, conf final 3%] | Y30: =N30-IF(T30="C",Assumptions!$B$27,IF(T30="B",Assumptions!$B$26,0))
A31: Brooklyn Nets | B31: East; win total 24.5 | D31: 0.0035 | E31: 0.0089 | F31: 0.0275 | G31: 0.075 | H31: 0.1956 | I31: 0.4477 | J31: 0.0546 | K31: 2.634 | L31: =Assumptions!$B$3*D31+Assumptions!$C$3*(E31-D31)+Assumptions!$D$3*(F31-E31)+Assumptions!$E$3*(G31-F31)+Assumptions!$F$3*(H31-G31) | M31: =K31+MIN(L31,Assumptions!$H$3) | N31: =M31-Assumptions!$I$3 | O31: =N31-Assumptions!$B$25*Q31 | P31: 4 | Q31: 2.241 | R31: BetMGM win total; title price estimated | league_sim.py: full-schedule + real playoff bracket Monte Carlo, ratings fitted to Kalshi | S31: 2026-10-08 | T31: A | U31: [sim: playoffs 20%, rd2 8%, conf final 3%] | Y31: =N31-IF(T31="C",Assumptions!$B$27,IF(T31="B",Assumptions!$B$26,0))
A32: Chicago Bulls | B32: East; win total 29.5 | D32: 0.0018 | E32: 0.006 | F32: 0.0181 | G32: 0.0584 | H32: 0.17 | I32: 0.4431 | J32: 0.0544 | K32: 2.412 | L32: =Assumptions!$B$3*D32+Assumptions!$C$3*(E32-D32)+Assumptions!$D$3*(F32-E32)+Assumptions!$E$3*(G32-F32)+Assumptions!$F$3*(H32-G32) | M32: =K32+MIN(L32,Assumptions!$H$3) | N32: =M32-Assumptions!$I$3 | O32: =N32-Assumptions!$B$25*Q32 | P32: 4 | Q32: 2.108 | R32: BetMGM win total; title price estimated | league_sim.py: full-schedule + real playoff bracket Monte Carlo, ratings fitted to Kalshi | S32: 2026-10-08 | T32: A | U32: [sim: playoffs 17%, rd2 6%, conf final 2%] | Y32: =N32-IF(T32="C",Assumptions!$B$27,IF(T32="B",Assumptions!$B$26,0))
A33: Milwaukee Bucks | B33: East; win total 25.5 | D33: 0.0018 | E33: 0.0065 | F33: 0.0166 | G33: 0.0495 | H33: 0.1581 | I33: 0.4405 | J33: 0.0542 | K33: 2.38 | L33: =Assumptions!$B$3*D33+Assumptions!$C$3*(E33-D33)+Assumptions!$D$3*(F33-E33)+Assumptions!$E$3*(G33-F33)+Assumptions!$F$3*(H33-G33) | M33: =K33+MIN(L33,Assumptions!$H$3) | N33: =M33-Assumptions!$I$3 | O33: =N33-Assumptions!$B$25*Q33 | P33: 4 | Q33: 2.018 | R33: BetMGM win total; title price estimated | league_sim.py: full-schedule + real playoff bracket Monte Carlo, ratings fitted to Kalshi | S33: 2026-10-08 | T33: A | U33: [sim: playoffs 16%, rd2 5%, conf final 2%] | X33: Molmen | Y33: =N33-IF(T33="C",Assumptions!$B$27,IF(T33="B",Assumptions!$B$26,0))
A34: Sacramento Kings | B34: West; win total 21.5 | D34: 0.0005 | E34: 0.0025 | F34: 0.0101 | G34: 0.0386 | H34: 0.1388 | I34: 0.4285 | J34: 0.0547 | K34: 2.083 | L34: =Assumptions!$B$3*D34+Assumptions!$C$3*(E34-D34)+Assumptions!$D$3*(F34-E34)+Assumptions!$E$3*(G34-F34)+Assumptions!$F$3*(H34-G34) | M34: =K34+MIN(L34,Assumptions!$H$3) | N34: =M34-Assumptions!$I$3 | O34: =N34-Assumptions!$B$25*Q34 | P34: 4 | Q34: 1.797 | R34: BetMGM win total; title price estimated | league_sim.py: full-schedule + real playoff bracket Monte Carlo, ratings fitted to Kalshi | S34: 2026-10-08 | T34: A | U34: [sim: playoffs 14%, rd2 4%, conf final 1%] | Y34: =N34-IF(T34="C",Assumptions!$B$27,IF(T34="B",Assumptions!$B$26,0))
A36: Replacement-level EV (Nth best)

Sheet MLB
A1: MLB — 2027 draft research (EV model; see README)
A2: As of 2026-10-22. Sorted by E[total]. Yellow = inferred / low-confidence (C).
A4: Candidate | B4: Detail | C4: Odds / price | D4: p(champ) | E4: p(final) | F4: p(semi) | G4: p(quarter) | H4: p(rd 1) | I4: mu | J4: sd | K4: E[rank pts] (MC) | L4: E[bonus] | M4: E[total] | N4: VOR | O4: Risk-adj VOR | P4: Tier | Q4: SD rank pts | R4: Source | S4: As of | T4: Conf | U4: Notes | V4: Field draft score | W4: Field rank | X4: Owner | Y4: Conf-adj VOR
A5: Los Angeles Dodgers | B5: 2026: 100-62 (.6173) | D5: 0.0902 | E5: 0.1804 | F5: 0.3608 | G5: 0.7216 | H5: 0.97 | I5: 0.54 | J5: 0.1 | K5: 7.524 | L5: =Assumptions!$B$4*D5+Assumptions!$C$4*(E5-D5)+Assumptions!$D$4*(F5-E5)+Assumptions!$E$4*(G5-F5)+Assumptions!$F$4*(H5-G5) | M5: =K5+MIN(L5,Assumptions!$H$4) | N5: =M5-Assumptions!$I$4 | O5: =N5-Assumptions!$B$25*Q5 | P5: 1 | Q5: 3.676 | R5: 2026 win% from league standings (A); title prob = model estimate — no 2027 World Series odds posted | S5: 2026-10-08 | T5: C | U5: 2026 playoffs still in progress [v2 certainty adj: sd x2.0, mu shrink 50%, p shrink 50%] | X5: Wu | Y5: =N5-IF(T5="C",Assumptions!$B$27,IF(T5="B",Assumptions!$B$26,0))
A6: Milwaukee Brewers | B6: 2026: 103-59 (.6358) | D6: 0.0559 | E6: 0.1118 | F6: 0.2236 | G6: 0.4472 | H6: 0.8944 | I6: 0.5442 | J6: 0.1 | K6: 7.601 | L6: =Assumptions!$B$4*D6+Assumptions!$C$4*(E6-D6)+Assumptions!$D$4*(F6-E6)+Assumptions!$E$4*(G6-F6)+Assumptions!$F$4*(H6-G6) | M6: =K6+MIN(L6,Assumptions!$H$4) | N6: =M6-Assumptions!$I$4 | O6: =N6-Assumptions!$B$25*Q6 | P6: 1 | Q6: 3.719 | R6: 2026 win% from league standings (A); title prob = model estimate — no 2027 World Series odds posted | S6: 2026-10-08 | T6: C | U6: 2026 playoffs still in progress [v2 certainty adj: sd x2.0, mu shrink 50%, p shrink 50%] | X6: Buckley | Y6: =N6-IF(T6="C",Assumptions!$B$27,IF(T6="B",Assumptions!$B$26,0))
A7: New York Yankees | B7: 2026: 94-68 (.5776) | D7: 0.0559 | E7: 0.1118 | F7: 0.2236 | G7: 0.4472 | H7: 0.8944 | I7: 0.5311 | J7: 0.1 | K7: 7.183 | L7: =Assumptions!$B$4*D7+Assumptions!$C$4*(E7-D7)+Assumptions!$D$4*(F7-E7)+Assumptions!$E$4*(G7-F7)+Assumptions!$F$4*(H7-G7) | M7: =K7+MIN(L7,Assumptions!$H$4) | N7: =M7-Assumptions!$I$4 | O7: =N7-Assumptions!$B$25*Q7 | P7: 1 | Q7: 3.758 | R7: 2026 win% from league standings (A); title prob = model estimate — no 2027 World Series odds posted | S7: 2026-10-08 | T7: C | U7: 2026 playoffs still in progress [v2 certainty adj: sd x2.0, mu shrink 50%, p shrink 50%] | X7: Jens | Y7: =N7-IF(T7="C",Assumptions!$B$27,IF(T7="B",Assumptions!$B$26,0))
A8: Atlanta Braves | B8: 2026: 94-68 (.5802) | D8: 0.0485 | E8: 0.097 | F8: 0.194 | G8: 0.388 | H8: 0.776 | I8: 0.5317 | J8: 0.1 | K8: 7.106 | L8: =Assumptions!$B$4*D8+Assumptions!$C$4*(E8-D8)+Assumptions!$D$4*(F8-E8)+Assumptions!$E$4*(G8-F8)+Assumptions!$F$4*(H8-G8) | M8: =K8+MIN(L8,Assumptions!$H$4) | N8: =M8-Assumptions!$I$4 | O8: =N8-Assumptions!$B$25*Q8 | P8: 2 | Q8: 3.73 | R8: 2026 win% from league standings (A); title prob = model estimate — no 2027 World Series odds posted | S8: 2026-10-08 | T8: C | U8: 2026 playoffs still in progress [v2 certainty adj: sd x2.0, mu shrink 50%, p shrink 50%] | X8: Todd | Y8: =N8-IF(T8="C",Assumptions!$B$27,IF(T8="B",Assumptions!$B$26,0))
A9: Tampa Bay Rays | B9: 2026: 98-64 (.6049) | D9: 0.0436 | E9: 0.0872 | F9: 0.1744 | G9: 0.3488 | H9: 0.6976 | I9: 0.5372 | J9: 0.1 | K9: 7.329 | L9: =Assumptions!$B$4*D9+Assumptions!$C$4*(E9-D9)+Assumptions!$D$4*(F9-E9)+Assumptions!$E$4*(G9-F9)+Assumptions!$F$4*(H9-G9) | M9: =K9+MIN(L9,Assumptions!$H$4) | N9: =M9-Assumptions!$I$4 | O9: =N9-Assumptions!$B$25*Q9 | P9: 2 | Q9: 3.704 | R9: 2026 win% from league standings (A); title prob = model estimate — no 2027 World Series odds posted | S9: 2026-10-08 | T9: C | U9: 2026 playoffs still in progress [v2 certainty adj: sd x2.0, mu shrink 50%, p shrink 50%] | Y9: =N9-IF(T9="C",Assumptions!$B$27,IF(T9="B",Assumptions!$B$26,0))
A10: Chicago Cubs | B10: 2026: 89-73 (.5494) | D10: 0.0412 | E10: 0.0824 | F10: 0.1648 | G10: 0.3296 | H10: 0.6592 | I10: 0.5247 | J10: 0.1 | K10: 6.979 | L10: =Assumptions!$B$4*D10+Assumptions!$C$4*(E10-D10)+Assumptions!$D$4*(F10-E10)+Assumptions!$E$4*(G10-F10)+Assumptions!$F$4*(H10-G10) | M10: =K10+MIN(L10,Assumptions!$H$4) | N10: =M10-Assumptions!$I$4 | O10: =N10-Assumptions!$B$25*Q10 | P10: 2 | Q10: 3.728 | R10: 2026 win% from league standings (A); title prob = model estimate — no 2027 World Series odds posted | S10: 2026-10-08 | T10: C | U10: 2026 playoffs still in progress [v2 certainty adj: sd x2.0, mu shrink 50%, p shrink 50%] | X10: Tim | Y10: =N10-IF(T10="C",Assumptions!$B$27,IF(T10="B",Assumptions!$B$26,0))
A11: San Diego Padres | B11: 2026: 91-71 (.5617) | D11: 0.0412 | E11: 0.0824 | F11: 0.1648 | G11: 0.3296 | H11: 0.6592 | I11: 0.5275 | J11: 0.1 | K11: 6.97 | L11: =Assumptions!$B$4*D11+Assumptions!$C$4*(E11-D11)+Assumptions!$D$4*(F11-E11)+Assumptions!$E$4*(G11-F11)+Assumptions!$F$4*(H11-G11) | M11: =K11+MIN(L11,Assumptions!$H$4) | N11: =M11-Assumptions!$I$4 | O11: =N11-Assumptions!$B$25*Q11 | P11: 2 | Q11: 3.741 | R11: 2026 win% from league standings (A); title prob = model estimate — no 2027 World Series odds posted | S11: 2026-10-08 | T11: C | U11: 2026 playoffs still in progress [v2 certainty adj: sd x2.0, mu shrink 50%, p shrink 50%] | X11: Theo | Y11: =N11-IF(T11="C",Assumptions!$B$27,IF(T11="B",Assumptions!$B$26,0))
A12: Philadelphia Phillies | B12: 2026: 88-74 (.5432) | D12: 0.0412 | E12: 0.0824 | F12: 0.1648 | G12: 0.3296 | H12: 0.6592 | I12: 0.5233 | J12: 0.1 | K12: 6.929 | L12: =Assumptions!$B$4*D12+Assumptions!$C$4*(E12-D12)+Assumptions!$D$4*(F12-E12)+Assumptions!$E$4*(G12-F12)+Assumptions!$F$4*(H12-G12) | M12: =K12+MIN(L12,Assumptions!$H$4) | N12: =M12-Assumptions!$I$4 | O12: =N12-Assumptions!$B$25*Q12 | P12: 3 | Q12: 3.76 | R12: 2026 win% from league standings (A); title prob = model estimate — no 2027 World Series odds posted | S12: 2026-10-08 | T12: C | U12: 2026 playoffs still in progress [v2 certainty adj: sd x2.0, mu shrink 50%, p shrink 50%] | X12: Mitchell | Y12: =N12-IF(T12="C",Assumptions!$B$27,IF(T12="B",Assumptions!$B$26,0))
A13: Boston Red Sox | B13: 2026: 87-75 (.5370) | D13: 0.0387 | E13: 0.0774 | F13: 0.1548 | G13: 0.3096 | H13: 0.6192 | I13: 0.522 | J13: 0.1 | K13: 6.821 | L13: =Assumptions!$B$4*D13+Assumptions!$C$4*(E13-D13)+Assumptions!$D$4*(F13-E13)+Assumptions!$E$4*(G13-F13)+Assumptions!$F$4*(H13-G13) | M13: =K13+MIN(L13,Assumptions!$H$4) | N13: =M13-Assumptions!$I$4 | O13: =N13-Assumptions!$B$25*Q13 | P13: 3 | Q13: 3.746 | R13: 2026 win% from league standings (A); title prob = model estimate — no 2027 World Series odds posted | S13: 2026-10-08 | T13: C | U13: 2026 playoffs still in progress [v2 certainty adj: sd x2.0, mu shrink 50%, p shrink 50%] | Y13: =N13-IF(T13="C",Assumptions!$B$27,IF(T13="B",Assumptions!$B$26,0))
A14: Arizona Diamondbacks | B14: 2026: 86-76 (.5309) | D14: 0.0314 | E14: 0.0628 | F14: 0.1256 | G14: 0.2512 | H14: 0.5024 | I14: 0.5206 | J14: 0.1 | K14: 6.766 | L14: =Assumptions!$B$4*D14+Assumptions!$C$4*(E14-D14)+Assumptions!$D$4*(F14-E14)+Assumptions!$E$4*(G14-F14)+Assumptions!$F$4*(H14-G14) | M14: =K14+MIN(L14,Assumptions!$H$4) | N14: =M14-Assumptions!$I$4 | O14: =N14-Assumptions!$B$25*Q14 | P14: 3 | Q14: 3.726 | R14: 2026 win% from league standings (A); title prob = model estimate — no 2027 World Series odds posted | S14: 2026-10-08 | T14: C | U14: 2026 playoffs still in progress [v2 certainty adj: sd x2.0, mu shrink 50%, p shrink 50%] | Y14: =N14-IF(T14="C",Assumptions!$B$27,IF(T14="B",Assumptions!$B$26,0))
A15: Cleveland Guardians | B15: 2026: 85-77 (.5247) | D15: 0.0289 | E15: 0.0578 | F15: 0.1156 | G15: 0.2312 | H15: 0.4624 | I15: 0.5192 | J15: 0.1 | K15: 6.718 | L15: =Assumptions!$B$4*D15+Assumptions!$C$4*(E15-D15)+Assumptions!$D$4*(F15-E15)+Assumptions!$E$4*(G15-F15)+Assumptions!$F$4*(H15-G15) | M15: =K15+MIN(L15,Assumptions!$H$4) | N15: =M15-Assumptions!$I$4 | O15: =N15-Assumptions!$B$25*Q15 | P15: 3 | Q15: 3.723 | R15: 2026 win% from league standings (A); title prob = model estimate — no 2027 World Series odds posted | S15: 2026-10-08 | T15: C | U15: 2026 playoffs still in progress [v2 certainty adj: sd x2.0, mu shrink 50%, p shrink 50%] | X15: Fryar | Y15: =N15-IF(T15="C",Assumptions!$B$27,IF(T15="B",Assumptions!$B$26,0))
A16: Pittsburgh Pirates | B16: 2026: 82-80 (.5062) | D16: 0.0314 | E16: 0.0628 | F16: 0.1256 | G16: 0.2512 | H16: 0.5024 | I16: 0.515 | J16: 0.1 | K16: 6.536 | L16: =Assumptions!$B$4*D16+Assumptions!$C$4*(E16-D16)+Assumptions!$D$4*(F16-E16)+Assumptions!$E$4*(G16-F16)+Assumptions!$F$4*(H16-G16) | M16: =K16+MIN(L16,Assumptions!$H$4) | N16: =M16-Assumptions!$I$4 | O16: =N16-Assumptions!$B$25*Q16 | P16: 3 | Q16: 3.702 | R16: 2026 win% from league standings (A); title prob = model estimate — no 2027 World Series odds posted | S16: 2026-10-08 | T16: C | U16: 2026 playoffs still in progress [v2 certainty adj: sd x2.0, mu shrink 50%, p shrink 50%] | Y16: =N16-IF(T16="C",Assumptions!$B$27,IF(T16="B",Assumptions!$B$26,0))
A17: Toronto Blue Jays | B17: 2026: 79-83 (.4877) | D17: 0.0314 | E17: 0.0628 | F17: 0.1256 | G17: 0.2512 | H17: 0.5024 | I17: 0.5109 | J17: 0.1 | K17: 6.438 | L17: =Assumptions!$B$4*D17+Assumptions!$C$4*(E17-D17)+Assumptions!$D$4*(F17-E17)+Assumptions!$E$4*(G17-F17)+Assumptions!$F$4*(H17-G17) | M17: =K17+MIN(L17,Assumptions!$H$4) | N17: =M17-Assumptions!$I$4 | O17: =N17-Assumptions!$B$25*Q17 | P17: 3 | Q17: 3.715 | R17: 2026 win% from league standings (A); title prob = model estimate — no 2027 World Series odds posted | S17: 2026-10-08 | T17: C | U17: 2026 playoffs still in progress [v2 certainty adj: sd x2.0, mu shrink 50%, p shrink 50%] | X17: Korch | Y17: =N17-IF(T17="C",Assumptions!$B$27,IF(T17="B",Assumptions!$B$26,0))
A18: Baltimore Orioles | B18: 2026: 79-83 (.4907) | D18: 0.0314 | E18: 0.0628 | F18: 0.1256 | G18: 0.2512 | H18: 0.5024 | I18: 0.5115 | J18: 0.1 | K18: 6.401 | L18: =Assumptions!$B$4*D18+Assumptions!$C$4*(E18-D18)+Assumptions!$D$4*(F18-E18)+Assumptions!$E$4*(G18-F18)+Assumptions!$F$4*(H18-G18) | M18: =K18+MIN(L18,Assumptions!$H$4) | N18: =M18-Assumptions!$I$4 | O18: =N18-Assumptions!$B$25*Q18 | P18: 4 | Q18: 3.735 | R18: 2026 win% from league standings (A); title prob = model estimate — no 2027 World Series odds posted | S18: 2026-10-08 | T18: C | U18: 2026 playoffs still in progress [v2 certainty adj: sd x2.0, mu shrink 50%, p shrink 50%] | Y18: =N18-IF(T18="C",Assumptions!$B$27,IF(T18="B",Assumptions!$B$26,0))
A19: New York Mets | B19: 2026: 74-88 (.4568) | D19: 0.0338 | E19: 0.0676 | F19: 0.1352 | G19: 0.2704 | H19: 0.5408 | I19: 0.5039 | J19: 0.1 | K19: 6.225 | L19: =Assumptions!$B$4*D19+Assumptions!$C$4*(E19-D19)+Assumptions!$D$4*(F19-E19)+Assumptions!$E$4*(G19-F19)+Assumptions!$F$4*(H19-G19) | M19: =K19+MIN(L19,Assumptions!$H$4) | N19: =M19-Assumptions!$I$4 | O19: =N19-Assumptions!$B$25*Q19 | P19: 4 | Q19: 3.697 | R19: 2026 win% from league standings (A); title prob = model estimate — no 2027 World Series odds posted | S19: 2026-10-08 | T19: C | U19: 2026 playoffs still in progress [v2 certainty adj: sd x2.0, mu shrink 50%, p shrink 50%] | X19: Feder | Y19: =N19-IF(T19="C",Assumptions!$B$27,IF(T19="B",Assumptions!$B$26,0))
A20: Houston Astros | B20: 2026: 81-81 (.5000) | D20: 0.0289 | E20: 0.0578 | F20: 0.1156 | G20: 0.2312 | H20: 0.4624 | I20: 0.5136 | J20: 0.1 | K20: 6.489 | L20: =Assumptions!$B$4*D20+Assumptions!$C$4*(E20-D20)+Assumptions!$D$4*(F20-E20)+Assumptions!$E$4*(G20-F20)+Assumptions!$F$4*(H20-G20) | M20: =K20+MIN(L20,Assumptions!$H$4) | N20: =M20-Assumptions!$I$4 | O20: =N20-Assumptions!$B$25*Q20 | P20: 4 | Q20: 3.691 | R20: 2026 win% from league standings (A); title prob = model estimate — no 2027 World Series odds posted | S20: 2026-10-08 | T20: C | U20: 2026 playoffs still in progress [v2 certainty adj: sd x2.0, mu shrink 50%, p shrink 50%] | X20: Shep | Y20: =N20-IF(T20="C",Assumptions!$B$27,IF(T20="B",Assumptions!$B$26,0))
A21: Chicago White Sox | B21: 2026: 84-78 (.5185) | D21: 0.0265 | E21: 0.053 | F21: 0.106 | G21: 0.212 | H21: 0.424 | I21: 0.5178 | J21: 0.1 | K21: 6.657 | L21: =Assumptions!$B$4*D21+Assumptions!$C$4*(E21-D21)+Assumptions!$D$4*(F21-E21)+Assumptions!$E$4*(G21-F21)+Assumptions!$F$4*(H21-G21) | M21: =K21+MIN(L21,Assumptions!$H$4) | N21: =M21-Assumptions!$I$4 | O21: =N21-Assumptions!$B$25*Q21 | P21: 4 | Q21: 3.741 | R21: 2026 win% from league standings (A); title prob = model estimate — no 2027 World Series odds posted | S21: 2026-10-08 | T21: C | U21: 2026 playoffs still in progress [v2 certainty adj: sd x2.0, mu shrink 50%, p shrink 50%] | Y21: =N21-IF(T21="C",Assumptions!$B$27,IF(T21="B",Assumptions!$B$26,0))
A22: Texas Rangers | B22: 2026: 80-82 (.4938) | D22: 0.0289 | E22: 0.0578 | F22: 0.1156 | G22: 0.2312 | H22: 0.4624 | I22: 0.5122 | J22: 0.1 | K22: 6.448 | L22: =Assumptions!$B$4*D22+Assumptions!$C$4*(E22-D22)+Assumptions!$D$4*(F22-E22)+Assumptions!$E$4*(G22-F22)+Assumptions!$F$4*(H22-G22) | M22: =K22+MIN(L22,Assumptions!$H$4) | N22: =M22-Assumptions!$I$4 | O22: =N22-Assumptions!$B$25*Q22 | P22: 4 | Q22: 3.74 | R22: 2026 win% from league standings (A); title prob = model estimate — no 2027 World Series odds posted | S22: 2026-10-08 | T22: C | U22: 2026 playoffs still in progress [v2 certainty adj: sd x2.0, mu shrink 50%, p shrink 50%] | X22: Molmen | Y22: =N22-IF(T22="C",Assumptions!$B$27,IF(T22="B",Assumptions!$B$26,0))
A23: Seattle Mariners | B23: 2026: 76-86 (.4691) | D23: 0.0314 | E23: 0.0628 | F23: 0.1256 | G23: 0.2512 | H23: 0.5024 | I23: 0.5067 | J23: 0.1 | K23: 6.238 | L23: =Assumptions!$B$4*D23+Assumptions!$C$4*(E23-D23)+Assumptions!$D$4*(F23-E23)+Assumptions!$E$4*(G23-F23)+Assumptions!$F$4*(H23-G23) | M23: =K23+MIN(L23,Assumptions!$H$4) | N23: =M23-Assumptions!$I$4 | O23: =N23-Assumptions!$B$25*Q23 | P23: 4 | Q23: 3.682 | R23: 2026 win% from league standings (A); title prob = model estimate — no 2027 World Series odds posted | S23: 2026-10-08 | T23: C | U23: 2026 playoffs still in progress [v2 certainty adj: sd x2.0, mu shrink 50%, p shrink 50%] | X23: Jamzee | Y23: =N23-IF(T23="C",Assumptions!$B$27,IF(T23="B",Assumptions!$B$26,0))
A24: Detroit Tigers | B24: 2026: 76-86 (.4691) | D24: 0.0289 | E24: 0.0578 | F24: 0.1156 | G24: 0.2312 | H24: 0.4624 | I24: 0.5067 | J24: 0.1 | K24: 6.278 | L24: =Assumptions!$B$4*D24+Assumptions!$C$4*(E24-D24)+Assumptions!$D$4*(F24-E24)+Assumptions!$E$4*(G24-F24)+Assumptions!$F$4*(H24-G24) | M24: =K24+MIN(L24,Assumptions!$H$4) | N24: =M24-Assumptions!$I$4 | O24: =N24-Assumptions!$B$25*Q24 | P24: 4 | Q24: 3.71 | R24: 2026 win% from league standings (A); title prob = model estimate — no 2027 World Series odds posted | S24: 2026-10-08 | T24: C | U24: 2026 playoffs still in progress [v2 certainty adj: sd x2.0, mu shrink 50%, p shrink 50%] | Y24: =N24-IF(T24="C",Assumptions!$B$27,IF(T24="B",Assumptions!$B$26,0))
A25: Miami Marlins | B25: 2026: 80-82 (.4938) | D25: 0.0226 | E25: 0.0452 | F25: 0.0904 | G25: 0.1808 | H25: 0.3616 | I25: 0.5122 | J25: 0.1 | K25: 6.428 | L25: =Assumptions!$B$4*D25+Assumptions!$C$4*(E25-D25)+Assumptions!$D$4*(F25-E25)+Assumptions!$E$4*(G25-F25)+Assumptions!$F$4*(H25-G25) | M25: =K25+MIN(L25,Assumptions!$H$4) | N25: =M25-Assumptions!$I$4 | O25: =N25-Assumptions!$B$25*Q25 | P25: 4 | Q25: 3.753 | R25: 2026 win% from league standings (A); title prob = model estimate — no 2027 World Series odds posted | S25: 2026-10-08 | T25: C | U25: 2026 playoffs still in progress [v2 certainty adj: sd x2.0, mu shrink 50%, p shrink 50%] | Y25: =N25-IF(T25="C",Assumptions!$B$27,IF(T25="B",Assumptions!$B$26,0))
A26: Cincinnati Reds | B26: 2026: 75-87 (.4630) | D26: 0.024 | E26: 0.048 | F26: 0.096 | G26: 0.192 | H26: 0.384 | I26: 0.5053 | J26: 0.1 | K26: 6.207 | L26: =Assumptions!$B$4*D26+Assumptions!$C$4*(E26-D26)+Assumptions!$D$4*(F26-E26)+Assumptions!$E$4*(G26-F26)+Assumptions!$F$4*(H26-G26) | M26: =K26+MIN(L26,Assumptions!$H$4) | N26: =M26-Assumptions!$I$4 | O26: =N26-Assumptions!$B$25*Q26 | P26: 4 | Q26: 3.697 | R26: 2026 win% from league standings (A); title prob = model estimate — no 2027 World Series odds posted | S26: 2026-10-08 | T26: C | U26: 2026 playoffs still in progress [v2 certainty adj: sd x2.0, mu shrink 50%, p shrink 50%] | Y26: =N26-IF(T26="C",Assumptions!$B$27,IF(T26="B",Assumptions!$B$26,0))
A27: Minnesota Twins | B27: 2026: 77-85 (.4753) | D27: 0.0216 | E27: 0.0432 | F27: 0.0864 | G27: 0.1728 | H27: 0.3456 | I27: 0.5081 | J27: 0.1 | K27: 6.317 | L27: =Assumptions!$B$4*D27+Assumptions!$C$4*(E27-D27)+Assumptions!$D$4*(F27-E27)+Assumptions!$E$4*(G27-F27)+Assumptions!$F$4*(H27-G27) | M27: =K27+MIN(L27,Assumptions!$H$4) | N27: =M27-Assumptions!$I$4 | O27: =N27-Assumptions!$B$25*Q27 | P27: 4 | Q27: 3.663 | R27: 2026 win% from league standings (A); title prob = model estimate — no 2027 World Series odds posted | S27: 2026-10-08 | T27: C | U27: 2026 playoffs still in progress [v2 certainty adj: sd x2.0, mu shrink 50%, p shrink 50%] | Y27: =N27-IF(T27="C",Assumptions!$B$27,IF(T27="B",Assumptions!$B$26,0))
A28: Washington Nationals | B28: 2026: 77-85 (.4753) | D28: 0.0216 | E28: 0.0432 | F28: 0.0864 | G28: 0.1728 | H28: 0.3456 | I28: 0.5081 | J28: 0.1 | K28: 6.311 | L28: =Assumptions!$B$4*D28+Assumptions!$C$4*(E28-D28)+Assumptions!$D$4*(F28-E28)+Assumptions!$E$4*(G28-F28)+Assumptions!$F$4*(H28-G28) | M28: =K28+MIN(L28,Assumptions!$H$4) | N28: =M28-Assumptions!$I$4 | O28: =N28-Assumptions!$B$25*Q28 | P28: 4 | Q28: 3.699 | R28: 2026 win% from league standings (A); title prob = model estimate — no 2027 World Series odds posted | S28: 2026-10-08 | T28: C | U28: 2026 playoffs still in progress [v2 certainty adj: sd x2.0, mu shrink 50%, p shrink 50%] | Y28: =N28-IF(T28="C",Assumptions!$B$27,IF(T28="B",Assumptions!$B$26,0))
A29: St. Louis Cardinals | B29: 2026: 77-85 (.4753) | D29: 0.0216 | E29: 0.0432 | F29: 0.0864 | G29: 0.1728 | H29: 0.3456 | I29: 0.5081 | J29: 0.1 | K29: 6.305 | L29: =Assumptions!$B$4*D29+Assumptions!$C$4*(E29-D29)+Assumptions!$D$4*(F29-E29)+Assumptions!$E$4*(G29-F29)+Assumptions!$F$4*(H29-G29) | M29: =K29+MIN(L29,Assumptions!$H$4) | N29: =M29-Assumptions!$I$4 | O29: =N29-Assumptions!$B$25*Q29 | P29: 4 | Q29: 3.694 | R29: 2026 win% from league standings (A); title prob = model estimate — no 2027 World Series odds posted | S29: 2026-10-08 | T29: C | U29: 2026 playoffs still in progress [v2 certainty adj: sd x2.0, mu shrink 50%, p shrink 50%] | Y29: =N29-IF(T29="C",Assumptions!$B$27,IF(T29="B",Assumptions!$B$26,0))
A30: Kansas City Royals | B30: 2026: 69-93 (.4259) | D30: 0.0216 | E30: 0.0432 | F30: 0.0864 | G30: 0.1728 | H30: 0.3456 | I30: 0.497 | J30: 0.1 | K30: 5.885 | L30: =Assumptions!$B$4*D30+Assumptions!$C$4*(E30-D30)+Assumptions!$D$4*(F30-E30)+Assumptions!$E$4*(G30-F30)+Assumptions!$F$4*(H30-G30) | M30: =K30+MIN(L30,Assumptions!$H$4) | N30: =M30-Assumptions!$I$4 | O30: =N30-Assumptions!$B$25*Q30 | P30: 4 | Q30: 3.651 | R30: 2026 win% from league standings (A); title prob = model estimate — no 2027 World Series odds posted | S30: 2026-10-08 | T30: C | U30: 2026 playoffs still in progress [v2 certainty adj: sd x2.0, mu shrink 50%, p shrink 50%] | Y30: =N30-IF(T30="C",Assumptions!$B$27,IF(T30="B",Assumptions!$B$26,0))
A31: Athletics | B31: 2026: 64-98 (.3951) | D31: 0.0216 | E31: 0.0432 | F31: 0.0864 | G31: 0.1728 | H31: 0.3456 | I31: 0.49 | J31: 0.1 | K31: 5.683 | L31: =Assumptions!$B$4*D31+Assumptions!$C$4*(E31-D31)+Assumptions!$D$4*(F31-E31)+Assumptions!$E$4*(G31-F31)+Assumptions!$F$4*(H31-G31) | M31: =K31+MIN(L31,Assumptions!$H$4) | N31: =M31-Assumptions!$I$4 | O31: =N31-Assumptions!$B$25*Q31 | P31: 4 | Q31: 3.659 | R31: 2026 win% from league standings (A); title prob = model estimate — no 2027 World Series odds posted | S31: 2026-10-08 | T31: C | U31: 2026 playoffs still in progress [v2 certainty adj: sd x2.0, mu shrink 50%, p shrink 50%] | Y31: =N31-IF(T31="C",Assumptions!$B$27,IF(T31="B",Assumptions!$B$26,0))
A32: San Francisco Giants | B32: 2026: 65-97 (.4012) | D32: 0.0196 | E32: 0.0392 | F32: 0.0784 | G32: 0.1568 | H32: 0.3136 | I32: 0.4914 | J32: 0.1 | K32: 5.807 | L32: =Assumptions!$B$4*D32+Assumptions!$C$4*(E32-D32)+Assumptions!$D$4*(F32-E32)+Assumptions!$E$4*(G32-F32)+Assumptions!$F$4*(H32-G32) | M32: =K32+MIN(L32,Assumptions!$H$4) | N32: =M32-Assumptions!$I$4 | O32: =N32-Assumptions!$B$25*Q32 | P32: 4 | Q32: 3.671 | R32: 2026 win% from league standings (A); title prob = model estimate — no 2027 World Series odds posted | S32: 2026-10-08 | T32: C | U32: 2026 playoffs still in progress [v2 certainty adj: sd x2.0, mu shrink 50%, p shrink 50%] | Y32: =N32-IF(T32="C",Assumptions!$B$27,IF(T32="B",Assumptions!$B$26,0))
A33: Los Angeles Angels | B33: 2026: 62-100 (.3827) | D33: 0.0191 | E33: 0.0382 | F33: 0.0764 | G33: 0.1528 | H33: 0.3056 | I33: 0.4872 | J33: 0.1 | K33: 5.69 | L33: =Assumptions!$B$4*D33+Assumptions!$C$4*(E33-D33)+Assumptions!$D$4*(F33-E33)+Assumptions!$E$4*(G33-F33)+Assumptions!$F$4*(H33-G33) | M33: =K33+MIN(L33,Assumptions!$H$4) | N33: =M33-Assumptions!$I$4 | O33: =N33-Assumptions!$B$25*Q33 | P33: 4 | Q33: 3.573 | R33: 2026 win% from league standings (A); title prob = model estimate — no 2027 World Series odds posted | S33: 2026-10-08 | T33: C | U33: 2026 playoffs still in progress [v2 certainty adj: sd x2.0, mu shrink 50%, p shrink 50%] | Y33: =N33-IF(T33="C",Assumptions!$B$27,IF(T33="B",Assumptions!$B$26,0))
A34: Colorado Rockies | B34: 2026: 58-104 (.3580) | D34: 0.0177 | E34: 0.0354 | F34: 0.0708 | G34: 0.1416 | H34: 0.2832 | I34: 0.4817 | J34: 0.1 | K34: 5.484 | L34: =Assumptions!$B$4*D34+Assumptions!$C$4*(E34-D34)+Assumptions!$D$4*(F34-E34)+Assumptions!$E$4*(G34-F34)+Assumptions!$F$4*(H34-G34) | M34: =K34+MIN(L34,Assumptions!$H$4) | N34: =M34-Assumptions!$I$4 | O34: =N34-Assumptions!$B$25*Q34 | P34: 4 | Q34: 3.612 | R34: 2026 win% from league standings (A); title prob = model estimate — no 2027 World Series odds posted | S34: 2026-10-08 | T34: C | U34: 2026 playoffs still in progress [v2 certainty adj: sd x2.0, mu shrink 50%, p shrink 50%] | Y34: =N34-IF(T34="C",Assumptions!$B$27,IF(T34="B",Assumptions!$B$26,0))
A36: Replacement-level EV (Nth best)

Sheet NHL
A1: NHL — 2027 draft research (EV model; see README)
A2: As of 2026-10-22. Sorted by E[total]. Yellow = inferred / low-confidence (C).
A4: Candidate | B4: Detail | C4: Odds / price | D4: p(champ) | E4: p(final) | F4: p(semi) | G4: p(quarter) | H4: p(rd 1) | I4: mu | J4: sd | K4: E[rank pts] (MC) | L4: E[bonus] | M4: E[total] | N4: VOR | O4: Risk-adj VOR | P4: Tier | Q4: SD rank pts | R4: Source | S4: As of | T4: Conf | U4: Notes | V4: Field draft score | W4: Field rank | X4: Owner | Y4: Conf-adj VOR
A5: Carolina Hurricanes | B5: East | C5: Kalshi 9.5% | D5: 0.0946 | E5: 0.17 | F5: 0.3196 | G5: 0.537 | H5: 0.9089 | I5: 0.6159 | J5: 0.0469 | K5: 9.197 | L5: =Assumptions!$B$5*D5+Assumptions!$C$5*(E5-D5)+Assumptions!$D$5*(F5-E5)+Assumptions!$E$5*(G5-F5)+Assumptions!$F$5*(H5-G5) | M5: =K5+MIN(L5,Assumptions!$H$5) | N5: =M5-Assumptions!$I$5 | O5: =N5-Assumptions!$B$25*Q5 | P5: 1 | Q5: 3.319 | R5: KXNHL-27 exchange mid-price, pulled 2026-10-08; p(final)=KXNHLEAST/KXNHLWEST-27 Kalshi mid | league_sim.py: full-schedule + real playoff bracket Monte Carlo, ratings fitted to Kalshi | S5: 2026-10-08 | T5: A | U5: pts 108.5, dated; 2026 champion [sim: playoffs 91%, rd2 54%, conf final 32%] | X5: Jamzee | Y5: =N5-IF(T5="C",Assumptions!$B$27,IF(T5="B",Assumptions!$B$26,0))
A6: Tampa Bay Lightning | B6: East | C6: Kalshi 5.5% | D6: 0.0833 | E6: 0.1546 | F6: 0.2725 | G6: 0.4975 | H6: 0.8814 | I6: 0.6143 | J6: 0.0477 | K6: 9.058 | L6: =Assumptions!$B$5*D6+Assumptions!$C$5*(E6-D6)+Assumptions!$D$5*(F6-E6)+Assumptions!$E$5*(G6-F6)+Assumptions!$F$5*(H6-G6) | M6: =K6+MIN(L6,Assumptions!$H$5) | N6: =M6-Assumptions!$I$5 | O6: =N6-Assumptions!$B$25*Q6 | P6: 1 | Q6: 3.367 | R6: KXNHL-27 exchange mid-price, pulled 2026-10-08; p(final)=KXNHLEAST/KXNHLWEST-27 Kalshi mid | league_sim.py: full-schedule + real playoff bracket Monte Carlo, ratings fitted to Kalshi | S6: 2026-10-08 | T6: A | U6: est. [sim: playoffs 88%, rd2 50%, conf final 27%] | X6: Fryar | Y6: =N6-IF(T6="C",Assumptions!$B$27,IF(T6="B",Assumptions!$B$26,0))
A7: Edmonton Oilers | B7: West | C7: Kalshi 8.5% | D7: 0.0765 | E7: 0.1455 | F7: 0.2931 | G7: 0.5152 | H7: 0.9026 | I7: 0.6082 | J7: 0.0481 | K7: 8.646 | L7: =Assumptions!$B$5*D7+Assumptions!$C$5*(E7-D7)+Assumptions!$D$5*(F7-E7)+Assumptions!$E$5*(G7-F7)+Assumptions!$F$5*(H7-G7) | M7: =K7+MIN(L7,Assumptions!$H$5) | N7: =M7-Assumptions!$I$5 | O7: =N7-Assumptions!$B$25*Q7 | P7: 1 | Q7: 3.473 | R7: KXNHL-27 exchange mid-price, pulled 2026-10-08; p(final)=KXNHLEAST/KXNHLWEST-27 Kalshi mid | league_sim.py: full-schedule + real playoff bracket Monte Carlo, ratings fitted to Kalshi | S7: 2026-10-08 | T7: A | U7: pts 104.5 [sim: playoffs 90%, rd2 52%, conf final 29%] | X7: Buckley | Y7: =N7-IF(T7="C",Assumptions!$B$27,IF(T7="B",Assumptions!$B$26,0))
A8: Colorado Avalanche | B8: West | C8: Kalshi 12.5% | D8: 0.1128 | E8: 0.1949 | F8: 0.3134 | G8: 0.5209 | H8: 0.8387 | I8: 0.5946 | J8: 0.0475 | K8: 7.656 | L8: =Assumptions!$B$5*D8+Assumptions!$C$5*(E8-D8)+Assumptions!$D$5*(F8-E8)+Assumptions!$E$5*(G8-F8)+Assumptions!$F$5*(H8-G8) | M8: =K8+MIN(L8,Assumptions!$H$5) | N8: =M8-Assumptions!$I$5 | O8: =N8-Assumptions!$B$25*Q8 | P8: 2 | Q8: 3.608 | R8: KXNHL-27 exchange mid-price, pulled 2026-10-08; p(final)=KXNHLEAST/KXNHLWEST-27 Kalshi mid | league_sim.py: full-schedule + real playoff bracket Monte Carlo, ratings fitted to Kalshi | S8: 2026-10-08 | T8: A | U8: pts 107.5 [sim: playoffs 84%, rd2 52%, conf final 31%] | X8: Korch | Y8: =N8-IF(T8="C",Assumptions!$B$27,IF(T8="B",Assumptions!$B$26,0))
A9: Florida Panthers | B9: East | C9: Kalshi 10.5% | D9: 0.0867 | E9: 0.1532 | F9: 0.2645 | G9: 0.4585 | H9: 0.7802 | I9: 0.5943 | J9: 0.0473 | K9: 7.681 | L9: =Assumptions!$B$5*D9+Assumptions!$C$5*(E9-D9)+Assumptions!$D$5*(F9-E9)+Assumptions!$E$5*(G9-F9)+Assumptions!$F$5*(H9-G9) | M9: =K9+MIN(L9,Assumptions!$H$5) | N9: =M9-Assumptions!$I$5 | O9: =N9-Assumptions!$B$25*Q9 | P9: 2 | Q9: 3.536 | R9: KXNHL-27 exchange mid-price, pulled 2026-10-08; p(final)=KXNHLEAST/KXNHLWEST-27 Kalshi mid | league_sim.py: full-schedule + real playoff bracket Monte Carlo, ratings fitted to Kalshi | S9: 2026-10-08 | T9: A | U9: pts 107.5 [sim: playoffs 78%, rd2 46%, conf final 26%] | X9: Todd | Y9: =N9-IF(T9="C",Assumptions!$B$27,IF(T9="B",Assumptions!$B$26,0))
A10: Vegas Golden Knights | B10: West | C10: Kalshi 7.5% | D10: 0.0437 | E10: 0.1006 | F10: 0.2082 | G10: 0.4233 | H10: 0.8197 | I10: 0.5875 | J10: 0.047 | K10: 7.211 | L10: =Assumptions!$B$5*D10+Assumptions!$C$5*(E10-D10)+Assumptions!$D$5*(F10-E10)+Assumptions!$E$5*(G10-F10)+Assumptions!$F$5*(H10-G10) | M10: =K10+MIN(L10,Assumptions!$H$5) | N10: =M10-Assumptions!$I$5 | O10: =N10-Assumptions!$B$25*Q10 | P10: 2 | Q10: 3.586 | R10: KXNHL-27 exchange mid-price, pulled 2026-10-08; p(final)=KXNHLEAST/KXNHLWEST-27 Kalshi mid | league_sim.py: full-schedule + real playoff bracket Monte Carlo, ratings fitted to Kalshi | S10: 2026-10-08 | T10: A | U10: est. [sim: playoffs 82%, rd2 42%, conf final 21%] | X10: Tim | Y10: =N10-IF(T10="C",Assumptions!$B$27,IF(T10="B",Assumptions!$B$26,0))
A11: Minnesota Wild | B11: West | C11: Kalshi 6.5% | D11: 0.0579 | E11: 0.1181 | F11: 0.2216 | G11: 0.4161 | H11: 0.7843 | I11: 0.5846 | J11: 0.0473 | K11: 6.919 | L11: =Assumptions!$B$5*D11+Assumptions!$C$5*(E11-D11)+Assumptions!$D$5*(F11-E11)+Assumptions!$E$5*(G11-F11)+Assumptions!$F$5*(H11-G11) | M11: =K11+MIN(L11,Assumptions!$H$5) | N11: =M11-Assumptions!$I$5 | O11: =N11-Assumptions!$B$25*Q11 | P11: 2 | Q11: 3.642 | R11: KXNHL-27 exchange mid-price, pulled 2026-10-08; p(final)=KXNHLEAST/KXNHLWEST-27 Kalshi mid | league_sim.py: full-schedule + real playoff bracket Monte Carlo, ratings fitted to Kalshi | S11: 2026-10-08 | T11: A | U11: pts 100.5 [sim: playoffs 78%, rd2 42%, conf final 22%] | Y11: =N11-IF(T11="C",Assumptions!$B$27,IF(T11="B",Assumptions!$B$26,0))
A12: Utah Mammoth | B12: West | C12: Kalshi 3.0% | D12: 0.0381 | E12: 0.0866 | F12: 0.1801 | G12: 0.3782 | H12: 0.761 | I12: 0.5807 | J12: 0.0473 | K12: 6.578 | L12: =Assumptions!$B$5*D12+Assumptions!$C$5*(E12-D12)+Assumptions!$D$5*(F12-E12)+Assumptions!$E$5*(G12-F12)+Assumptions!$F$5*(H12-G12) | M12: =K12+MIN(L12,Assumptions!$H$5) | N12: =M12-Assumptions!$I$5 | O12: =N12-Assumptions!$B$25*Q12 | P12: 3 | Q12: 3.589 | R12: KXNHL-27 exchange mid-price, pulled 2026-10-08; p(final)=KXNHLEAST/KXNHLWEST-27 Kalshi mid | league_sim.py: full-schedule + real playoff bracket Monte Carlo, ratings fitted to Kalshi | S12: 2026-10-08 | T12: A | U12: est. [sim: playoffs 76%, rd2 38%, conf final 18%] | Y12: =N12-IF(T12="C",Assumptions!$B$27,IF(T12="B",Assumptions!$B$26,0))
A13: Washington Capitals | B13: East | C13: Kalshi 5.5% | D13: 0.0442 | E13: 0.0875 | F13: 0.1859 | G13: 0.3738 | H13: 0.687 | I13: 0.5764 | J13: 0.0479 | K13: 6.35 | L13: =Assumptions!$B$5*D13+Assumptions!$C$5*(E13-D13)+Assumptions!$D$5*(F13-E13)+Assumptions!$E$5*(G13-F13)+Assumptions!$F$5*(H13-G13) | M13: =K13+MIN(L13,Assumptions!$H$5) | N13: =M13-Assumptions!$I$5 | O13: =N13-Assumptions!$B$25*Q13 | P13: 3 | Q13: 3.567 | R13: KXNHL-27 exchange mid-price, pulled 2026-10-08; p(final)=KXNHLEAST/KXNHLWEST-27 Kalshi mid | league_sim.py: full-schedule + real playoff bracket Monte Carlo, ratings fitted to Kalshi | S13: 2026-10-08 | T13: A | U13: est. [sim: playoffs 69%, rd2 37%, conf final 19%] | X13: Feder | Y13: =N13-IF(T13="C",Assumptions!$B$27,IF(T13="B",Assumptions!$B$26,0))
A14: Dallas Stars | B14: West | C14: Kalshi 5.5% | D14: 0.0444 | E14: 0.0891 | F14: 0.1726 | G14: 0.3544 | H14: 0.6989 | I14: 0.5713 | J14: 0.0479 | K14: 5.972 | L14: =Assumptions!$B$5*D14+Assumptions!$C$5*(E14-D14)+Assumptions!$D$5*(F14-E14)+Assumptions!$E$5*(G14-F14)+Assumptions!$F$5*(H14-G14) | M14: =K14+MIN(L14,Assumptions!$H$5) | N14: =M14-Assumptions!$I$5 | O14: =N14-Assumptions!$B$25*Q14 | P14: 3 | Q14: 3.562 | R14: KXNHL-27 exchange mid-price, pulled 2026-10-08; p(final)=KXNHLEAST/KXNHLWEST-27 Kalshi mid | league_sim.py: full-schedule + real playoff bracket Monte Carlo, ratings fitted to Kalshi | S14: 2026-10-08 | T14: A | U14: pts 100.5 [sim: playoffs 70%, rd2 35%, conf final 17%] | X14: Mitchell | Y14: =N14-IF(T14="C",Assumptions!$B$27,IF(T14="B",Assumptions!$B$26,0))
A15: Boston Bruins | B15: East | C15: Kalshi +9900 | D15: 0.0265 | E15: 0.0549 | F15: 0.123 | G15: 0.2772 | H15: 0.6195 | I15: 0.5728 | J15: 0.0481 | K15: 6.086 | L15: =Assumptions!$B$5*D15+Assumptions!$C$5*(E15-D15)+Assumptions!$D$5*(F15-E15)+Assumptions!$E$5*(G15-F15)+Assumptions!$F$5*(H15-G15) | M15: =K15+MIN(L15,Assumptions!$H$5) | N15: =M15-Assumptions!$I$5 | O15: =N15-Assumptions!$B$25*Q15 | P15: 3 | Q15: 3.594 | R15: Kalshi Cup market (~1 month old) normalised; points totals SportsBettingDime | league_sim.py: full-schedule + real playoff bracket Monte Carlo, ratings fitted to Kalshi | S15: 2026-10-08 | T15: A | U15: pts 88.5 | price superseded by Kalshi field; p rescaled [sim: playoffs 62%, rd2 28%, conf final 12%] | X15: Shep | Y15: =N15-IF(T15="C",Assumptions!$B$27,IF(T15="B",Assumptions!$B$26,0))
A16: Ottawa Senators | B16: East | C16: Kalshi +3900 | D16: 0.0213 | E16: 0.0461 | F16: 0.1067 | G16: 0.2399 | H16: 0.5741 | I16: 0.5658 | J16: 0.0484 | K16: 5.607 | L16: =Assumptions!$B$5*D16+Assumptions!$C$5*(E16-D16)+Assumptions!$D$5*(F16-E16)+Assumptions!$E$5*(G16-F16)+Assumptions!$F$5*(H16-G16) | M16: =K16+MIN(L16,Assumptions!$H$5) | N16: =M16-Assumptions!$I$5 | O16: =N16-Assumptions!$B$25*Q16 | P16: 3 | Q16: 3.515 | R16: Kalshi Cup market (~1 month old) normalised; points totals SportsBettingDime | league_sim.py: full-schedule + real playoff bracket Monte Carlo, ratings fitted to Kalshi | S16: 2026-10-08 | T16: A | U16: pts 94.5 | price superseded by Kalshi field; p rescaled [sim: playoffs 57%, rd2 24%, conf final 11%] | Y16: =N16-IF(T16="C",Assumptions!$B$27,IF(T16="B",Assumptions!$B$26,0))
A17: New Jersey Devils | B17: East | C17: Kalshi 3.5% | D17: 0.028 | E17: 0.0571 | F17: 0.1242 | G17: 0.2712 | H17: 0.5534 | I17: 0.5595 | J17: 0.0478 | K17: 5.192 | L17: =Assumptions!$B$5*D17+Assumptions!$C$5*(E17-D17)+Assumptions!$D$5*(F17-E17)+Assumptions!$E$5*(G17-F17)+Assumptions!$F$5*(H17-G17) | M17: =K17+MIN(L17,Assumptions!$H$5) | N17: =M17-Assumptions!$I$5 | O17: =N17-Assumptions!$B$25*Q17 | P17: 3 | Q17: 3.408 | R17: KXNHL-27 exchange mid-price, pulled 2026-10-08; p(final)=KXNHLEAST/KXNHLWEST-27 Kalshi mid | league_sim.py: full-schedule + real playoff bracket Monte Carlo, ratings fitted to Kalshi | S17: 2026-10-08 | T17: A | U17: pts 95.5 [sim: playoffs 55%, rd2 27%, conf final 12%] | X17: Wu | Y17: =N17-IF(T17="C",Assumptions!$B$27,IF(T17="B",Assumptions!$B$26,0))
A18: Montreal Canadiens | B18: East | C18: Kalshi 4.5% | D18: 0.0357 | E18: 0.0679 | F18: 0.132 | G18: 0.2632 | H18: 0.5228 | I18: 0.5597 | J18: 0.0478 | K18: 5.17 | L18: =Assumptions!$B$5*D18+Assumptions!$C$5*(E18-D18)+Assumptions!$D$5*(F18-E18)+Assumptions!$E$5*(G18-F18)+Assumptions!$F$5*(H18-G18) | M18: =K18+MIN(L18,Assumptions!$H$5) | N18: =M18-Assumptions!$I$5 | O18: =N18-Assumptions!$B$25*Q18 | P18: 4 | Q18: 3.445 | R18: KXNHL-27 exchange mid-price, pulled 2026-10-08; p(final)=KXNHLEAST/KXNHLWEST-27 Kalshi mid | league_sim.py: full-schedule + real playoff bracket Monte Carlo, ratings fitted to Kalshi | S18: 2026-10-08 | T18: A | U18: pts 98.5 [sim: playoffs 52%, rd2 26%, conf final 13%] | Y18: =N18-IF(T18="C",Assumptions!$B$27,IF(T18="B",Assumptions!$B$26,0))
A19: San Jose Sharks | B19: West | C19: Kalshi 4.5% | D19: 0.0286 | E19: 0.0633 | F19: 0.1439 | G19: 0.2921 | H19: 0.5856 | I19: 0.5545 | J19: 0.0474 | K19: 4.721 | L19: =Assumptions!$B$5*D19+Assumptions!$C$5*(E19-D19)+Assumptions!$D$5*(F19-E19)+Assumptions!$E$5*(G19-F19)+Assumptions!$F$5*(H19-G19) | M19: =K19+MIN(L19,Assumptions!$H$5) | N19: =M19-Assumptions!$I$5 | O19: =N19-Assumptions!$B$25*Q19 | P19: 4 | Q19: 3.296 | R19: KXNHL-27 exchange mid-price, pulled 2026-10-08; p(final)=KXNHLEAST/KXNHLWEST-27 Kalshi mid | league_sim.py: full-schedule + real playoff bracket Monte Carlo, ratings fitted to Kalshi | S19: 2026-10-08 | T19: A | U19: pts 94.5 [sim: playoffs 59%, rd2 29%, conf final 14%] | Y19: =N19-IF(T19="C",Assumptions!$B$27,IF(T19="B",Assumptions!$B$26,0))
A20: Buffalo Sabres | B20: East | C20: Kalshi +2757 | D20: 0.0255 | E20: 0.0505 | F20: 0.1024 | G20: 0.2122 | H20: 0.4434 | I20: 0.5503 | J20: 0.0473 | K20: 4.569 | L20: =Assumptions!$B$5*D20+Assumptions!$C$5*(E20-D20)+Assumptions!$D$5*(F20-E20)+Assumptions!$E$5*(G20-F20)+Assumptions!$F$5*(H20-G20) | M20: =K20+MIN(L20,Assumptions!$H$5) | N20: =M20-Assumptions!$I$5 | O20: =N20-Assumptions!$B$25*Q20 | P20: 4 | Q20: 3.233 | R20: Kalshi Cup market (~1 month old) normalised; points totals SportsBettingDime; p(final)=KXNHLEAST/KXNHLWEST-27 Kalshi mid | league_sim.py: full-schedule + real playoff bracket Monte Carlo, ratings fitted to Kalshi | S20: 2026-10-08 | T20: A | U20: pts 96.5 | price superseded by Kalshi field; p rescaled [sim: playoffs 44%, rd2 21%, conf final 10%] | Y20: =N20-IF(T20="C",Assumptions!$B$27,IF(T20="B",Assumptions!$B$26,0))
A21: Anaheim Ducks | B21: West | C21: Kalshi 3.5% | D21: 0.0195 | E21: 0.0486 | F21: 0.109 | G21: 0.227 | H21: 0.4835 | I21: 0.5436 | J21: 0.0488 | K21: 4.201 | L21: =Assumptions!$B$5*D21+Assumptions!$C$5*(E21-D21)+Assumptions!$D$5*(F21-E21)+Assumptions!$E$5*(G21-F21)+Assumptions!$F$5*(H21-G21) | M21: =K21+MIN(L21,Assumptions!$H$5) | N21: =M21-Assumptions!$I$5 | O21: =N21-Assumptions!$B$25*Q21 | P21: 4 | Q21: 3.15 | R21: KXNHL-27 exchange mid-price, pulled 2026-10-08; p(final)=KXNHLEAST/KXNHLWEST-27 Kalshi mid | league_sim.py: full-schedule + real playoff bracket Monte Carlo, ratings fitted to Kalshi | S21: 2026-10-08 | T21: A | U21: pts 94.5 [sim: playoffs 48%, rd2 23%, conf final 11%] | Y21: =N21-IF(T21="C",Assumptions!$B$27,IF(T21="B",Assumptions!$B$26,0))
A22: New York Rangers | B22: East | C22: Kalshi +6567 | D22: 0.013 | E22: 0.0311 | F22: 0.0777 | G22: 0.1867 | H22: 0.4542 | I22: 0.5478 | J22: 0.0475 | K22: 4.452 | L22: =Assumptions!$B$5*D22+Assumptions!$C$5*(E22-D22)+Assumptions!$D$5*(F22-E22)+Assumptions!$E$5*(G22-F22)+Assumptions!$F$5*(H22-G22) | M22: =K22+MIN(L22,Assumptions!$H$5) | N22: =M22-Assumptions!$I$5 | O22: =N22-Assumptions!$B$25*Q22 | P22: 4 | Q22: 3.206 | R22: Kalshi Cup market (~1 month old) normalised; points totals SportsBettingDime; p(final)=KXNHLEAST/KXNHLWEST-27 Kalshi mid | league_sim.py: full-schedule + real playoff bracket Monte Carlo, ratings fitted to Kalshi | S22: 2026-10-08 | T22: A | U22: pts 86.5 | price superseded by Kalshi field; p rescaled [sim: playoffs 45%, rd2 19%, conf final 8%] | X22: Molmen | Y22: =N22-IF(T22="C",Assumptions!$B$27,IF(T22="B",Assumptions!$B$26,0))
A23: Toronto Maple Leafs | B23: East | C23: Kalshi +3900 | D23: 0.0216 | E23: 0.0428 | F23: 0.0866 | G23: 0.1913 | H23: 0.404 | I23: 0.5467 | J23: 0.0469 | K23: 4.338 | L23: =Assumptions!$B$5*D23+Assumptions!$C$5*(E23-D23)+Assumptions!$D$5*(F23-E23)+Assumptions!$E$5*(G23-F23)+Assumptions!$F$5*(H23-G23) | M23: =K23+MIN(L23,Assumptions!$H$5) | N23: =M23-Assumptions!$I$5 | O23: =N23-Assumptions!$B$25*Q23 | P23: 4 | Q23: 3.172 | R23: Kalshi Cup market (~1 month old) normalised; points totals SportsBettingDime; p(final)=KXNHLEAST/KXNHLWEST-27 Kalshi mid | league_sim.py: full-schedule + real playoff bracket Monte Carlo, ratings fitted to Kalshi | S23: 2026-10-08 | T23: A | U23: est. [sim: playoffs 40%, rd2 19%, conf final 9%] | X23: Jens | Y23: =N23-IF(T23="C",Assumptions!$B$27,IF(T23="B",Assumptions!$B$26,0))
A24: Los Angeles Kings | B24: West | C24: Kalshi +6567 | D24: 0.021 | E24: 0.0504 | F24: 0.0976 | G24: 0.2013 | H24: 0.4044 | I24: 0.5331 | J24: 0.0477 | K24: 3.595 | L24: =Assumptions!$B$5*D24+Assumptions!$C$5*(E24-D24)+Assumptions!$D$5*(F24-E24)+Assumptions!$E$5*(G24-F24)+Assumptions!$F$5*(H24-G24) | M24: =K24+MIN(L24,Assumptions!$H$5) | N24: =M24-Assumptions!$I$5 | O24: =N24-Assumptions!$B$25*Q24 | P24: 4 | Q24: 2.854 | R24: Kalshi Cup market (~1 month old) normalised; points totals SportsBettingDime; p(final)=KXNHLEAST/KXNHLWEST-27 Kalshi mid | league_sim.py: full-schedule + real playoff bracket Monte Carlo, ratings fitted to Kalshi | S24: 2026-10-08 | T24: A | U24: pts 95.5 | price superseded by Kalshi field; p rescaled [sim: playoffs 40%, rd2 20%, conf final 10%] | Y24: =N24-IF(T24="C",Assumptions!$B$27,IF(T24="B",Assumptions!$B$26,0))
A25: Seattle Kraken | B25: West | C25: Kalshi +9900 | D25: 0.0067 | E25: 0.0205 | F25: 0.0589 | G25: 0.1598 | H25: 0.4096 | I25: 0.5348 | J25: 0.0473 | K25: 3.665 | L25: =Assumptions!$B$5*D25+Assumptions!$C$5*(E25-D25)+Assumptions!$D$5*(F25-E25)+Assumptions!$E$5*(G25-F25)+Assumptions!$F$5*(H25-G25) | M25: =K25+MIN(L25,Assumptions!$H$5) | N25: =M25-Assumptions!$I$5 | O25: =N25-Assumptions!$B$25*Q25 | P25: 4 | Q25: 2.877 | R25: Kalshi Cup market (~1 month old) normalised; points totals SportsBettingDime | league_sim.py: full-schedule + real playoff bracket Monte Carlo, ratings fitted to Kalshi | S25: 2026-10-08 | T25: A | U25: est. [sim: playoffs 41%, rd2 16%, conf final 6%] | Y25: =N25-IF(T25="C",Assumptions!$B$27,IF(T25="B",Assumptions!$B$26,0))
A26: St. Louis Blues | B26: West | C26: Kalshi +9900 | D26: 0.0112 | E26: 0.0257 | F26: 0.0578 | G26: 0.1444 | H26: 0.3646 | I26: 0.5295 | J26: 0.0484 | K26: 3.44 | L26: =Assumptions!$B$5*D26+Assumptions!$C$5*(E26-D26)+Assumptions!$D$5*(F26-E26)+Assumptions!$E$5*(G26-F26)+Assumptions!$F$5*(H26-G26) | M26: =K26+MIN(L26,Assumptions!$H$5) | N26: =M26-Assumptions!$I$5 | O26: =N26-Assumptions!$B$25*Q26 | P26: 4 | Q26: 2.773 | R26: Kalshi Cup market (~1 month old) normalised; points totals SportsBettingDime | league_sim.py: full-schedule + real playoff bracket Monte Carlo, ratings fitted to Kalshi | S26: 2026-10-08 | T26: A | U26: est. [sim: playoffs 36%, rd2 14%, conf final 6%] | Y26: =N26-IF(T26="C",Assumptions!$B$27,IF(T26="B",Assumptions!$B$26,0))
A27: New York Islanders | B27: East | C27: Kalshi +9900 | D27: 0.0076 | E27: 0.02 | F27: 0.0488 | G27: 0.1229 | H27: 0.3101 | I27: 0.5289 | J27: 0.0478 | K27: 3.376 | L27: =Assumptions!$B$5*D27+Assumptions!$C$5*(E27-D27)+Assumptions!$D$5*(F27-E27)+Assumptions!$E$5*(G27-F27)+Assumptions!$F$5*(H27-G27) | M27: =K27+MIN(L27,Assumptions!$H$5) | N27: =M27-Assumptions!$I$5 | O27: =N27-Assumptions!$B$25*Q27 | P27: 4 | Q27: 2.71 | R27: Kalshi Cup market (~1 month old) normalised; points totals SportsBettingDime | league_sim.py: full-schedule + real playoff bracket Monte Carlo, ratings fitted to Kalshi | S27: 2026-10-08 | T27: A | U27: pts 88.5 | price superseded by Kalshi field; p rescaled [sim: playoffs 31%, rd2 12%, conf final 5%] | Y27: =N27-IF(T27="C",Assumptions!$B$27,IF(T27="B",Assumptions!$B$26,0))
A28: Columbus Blue Jackets | B28: East | C28: Kalshi +6567 | D28: 0.0084 | E28: 0.0182 | F28: 0.0488 | G28: 0.1197 | H28: 0.279 | I28: 0.5251 | J28: 0.0484 | K28: 3.18 | L28: =Assumptions!$B$5*D28+Assumptions!$C$5*(E28-D28)+Assumptions!$D$5*(F28-E28)+Assumptions!$E$5*(G28-F28)+Assumptions!$F$5*(H28-G28) | M28: =K28+MIN(L28,Assumptions!$H$5) | N28: =M28-Assumptions!$I$5 | O28: =N28-Assumptions!$B$25*Q28 | P28: 4 | Q28: 2.626 | R28: Kalshi Cup market (~1 month old) normalised; points totals SportsBettingDime | league_sim.py: full-schedule + real playoff bracket Monte Carlo, ratings fitted to Kalshi | S28: 2026-10-08 | T28: A | U28: pts 91.5 | price superseded by Kalshi field; p rescaled [sim: playoffs 28%, rd2 12%, conf final 5%] | Y28: =N28-IF(T28="C",Assumptions!$B$27,IF(T28="B",Assumptions!$B$26,0))
A29: Winnipeg Jets | B29: West | C29: Kalshi +9900 | D29: 0.0079 | E29: 0.0185 | F29: 0.0466 | G29: 0.1164 | H29: 0.2919 | I29: 0.5211 | J29: 0.0483 | K29: 3.028 | L29: =Assumptions!$B$5*D29+Assumptions!$C$5*(E29-D29)+Assumptions!$D$5*(F29-E29)+Assumptions!$E$5*(G29-F29)+Assumptions!$F$5*(H29-G29) | M29: =K29+MIN(L29,Assumptions!$H$5) | N29: =M29-Assumptions!$I$5 | O29: =N29-Assumptions!$B$25*Q29 | P29: 4 | Q29: 2.555 | R29: Kalshi Cup market (~1 month old) normalised; points totals SportsBettingDime | league_sim.py: full-schedule + real playoff bracket Monte Carlo, ratings fitted to Kalshi | S29: 2026-10-08 | T29: A | U29: est. [sim: playoffs 29%, rd2 12%, conf final 5%] | Y29: =N29-IF(T29="C",Assumptions!$B$27,IF(T29="B",Assumptions!$B$26,0))
A30: Philadelphia Flyers | B30: East | C30: Kalshi +6567 | D30: 0.011 | E30: 0.0221 | F30: 0.0467 | G30: 0.1014 | H30: 0.2191 | I30: 0.5159 | J30: 0.0473 | K30: 2.85 | L30: =Assumptions!$B$5*D30+Assumptions!$C$5*(E30-D30)+Assumptions!$D$5*(F30-E30)+Assumptions!$E$5*(G30-F30)+Assumptions!$F$5*(H30-G30) | M30: =K30+MIN(L30,Assumptions!$H$5) | N30: =M30-Assumptions!$I$5 | O30: =N30-Assumptions!$B$25*Q30 | P30: 4 | Q30: 2.423 | R30: Kalshi Cup market (~1 month old) normalised; points totals SportsBettingDime | league_sim.py: full-schedule + real playoff bracket Monte Carlo, ratings fitted to Kalshi | S30: 2026-10-08 | T30: A | U30: pts 93.5 | price superseded by Kalshi field; p rescaled [sim: playoffs 22%, rd2 10%, conf final 5%] | Y30: =N30-IF(T30="C",Assumptions!$B$27,IF(T30="B",Assumptions!$B$26,0))
A31: Pittsburgh Penguins | B31: East | C31: Kalshi +4900 | D31: 0.0047 | E31: 0.0124 | F31: 0.0339 | G31: 0.0882 | H31: 0.2051 | I31: 0.5138 | J31: 0.0478 | K31: 2.797 | L31: =Assumptions!$B$5*D31+Assumptions!$C$5*(E31-D31)+Assumptions!$D$5*(F31-E31)+Assumptions!$E$5*(G31-F31)+Assumptions!$F$5*(H31-G31) | M31: =K31+MIN(L31,Assumptions!$H$5) | N31: =M31-Assumptions!$I$5 | O31: =N31-Assumptions!$B$25*Q31 | P31: 4 | Q31: 2.44 | R31: Kalshi Cup market (~1 month old) normalised; points totals SportsBettingDime | league_sim.py: full-schedule + real playoff bracket Monte Carlo, ratings fitted to Kalshi | S31: 2026-10-08 | T31: A | U31: pts 89.5 | price superseded by Kalshi field; p rescaled [sim: playoffs 21%, rd2 9%, conf final 3%] | Y31: =N31-IF(T31="C",Assumptions!$B$27,IF(T31="B",Assumptions!$B$26,0))
A32: Chicago Blackhawks | B32: West | C32: Kalshi +9900 | D32: 0.0054 | E32: 0.0149 | F32: 0.035 | G32: 0.087 | H32: 0.2244 | I32: 0.5104 | J32: 0.0482 | K32: 2.619 | L32: =Assumptions!$B$5*D32+Assumptions!$C$5*(E32-D32)+Assumptions!$D$5*(F32-E32)+Assumptions!$E$5*(G32-F32)+Assumptions!$F$5*(H32-G32) | M32: =K32+MIN(L32,Assumptions!$H$5) | N32: =M32-Assumptions!$I$5 | O32: =N32-Assumptions!$B$25*Q32 | P32: 4 | Q32: 2.285 | R32: Kalshi Cup market (~1 month old) normalised; points totals SportsBettingDime | league_sim.py: full-schedule + real playoff bracket Monte Carlo, ratings fitted to Kalshi | S32: 2026-10-08 | T32: A | U32: pts 79.5 | price superseded by Kalshi field; p rescaled [sim: playoffs 22%, rd2 9%, conf final 4%] | Y32: =N32-IF(T32="C",Assumptions!$B$27,IF(T32="B",Assumptions!$B$26,0))
A33: Nashville Predators | B33: West | C33: Kalshi +9900 | D33: 0.0047 | E33: 0.0125 | F33: 0.0333 | G33: 0.0819 | H33: 0.2075 | I33: 0.5091 | J33: 0.0479 | K33: 2.574 | L33: =Assumptions!$B$5*D33+Assumptions!$C$5*(E33-D33)+Assumptions!$D$5*(F33-E33)+Assumptions!$E$5*(G33-F33)+Assumptions!$F$5*(H33-G33) | M33: =K33+MIN(L33,Assumptions!$H$5) | N33: =M33-Assumptions!$I$5 | O33: =N33-Assumptions!$B$25*Q33 | P33: 4 | Q33: 2.234 | R33: Kalshi Cup market (~1 month old) normalised; points totals SportsBettingDime | league_sim.py: full-schedule + real playoff bracket Monte Carlo, ratings fitted to Kalshi | S33: 2026-10-08 | T33: A | U33: pts 85.5 | price superseded by Kalshi field; p rescaled [sim: playoffs 21%, rd2 8%, conf final 3%] | Y33: =N33-IF(T33="C",Assumptions!$B$27,IF(T33="B",Assumptions!$B$26,0))
A34: Detroit Red Wings | B34: East | C34: Kalshi +9900 | D34: 0.005 | E34: 0.0115 | F34: 0.0266 | G34: 0.0591 | H34: 0.1578 | I34: 0.5086 | J34: 0.0484 | K34: 2.531 | L34: =Assumptions!$B$5*D34+Assumptions!$C$5*(E34-D34)+Assumptions!$D$5*(F34-E34)+Assumptions!$E$5*(G34-F34)+Assumptions!$F$5*(H34-G34) | M34: =K34+MIN(L34,Assumptions!$H$5) | N34: =M34-Assumptions!$I$5 | O34: =N34-Assumptions!$B$25*Q34 | P34: 4 | Q34: 2.228 | R34: Kalshi Cup market (~1 month old) normalised; points totals SportsBettingDime | league_sim.py: full-schedule + real playoff bracket Monte Carlo, ratings fitted to Kalshi | S34: 2026-10-08 | T34: A | U34: pts 86.5 | price superseded by Kalshi field; p rescaled [sim: playoffs 16%, rd2 6%, conf final 3%] | X34: Theo | Y34: =N34-IF(T34="C",Assumptions!$B$27,IF(T34="B",Assumptions!$B$26,0))
A35: Calgary Flames | B35: West | C35: Kalshi +9900 | D35: 0.0031 | E35: 0.0065 | F35: 0.0192 | G35: 0.0537 | H35: 0.145 | I35: 0.494 | J35: 0.0482 | K35: 2.03 | L35: =Assumptions!$B$5*D35+Assumptions!$C$5*(E35-D35)+Assumptions!$D$5*(F35-E35)+Assumptions!$E$5*(G35-F35)+Assumptions!$F$5*(H35-G35) | M35: =K35+MIN(L35,Assumptions!$H$5) | N35: =M35-Assumptions!$I$5 | O35: =N35-Assumptions!$B$25*Q35 | P35: 4 | Q35: 1.795 | R35: Kalshi Cup market (~1 month old) normalised; points totals SportsBettingDime | league_sim.py: full-schedule + real playoff bracket Monte Carlo, ratings fitted to Kalshi | S35: 2026-10-08 | T35: A | U35: pts 77.5 | price superseded by Kalshi field; p rescaled [sim: playoffs 14%, rd2 5%, conf final 2%] | Y35: =N35-IF(T35="C",Assumptions!$B$27,IF(T35="B",Assumptions!$B$26,0))
A36: Vancouver Canucks | B36: West | C36: Kalshi +9900 | D36: 0.0011 | E36: 0.0043 | F36: 0.0096 | G36: 0.0284 | H36: 0.0783 | I36: 0.4783 | J36: 0.0473 | K36: 1.72 | L36: =Assumptions!$B$5*D36+Assumptions!$C$5*(E36-D36)+Assumptions!$D$5*(F36-E36)+Assumptions!$E$5*(G36-F36)+Assumptions!$F$5*(H36-G36) | M36: =K36+MIN(L36,Assumptions!$H$5) | N36: =M36-Assumptions!$I$5 | O36: =N36-Assumptions!$B$25*Q36 | P36: 4 | Q36: 1.457 | R36: Kalshi Cup market (~1 month old) normalised; points totals SportsBettingDime | league_sim.py: full-schedule + real playoff bracket Monte Carlo, ratings fitted to Kalshi | S36: 2026-10-08 | T36: A | U36: pts 74.5 (one blog) | price superseded by Kalshi field; p rescaled [sim: playoffs 8%, rd2 3%, conf final 1%] | Y36: =N36-IF(T36="C",Assumptions!$B$27,IF(T36="B",Assumptions!$B$26,0))
A38: Replacement-level EV (Nth best)

Sheet NCAAF
A1: NCAAF — 2027 draft research (EV model; see README)
A2: As of 2026-10-22. Sorted by E[total]. Yellow = inferred / low-confidence (C).
A4: Candidate | B4: Detail | C4: Odds / price | D4: p(champ) | E4: p(final) | F4: p(semi) | G4: p(quarter) | H4: p(rd 1) | I4: mu | J4: sd | K4: E[rank pts] (MC) | L4: E[bonus] | M4: E[total] | N4: VOR | O4: Risk-adj VOR | P4: Tier | Q4: SD rank pts | R4: Source | S4: As of | T4: Conf | U4: Notes | V4: Field draft score | W4: Field rank | X4: Owner | Y4: Conf-adj VOR
A5: Georgia | B5: AP #2, 5-0, SEC | C5: Kalshi 16.5% | D5: 0.165 | E5: 0.33 | F5: 0.66 | G5: 0.97 | H5: 0.97 | I5: 0.85 | J5: 0.15 | K5: 9.853 | L5: =Assumptions!$B$6*D5+Assumptions!$C$6*(E5-D5)+Assumptions!$D$6*(F5-E5)+Assumptions!$E$6*(G5-F5)+Assumptions!$F$6*(H5-G5) | M5: =K5+MIN(L5,Assumptions!$H$6) | N5: =M5-Assumptions!$I$6 | O5: =N5-Assumptions!$B$25*Q5 | P5: 1 | Q5: 2.866 | R5: KXNCAAF-27 exchange mid-price, pulled 2026-10-22 | S5: 2026-10-22 | T5: A | U5: at Alabama Oct 10 | X5: Theo | Y5: =N5-IF(T5="C",Assumptions!$B$27,IF(T5="B",Assumptions!$B$26,0))
A6: Notre Dame | B6: AP #3, 5-0, Ind | C6: Kalshi 12.5% | D6: 0.125 | E6: 0.25 | F6: 0.5 | G6: 0.97 | H6: 0.97 | I6: 0.82 | J6: 0.15 | K6: 9.204 | L6: =Assumptions!$B$6*D6+Assumptions!$C$6*(E6-D6)+Assumptions!$D$6*(F6-E6)+Assumptions!$E$6*(G6-F6)+Assumptions!$F$6*(H6-G6) | M6: =K6+MIN(L6,Assumptions!$H$6) | N6: =M6-Assumptions!$I$6 | O6: =N6-Assumptions!$B$25*Q6 | P6: 1 | Q6: 3.067 | R6: KXNCAAF-27 exchange mid-price, pulled 2026-10-22 | S6: 2026-10-22 | T6: A | X6: Feder | Y6: =N6-IF(T6="C",Assumptions!$B$27,IF(T6="B",Assumptions!$B$26,0))
A7: Miami (FL) | B7: AP #4, 5-0, ACC | C7: Kalshi 14.5% | D7: 0.145 | E7: 0.29 | F7: 0.58 | G7: 0.97 | H7: 0.97 | I7: 0.8 | J7: 0.15 | K7: 8.748 | L7: =Assumptions!$B$6*D7+Assumptions!$C$6*(E7-D7)+Assumptions!$D$6*(F7-E7)+Assumptions!$E$6*(G7-F7)+Assumptions!$F$6*(H7-G7) | M7: =K7+MIN(L7,Assumptions!$H$6) | N7: =M7-Assumptions!$I$6 | O7: =N7-Assumptions!$B$25*Q7 | P7: 1 | Q7: 3.18 | R7: KXNCAAF-27 exchange mid-price, pulled 2026-10-22 | S7: 2026-10-22 | T7: A | X7: Wu | Y7: =N7-IF(T7="C",Assumptions!$B$27,IF(T7="B",Assumptions!$B$26,0))
A8: Ohio State | B8: AP #5, 4-1, Big Ten | C8: Kalshi 12.5% | D8: 0.125 | E8: 0.25 | F8: 0.5 | G8: 0.97 | H8: 0.97 | I8: 0.8 | J8: 0.15 | K8: 8.858 | L8: =Assumptions!$B$6*D8+Assumptions!$C$6*(E8-D8)+Assumptions!$D$6*(F8-E8)+Assumptions!$E$6*(G8-F8)+Assumptions!$F$6*(H8-G8) | M8: =K8+MIN(L8,Assumptions!$H$6) | N8: =M8-Assumptions!$I$6 | O8: =N8-Assumptions!$B$25*Q8 | P8: 2 | Q8: 3.155 | R8: KXNCAAF-27 exchange mid-price, pulled 2026-10-22 | S8: 2026-10-22 | T8: A | U8: one loss; books' favourite | X8: Mitchell | Y8: =N8-IF(T8="C",Assumptions!$B$27,IF(T8="B",Assumptions!$B$26,0))
A9: Texas | B9: AP #1, 4-0, SEC | C9: Kalshi 3.5% | D9: 0.035 | E9: 0.07 | F9: 0.14 | G9: 0.28 | H9: 0.56 | I9: 0.85 | J9: 0.15 | K9: 9.803 | L9: =Assumptions!$B$6*D9+Assumptions!$C$6*(E9-D9)+Assumptions!$D$6*(F9-E9)+Assumptions!$E$6*(G9-F9)+Assumptions!$F$6*(H9-G9) | M9: =K9+MIN(L9,Assumptions!$H$6) | N9: =M9-Assumptions!$I$6 | O9: =N9-Assumptions!$B$25*Q9 | P9: 2 | Q9: 2.904 | R9: KXNCAAF-27 exchange mid-price, pulled 2026-10-22 | S9: 2026-10-22 | T9: A | Y9: =N9-IF(T9="C",Assumptions!$B$27,IF(T9="B",Assumptions!$B$26,0))
A10: Indiana | B10: AP #7, 5-0, Big Ten | C10: Kalshi 7.5% | D10: 0.075 | E10: 0.15 | F10: 0.3 | G10: 0.6 | H10: 0.97 | I10: 0.72 | J10: 0.15 | K10: 7.172 | L10: =Assumptions!$B$6*D10+Assumptions!$C$6*(E10-D10)+Assumptions!$D$6*(F10-E10)+Assumptions!$E$6*(G10-F10)+Assumptions!$F$6*(H10-G10) | M10: =K10+MIN(L10,Assumptions!$H$6) | N10: =M10-Assumptions!$I$6 | O10: =N10-Assumptions!$B$25*Q10 | P10: 2 | Q10: 3.301 | R10: KXNCAAF-27 exchange mid-price, pulled 2026-10-22 | S10: 2026-10-22 | T10: A | X10: Korch | Y10: =N10-IF(T10="C",Assumptions!$B$27,IF(T10="B",Assumptions!$B$26,0))
A11: Alabama | B11: AP #6, 5-0, SEC | C11: Kalshi 4.5% | D11: 0.045 | E11: 0.09 | F11: 0.18 | G11: 0.36 | H11: 0.72 | I11: 0.74 | J11: 0.15 | K11: 7.519 | L11: =Assumptions!$B$6*D11+Assumptions!$C$6*(E11-D11)+Assumptions!$D$6*(F11-E11)+Assumptions!$E$6*(G11-F11)+Assumptions!$F$6*(H11-G11) | M11: =K11+MIN(L11,Assumptions!$H$6) | N11: =M11-Assumptions!$I$6 | O11: =N11-Assumptions!$B$25*Q11 | P11: 2 | Q11: 3.324 | R11: KXNCAAF-27 exchange mid-price, pulled 2026-10-22 | S11: 2026-10-22 | T11: A | X11: Jamzee | Y11: =N11-IF(T11="C",Assumptions!$B$27,IF(T11="B",Assumptions!$B$26,0))
A12: BYU | B12: AP #8, 4-0, Big 12 | C12: Kalshi 3.5% | D12: 0.035 | E12: 0.07 | F12: 0.14 | G12: 0.28 | H12: 0.56 | I12: 0.66 | J12: 0.16 | K12: 5.91 | L12: =Assumptions!$B$6*D12+Assumptions!$C$6*(E12-D12)+Assumptions!$D$6*(F12-E12)+Assumptions!$E$6*(G12-F12)+Assumptions!$F$6*(H12-G12) | M12: =K12+MIN(L12,Assumptions!$H$6) | N12: =M12-Assumptions!$I$6 | O12: =N12-Assumptions!$B$25*Q12 | P12: 3 | Q12: 3.384 | R12: KXNCAAF-27 exchange mid-price, pulled 2026-10-22 | S12: 2026-10-22 | T12: A | X12: Tim | Y12: =N12-IF(T12="C",Assumptions!$B$27,IF(T12="B",Assumptions!$B$26,0))
A13: Ole Miss | B13: AP #9, 3-1, SEC | C13: Kalshi 4.5% | D13: 0.045 | E13: 0.09 | F13: 0.18 | G13: 0.36 | H13: 0.72 | I13: 0.62 | J13: 0.16 | K13: 5.047 | L13: =Assumptions!$B$6*D13+Assumptions!$C$6*(E13-D13)+Assumptions!$D$6*(F13-E13)+Assumptions!$E$6*(G13-F13)+Assumptions!$F$6*(H13-G13) | M13: =K13+MIN(L13,Assumptions!$H$6) | N13: =M13-Assumptions!$I$6 | O13: =N13-Assumptions!$B$25*Q13 | P13: 3 | Q13: 3.233 | R13: KXNCAAF-27 exchange mid-price, pulled 2026-10-22 | S13: 2026-10-22 | T13: A | X13: Todd | Y13: =N13-IF(T13="C",Assumptions!$B$27,IF(T13="B",Assumptions!$B$26,0))
A14: LSU | B14: AP #10, 4-1, SEC | C14: Kalshi 4.5% | D14: 0.045 | E14: 0.09 | F14: 0.18 | G14: 0.36 | H14: 0.72 | I14: 0.6 | J14: 0.16 | K14: 4.656 | L14: =Assumptions!$B$6*D14+Assumptions!$C$6*(E14-D14)+Assumptions!$D$6*(F14-E14)+Assumptions!$E$6*(G14-F14)+Assumptions!$F$6*(H14-G14) | M14: =K14+MIN(L14,Assumptions!$H$6) | N14: =M14-Assumptions!$I$6 | O14: =N14-Assumptions!$B$25*Q14 | P14: 3 | Q14: 3.11 | R14: KXNCAAF-27 exchange mid-price, pulled 2026-10-22 | S14: 2026-10-22 | T14: A | Y14: =N14-IF(T14="C",Assumptions!$B$27,IF(T14="B",Assumptions!$B$26,0))
A15: Oregon | B15: AP #13, 3-1, Big Ten | C15: Kalshi 2.0% | D15: 0.02 | E15: 0.04 | F15: 0.08 | G15: 0.16 | H15: 0.32 | I15: 0.62 | J15: 0.16 | K15: 5.029 | L15: =Assumptions!$B$6*D15+Assumptions!$C$6*(E15-D15)+Assumptions!$D$6*(F15-E15)+Assumptions!$E$6*(G15-F15)+Assumptions!$F$6*(H15-G15) | M15: =K15+MIN(L15,Assumptions!$H$6) | N15: =M15-Assumptions!$I$6 | O15: =N15-Assumptions!$B$25*Q15 | P15: 3 | Q15: 3.179 | R15: KXNCAAF-27 exchange mid-price, pulled 2026-10-22 | S15: 2026-10-22 | T15: A | X15: Buckley | Y15: =N15-IF(T15="C",Assumptions!$B$27,IF(T15="B",Assumptions!$B$26,0))
A16: Texas Tech | B16: AP #11, 5-0, Big 12 | C16: Kalshi 1.5% | D16: 0.015 | E16: 0.03 | F16: 0.06 | G16: 0.12 | H16: 0.24 | I16: 0.62 | J16: 0.16 | K16: 5.056 | L16: =Assumptions!$B$6*D16+Assumptions!$C$6*(E16-D16)+Assumptions!$D$6*(F16-E16)+Assumptions!$E$6*(G16-F16)+Assumptions!$F$6*(H16-G16) | M16: =K16+MIN(L16,Assumptions!$H$6) | N16: =M16-Assumptions!$I$6 | O16: =N16-Assumptions!$B$25*Q16 | P16: 3 | Q16: 3.216 | R16: KXNCAAF-27 exchange mid-price, pulled 2026-10-22 | S16: 2026-10-22 | T16: A | X16: Molmen | Y16: =N16-IF(T16="C",Assumptions!$B$27,IF(T16="B",Assumptions!$B$26,0))
A17: Utah | B17: AP #12, 4-0, Big 12 | C17: Kalshi 1.5% | D17: 0.015 | E17: 0.03 | F17: 0.06 | G17: 0.12 | H17: 0.24 | I17: 0.58 | J17: 0.16 | K17: 4.282 | L17: =Assumptions!$B$6*D17+Assumptions!$C$6*(E17-D17)+Assumptions!$D$6*(F17-E17)+Assumptions!$E$6*(G17-F17)+Assumptions!$F$6*(H17-G17) | M17: =K17+MIN(L17,Assumptions!$H$6) | N17: =M17-Assumptions!$I$6 | O17: =N17-Assumptions!$B$25*Q17 | P17: 3 | Q17: 3.007 | R17: KXNCAAF-27 exchange mid-price, pulled 2026-10-22 | S17: 2026-10-22 | T17: A | Y17: =N17-IF(T17="C",Assumptions!$B$27,IF(T17="B",Assumptions!$B$26,0))
A18: Missouri | B18: AP #14, 4-1, SEC | C18: +10000 | D18: 0.0115 | E18: 0.023 | F18: 0.046 | G18: 0.092 | H18: 0.184 | I18: 0.5394 | J18: 0.2 | K18: 3.926 | L18: =Assumptions!$B$6*D18+Assumptions!$C$6*(E18-D18)+Assumptions!$D$6*(F18-E18)+Assumptions!$E$6*(G18-F18)+Assumptions!$F$6*(H18-G18) | M18: =K18+MIN(L18,Assumptions!$H$6) | N18: =M18-Assumptions!$I$6 | O18: =N18-Assumptions!$B$25*Q18 | P18: 4 | Q18: 3.182 | R18: estimate | S18: 2026-10-08 | T18: C | U18: [conf C: sd x1.25, p shrink 20%] | Y18: =N18-IF(T18="C",Assumptions!$B$27,IF(T18="B",Assumptions!$B$26,0))
A19: Tennessee | B19: AP #15, 4-1, SEC | C19: Kalshi 1.5% | D19: 0.015 | E19: 0.03 | F19: 0.06 | G19: 0.12 | H19: 0.24 | I19: 0.5 | J19: 0.16 | K19: 3.098 | L19: =Assumptions!$B$6*D19+Assumptions!$C$6*(E19-D19)+Assumptions!$D$6*(F19-E19)+Assumptions!$E$6*(G19-F19)+Assumptions!$F$6*(H19-G19) | M19: =K19+MIN(L19,Assumptions!$H$6) | N19: =M19-Assumptions!$I$6 | O19: =N19-Assumptions!$B$25*Q19 | P19: 4 | Q19: 2.47 | R19: KXNCAAF-27 exchange mid-price, pulled 2026-10-22 | S19: 2026-10-22 | T19: A | Y19: =N19-IF(T19="C",Assumptions!$B$27,IF(T19="B",Assumptions!$B$26,0))
A20: Florida | B20: AP #16, 4-1, SEC | C20: Kalshi 1.5% | D20: 0.015 | E20: 0.03 | F20: 0.06 | G20: 0.12 | H20: 0.24 | I20: 0.48 | J20: 0.16 | K20: 2.86 | L20: =Assumptions!$B$6*D20+Assumptions!$C$6*(E20-D20)+Assumptions!$D$6*(F20-E20)+Assumptions!$E$6*(G20-F20)+Assumptions!$F$6*(H20-G20) | M20: =K20+MIN(L20,Assumptions!$H$6) | N20: =M20-Assumptions!$I$6 | O20: =N20-Assumptions!$B$25*Q20 | P20: 4 | Q20: 2.353 | R20: KXNCAAF-27 exchange mid-price, pulled 2026-10-22 | S20: 2026-10-22 | T20: A | Y20: =N20-IF(T20="C",Assumptions!$B$27,IF(T20="B",Assumptions!$B$26,0))
A21: Oklahoma State | B21: AP #18, 3-1, Big 12 | C21: +30000 | D21: 0.0083 | E21: 0.0166 | F21: 0.0332 | G21: 0.0664 | H21: 0.1328 | I21: 0.4494 | J21: 0.2 | K21: 2.869 | L21: =Assumptions!$B$6*D21+Assumptions!$C$6*(E21-D21)+Assumptions!$D$6*(F21-E21)+Assumptions!$E$6*(G21-F21)+Assumptions!$F$6*(H21-G21) | M21: =K21+MIN(L21,Assumptions!$H$6) | N21: =M21-Assumptions!$I$6 | O21: =N21-Assumptions!$B$25*Q21 | P21: 4 | Q21: 2.616 | R21: estimate | S21: 2026-10-08 | T21: C | U21: [conf C: sd x1.25, p shrink 20%] | Y21: =N21-IF(T21="C",Assumptions!$B$27,IF(T21="B",Assumptions!$B$26,0))
A22: USC | B22: AP #19, 5-1, Big Ten | C22: +20000 | D22: 0.0088 | E22: 0.0176 | F22: 0.0352 | G22: 0.0704 | H22: 0.1408 | I22: 0.4494 | J22: 0.2 | K22: 2.807 | L22: =Assumptions!$B$6*D22+Assumptions!$C$6*(E22-D22)+Assumptions!$D$6*(F22-E22)+Assumptions!$E$6*(G22-F22)+Assumptions!$F$6*(H22-G22) | M22: =K22+MIN(L22,Assumptions!$H$6) | N22: =M22-Assumptions!$I$6 | O22: =N22-Assumptions!$B$25*Q22 | P22: 4 | Q22: 2.571 | R22: estimate | S22: 2026-10-08 | T22: C | U22: [conf C: sd x1.25, p shrink 20%] | Y22: =N22-IF(T22="C",Assumptions!$B$27,IF(T22="B",Assumptions!$B$26,0))
A23: Iowa | B23: AP #20, 4-1, Big Ten | C23: +30000 | D23: 0.0083 | E23: 0.0166 | F23: 0.0332 | G23: 0.0664 | H23: 0.1328 | I23: 0.4134 | J23: 0.2 | K23: 2.495 | L23: =Assumptions!$B$6*D23+Assumptions!$C$6*(E23-D23)+Assumptions!$D$6*(F23-E23)+Assumptions!$E$6*(G23-F23)+Assumptions!$F$6*(H23-G23) | M23: =K23+MIN(L23,Assumptions!$H$6) | N23: =M23-Assumptions!$I$6 | O23: =N23-Assumptions!$B$25*Q23 | P23: 4 | Q23: 2.336 | R23: estimate | S23: 2026-10-08 | T23: C | U23: [conf C: sd x1.25, p shrink 20%] | Y23: =N23-IF(T23="C",Assumptions!$B$27,IF(T23="B",Assumptions!$B$26,0))
A24: Mississippi State | B24: AP #17, 4-1, SEC | C24: Kalshi 0.5% | D24: 0.0096 | E24: 0.0192 | F24: 0.0384 | G24: 0.0768 | H24: 0.1536 | I24: 0.44 | J24: 0.16 | K24: 2.396 | L24: =Assumptions!$B$6*D24+Assumptions!$C$6*(E24-D24)+Assumptions!$D$6*(F24-E24)+Assumptions!$E$6*(G24-F24)+Assumptions!$F$6*(H24-G24) | M24: =K24+MIN(L24,Assumptions!$H$6) | N24: =M24-Assumptions!$I$6 | O24: =N24-Assumptions!$B$25*Q24 | P24: 4 | Q24: 1.975 | R24: KXNCAAF-27 exchange mid-price, pulled 2026-10-08 | S24: 2026-10-08 | T24: A | Y24: =N24-IF(T24="C",Assumptions!$B$27,IF(T24="B",Assumptions!$B$26,0))
A25: Michigan | B25: owned (Shep); AP rank not pulled | D25: 0.0077 | E25: 0.0154 | F25: 0.0308 | G25: 0.0616 | H25: 0.1232 | I25: 0.3864 | J25: 0.2 | K25: 2.299 | L25: =Assumptions!$B$6*D25+Assumptions!$C$6*(E25-D25)+Assumptions!$D$6*(F25-E25)+Assumptions!$E$6*(G25-F25)+Assumptions!$F$6*(H25-G25) | M25: =K25+MIN(L25,Assumptions!$H$6) | N25: =M25-Assumptions!$I$6 | O25: =N25-Assumptions!$B$25*Q25 | P25: 4 | Q25: 2.167 | R25: added because a league member currently owns this pick (draft_picks_2026.py); not in the first-pass pool, so figures are placeholders (conf C) | S25: 2026-10-08 | T25: C | U25: [conf C: sd x1.25, p shrink 20%] | X25: Shep | Y25: =N25-IF(T25="C",Assumptions!$B$27,IF(T25="B",Assumptions!$B$26,0))
A26: UCLA | B26: AP #21, 4-0, Big Ten | C26: Kalshi 1.5% | D26: 0.015 | E26: 0.03 | F26: 0.06 | G26: 0.12 | H26: 0.24 | I26: 0.36 | J26: 0.16 | K26: 1.773 | L26: =Assumptions!$B$6*D26+Assumptions!$C$6*(E26-D26)+Assumptions!$D$6*(F26-E26)+Assumptions!$E$6*(G26-F26)+Assumptions!$F$6*(H26-G26) | M26: =K26+MIN(L26,Assumptions!$H$6) | N26: =M26-Assumptions!$I$6 | O26: =N26-Assumptions!$B$25*Q26 | P26: 4 | Q26: 1.406 | R26: KXNCAAF-27 exchange mid-price, pulled 2026-10-22 | S26: 2026-10-22 | T26: A | Y26: =N26-IF(T26="C",Assumptions!$B$27,IF(T26="B",Assumptions!$B$26,0))
A27: Texas A&M | B27: owned (Fryar); AP rank not pulled | D27: 0.0077 | E27: 0.0154 | F27: 0.0308 | G27: 0.0616 | H27: 0.1232 | I27: 0.3864 | J27: 0.2 | K27: 2.244 | L27: =Assumptions!$B$6*D27+Assumptions!$C$6*(E27-D27)+Assumptions!$D$6*(F27-E27)+Assumptions!$E$6*(G27-F27)+Assumptions!$F$6*(H27-G27) | M27: =K27+MIN(L27,Assumptions!$H$6) | N27: =M27-Assumptions!$I$6 | O27: =N27-Assumptions!$B$25*Q27 | P27: 4 | Q27: 2.095 | R27: added because a league member currently owns this pick (draft_picks_2026.py); not in the first-pass pool, so figures are placeholders (conf C) | S27: 2026-10-08 | T27: C | U27: [conf C: sd x1.25, p shrink 20%] | X27: Fryar | Y27: =N27-IF(T27="C",Assumptions!$B$27,IF(T27="B",Assumptions!$B$26,0))
A28: Georgia Tech | B28: owned (Jens); AP rank not pulled | D28: 0.0077 | E28: 0.0154 | F28: 0.0308 | G28: 0.0616 | H28: 0.1232 | I28: 0.3864 | J28: 0.2 | K28: 2.228 | L28: =Assumptions!$B$6*D28+Assumptions!$C$6*(E28-D28)+Assumptions!$D$6*(F28-E28)+Assumptions!$E$6*(G28-F28)+Assumptions!$F$6*(H28-G28) | M28: =K28+MIN(L28,Assumptions!$H$6) | N28: =M28-Assumptions!$I$6 | O28: =N28-Assumptions!$B$25*Q28 | P28: 4 | Q28: 2.112 | R28: added because a league member currently owns this pick (draft_picks_2026.py); not in the first-pass pool, so figures are placeholders (conf C) | S28: 2026-10-08 | T28: C | U28: [conf C: sd x1.25, p shrink 20%] | X28: Jens | Y28: =N28-IF(T28="C",Assumptions!$B$27,IF(T28="B",Assumptions!$B$26,0))
A29: Boise State | B29: AP #23, 4-1, MWC | C29: +50000 | D29: 0.0077 | E29: 0.0154 | F29: 0.0308 | G29: 0.0616 | H29: 0.1232 | I29: 0.3774 | J29: 0.2 | K29: 2.183 | L29: =Assumptions!$B$6*D29+Assumptions!$C$6*(E29-D29)+Assumptions!$D$6*(F29-E29)+Assumptions!$E$6*(G29-F29)+Assumptions!$F$6*(H29-G29) | M29: =K29+MIN(L29,Assumptions!$H$6) | N29: =M29-Assumptions!$I$6 | O29: =N29-Assumptions!$B$25*Q29 | P29: 4 | Q29: 2.035 | R29: estimate | S29: 2026-10-08 | T29: C | U29: [conf C: sd x1.25, p shrink 20%] | Y29: =N29-IF(T29="C",Assumptions!$B$27,IF(T29="B",Assumptions!$B$26,0))
A30: Houston | B30: AP #22, 4-1, Big 12 | C30: +50000 | D30: 0.0077 | E30: 0.0154 | F30: 0.0308 | G30: 0.0616 | H30: 0.1232 | I30: 0.3774 | J30: 0.2 | K30: 2.174 | L30: =Assumptions!$B$6*D30+Assumptions!$C$6*(E30-D30)+Assumptions!$D$6*(F30-E30)+Assumptions!$E$6*(G30-F30)+Assumptions!$F$6*(H30-G30) | M30: =K30+MIN(L30,Assumptions!$H$6) | N30: =M30-Assumptions!$I$6 | O30: =N30-Assumptions!$B$25*Q30 | P30: 4 | Q30: 2.033 | R30: estimate | S30: 2026-10-08 | T30: C | U30: [conf C: sd x1.25, p shrink 20%] | Y30: =N30-IF(T30="C",Assumptions!$B$27,IF(T30="B",Assumptions!$B$26,0))
A31: Pittsburgh | B31: AP #25, 5-0, ACC | C31: +50000 | D31: 0.0077 | E31: 0.0154 | F31: 0.0308 | G31: 0.0616 | H31: 0.1232 | I31: 0.3594 | J31: 0.2 | K31: 2.087 | L31: =Assumptions!$B$6*D31+Assumptions!$C$6*(E31-D31)+Assumptions!$D$6*(F31-E31)+Assumptions!$E$6*(G31-F31)+Assumptions!$F$6*(H31-G31) | M31: =K31+MIN(L31,Assumptions!$H$6) | N31: =M31-Assumptions!$I$6 | O31: =N31-Assumptions!$B$25*Q31 | P31: 4 | Q31: 1.966 | R31: estimate | S31: 2026-10-08 | T31: C | U31: [conf C: sd x1.25, p shrink 20%] | Y31: =N31-IF(T31="C",Assumptions!$B$27,IF(T31="B",Assumptions!$B$26,0))
A32: SMU | B32: AP #24, 4-1, ACC | C32: +50000 | D32: 0.0077 | E32: 0.0154 | F32: 0.0308 | G32: 0.0616 | H32: 0.1232 | I32: 0.3594 | J32: 0.2 | K32: 2.031 | L32: =Assumptions!$B$6*D32+Assumptions!$C$6*(E32-D32)+Assumptions!$D$6*(F32-E32)+Assumptions!$E$6*(G32-F32)+Assumptions!$F$6*(H32-G32) | M32: =K32+MIN(L32,Assumptions!$H$6) | N32: =M32-Assumptions!$I$6 | O32: =N32-Assumptions!$B$25*Q32 | P32: 4 | Q32: 1.888 | R32: estimate | S32: 2026-10-08 | T32: C | U32: [conf C: sd x1.25, p shrink 20%] | Y32: =N32-IF(T32="C",Assumptions!$B$27,IF(T32="B",Assumptions!$B$26,0))
A34: Replacement-level EV (Nth best)

Sheet NCAAB
A1: NCAAB — 2027 draft research (EV model; see README)
A2: As of 2026-10-22. Sorted by E[total]. Yellow = inferred / low-confidence (C).
A4: Candidate | B4: Detail | C4: Odds / price | D4: p(champ) | E4: p(final) | F4: p(semi) | G4: p(quarter) | H4: p(rd 1) | I4: mu | J4: sd | K4: E[rank pts] (MC) | L4: E[bonus] | M4: E[total] | N4: VOR | O4: Risk-adj VOR | P4: Tier | Q4: SD rank pts | R4: Source | S4: As of | T4: Conf | U4: Notes | V4: Field draft score | W4: Field rank | X4: Owner | Y4: Conf-adj VOR
A5: Florida | C5: +600 | D5: 0.0983 | E5: 0.1966 | F5: 0.3932 | G5: 0.7864 | H5: 0.97 | I5: 0.9205 | J5: 0.128 | K5: 9.446 | L5: =Assumptions!$B$7*D5+Assumptions!$C$7*(E5-D5)+Assumptions!$D$7*(F5-E5)+Assumptions!$E$7*(G5-F5)+Assumptions!$F$7*(H5-G5) | M5: =K5+MIN(L5,Assumptions!$H$7) | N5: =M5-Assumptions!$I$7 | O5: =N5-Assumptions!$B$25*Q5 | P5: 1 | Q5: 3.181 | R5: CBS Sports title odds 2026-08-04 | S5: 2026-10-08 | T5: B | U5: ESPN preseason #1 [v2 certainty adj: sd x1.6, mu shrink 30%, p shrink 25%] | X5: Wu | Y5: =N5-IF(T5="C",Assumptions!$B$27,IF(T5="B",Assumptions!$B$26,0))
A6: Duke | C6: +600 | D6: 0.0983 | E6: 0.1966 | F6: 0.3932 | G6: 0.7864 | H6: 0.97 | I6: 0.9135 | J6: 0.128 | K6: 9.213 | L6: =Assumptions!$B$7*D6+Assumptions!$C$7*(E6-D6)+Assumptions!$D$7*(F6-E6)+Assumptions!$E$7*(G6-F6)+Assumptions!$F$7*(H6-G6) | M6: =K6+MIN(L6,Assumptions!$H$7) | N6: =M6-Assumptions!$I$7 | O6: =N6-Assumptions!$B$25*Q6 | P6: 1 | Q6: 3.263 | R6: CBS Sports title odds 2026-08-04 | S6: 2026-10-08 | T6: B | U6: [v2 certainty adj: sd x1.6, mu shrink 30%, p shrink 25%] | X6: Jens | Y6: =N6-IF(T6="C",Assumptions!$B$27,IF(T6="B",Assumptions!$B$26,0))
A7: UConn | C7: +1300 | D7: 0.0533 | E7: 0.1066 | F7: 0.2132 | G7: 0.4264 | H7: 0.8528 | I7: 0.8645 | J7: 0.128 | K7: 7.909 | L7: =Assumptions!$B$7*D7+Assumptions!$C$7*(E7-D7)+Assumptions!$D$7*(F7-E7)+Assumptions!$E$7*(G7-F7)+Assumptions!$F$7*(H7-G7) | M7: =K7+MIN(L7,Assumptions!$H$7) | N7: =M7-Assumptions!$I$7 | O7: =N7-Assumptions!$B$25*Q7 | P7: 1 | Q7: 3.471 | R7: CBS Sports title odds 2026-08-04 | S7: 2026-10-08 | T7: B | U7: [v2 certainty adj: sd x1.6, mu shrink 30%, p shrink 25%] | X7: Fryar | Y7: =N7-IF(T7="C",Assumptions!$B$27,IF(T7="B",Assumptions!$B$26,0))
A8: Illinois | C8: +1300 | D8: 0.0533 | E8: 0.1066 | F8: 0.2132 | G8: 0.4264 | H8: 0.8528 | I8: 0.8645 | J8: 0.128 | K8: 7.9 | L8: =Assumptions!$B$7*D8+Assumptions!$C$7*(E8-D8)+Assumptions!$D$7*(F8-E8)+Assumptions!$E$7*(G8-F8)+Assumptions!$F$7*(H8-G8) | M8: =K8+MIN(L8,Assumptions!$H$7) | N8: =M8-Assumptions!$I$7 | O8: =N8-Assumptions!$B$25*Q8 | P8: 2 | Q8: 3.501 | R8: CBS Sports title odds 2026-08-04 | S8: 2026-10-08 | T8: B | U8: [v2 certainty adj: sd x1.6, mu shrink 30%, p shrink 25%] | Y8: =N8-IF(T8="C",Assumptions!$B$27,IF(T8="B",Assumptions!$B$26,0))
A9: Michigan | C9: +1600 | D9: 0.0458 | E9: 0.0916 | F9: 0.1832 | G9: 0.3664 | H9: 0.7328 | I9: 0.8505 | J9: 0.128 | K9: 7.607 | L9: =Assumptions!$B$7*D9+Assumptions!$C$7*(E9-D9)+Assumptions!$D$7*(F9-E9)+Assumptions!$E$7*(G9-F9)+Assumptions!$F$7*(H9-G9) | M9: =K9+MIN(L9,Assumptions!$H$7) | N9: =M9-Assumptions!$I$7 | O9: =N9-Assumptions!$B$25*Q9 | P9: 2 | Q9: 3.537 | R9: CBS Sports title odds 2026-08-04 | S9: 2026-10-08 | T9: B | U9: 2026 champion [v2 certainty adj: sd x1.6, mu shrink 30%, p shrink 25%] | X9: Jamzee | Y9: =N9-IF(T9="C",Assumptions!$B$27,IF(T9="B",Assumptions!$B$26,0))
A10: Michigan State | C10: +2200 | D10: 0.0383 | E10: 0.0766 | F10: 0.1532 | G10: 0.3064 | H10: 0.6128 | I10: 0.8365 | J10: 0.128 | K10: 7.173 | L10: =Assumptions!$B$7*D10+Assumptions!$C$7*(E10-D10)+Assumptions!$D$7*(F10-E10)+Assumptions!$E$7*(G10-F10)+Assumptions!$F$7*(H10-G10) | M10: =K10+MIN(L10,Assumptions!$H$7) | N10: =M10-Assumptions!$I$7 | O10: =N10-Assumptions!$B$25*Q10 | P10: 2 | Q10: 3.541 | R10: CBS Sports title odds 2026-08-04 | S10: 2026-10-08 | T10: B | U10: [v2 certainty adj: sd x1.6, mu shrink 30%, p shrink 25%] | Y10: =N10-IF(T10="C",Assumptions!$B$27,IF(T10="B",Assumptions!$B$26,0))
A11: Houston | C11: +2500 | D11: 0.0346 | E11: 0.0692 | F11: 0.1384 | G11: 0.2768 | H11: 0.5536 | I11: 0.8365 | J11: 0.128 | K11: 7.274 | L11: =Assumptions!$B$7*D11+Assumptions!$C$7*(E11-D11)+Assumptions!$D$7*(F11-E11)+Assumptions!$E$7*(G11-F11)+Assumptions!$F$7*(H11-G11) | M11: =K11+MIN(L11,Assumptions!$H$7) | N11: =M11-Assumptions!$I$7 | O11: =N11-Assumptions!$B$25*Q11 | P11: 2 | Q11: 3.529 | R11: CBS Sports title odds 2026-08-04 | S11: 2026-10-08 | T11: B | U11: [v2 certainty adj: sd x1.6, mu shrink 30%, p shrink 25%] | X11: Theo | Y11: =N11-IF(T11="C",Assumptions!$B$27,IF(T11="B",Assumptions!$B$26,0))
A12: Arizona | C12: +2500 | D12: 0.0346 | E12: 0.0692 | F12: 0.1384 | G12: 0.2768 | H12: 0.5536 | I12: 0.8365 | J12: 0.128 | K12: 7.267 | L12: =Assumptions!$B$7*D12+Assumptions!$C$7*(E12-D12)+Assumptions!$D$7*(F12-E12)+Assumptions!$E$7*(G12-F12)+Assumptions!$F$7*(H12-G12) | M12: =K12+MIN(L12,Assumptions!$H$7) | N12: =M12-Assumptions!$I$7 | O12: =N12-Assumptions!$B$25*Q12 | P12: 3 | Q12: 3.554 | R12: CBS Sports title odds 2026-08-04 | S12: 2026-10-08 | T12: B | U12: [v2 certainty adj: sd x1.6, mu shrink 30%, p shrink 25%] | Y12: =N12-IF(T12="C",Assumptions!$B$27,IF(T12="B",Assumptions!$B$26,0))
A13: Kansas | C13: +4000 | D13: 0.0233 | E13: 0.0466 | F13: 0.0932 | G13: 0.1864 | H13: 0.3728 | I13: 0.7945 | J13: 0.128 | K13: 6.079 | L13: =Assumptions!$B$7*D13+Assumptions!$C$7*(E13-D13)+Assumptions!$D$7*(F13-E13)+Assumptions!$E$7*(G13-F13)+Assumptions!$F$7*(H13-G13) | M13: =K13+MIN(L13,Assumptions!$H$7) | N13: =M13-Assumptions!$I$7 | O13: =N13-Assumptions!$B$25*Q13 | P13: 3 | Q13: 3.512 | R13: CBS Sports title odds 2026-08-04 | S13: 2026-10-08 | T13: B | U13: [v2 certainty adj: sd x1.6, mu shrink 30%, p shrink 25%] | X13: Shep | Y13: =N13-IF(T13="C",Assumptions!$B$27,IF(T13="B",Assumptions!$B$26,0))
A14: Kentucky | D14: 0.0233 | E14: 0.0466 | F14: 0.0932 | G14: 0.1864 | H14: 0.3728 | I14: 0.7805 | J14: 0.144 | K14: 5.786 | L14: =Assumptions!$B$7*D14+Assumptions!$C$7*(E14-D14)+Assumptions!$D$7*(F14-E14)+Assumptions!$E$7*(G14-F14)+Assumptions!$F$7*(H14-G14) | M14: =K14+MIN(L14,Assumptions!$H$7) | N14: =M14-Assumptions!$I$7 | O14: =N14-Assumptions!$B$25*Q14 | P14: 3 | Q14: 3.657 | R14: estimate | S14: 2026-10-08 | T14: C | U14: [v2 certainty adj: sd x1.6, mu shrink 30%, p shrink 25%] | X14: Feder | Y14: =N14-IF(T14="C",Assumptions!$B$27,IF(T14="B",Assumptions!$B$26,0))
A15: Purdue | C15: +6500 | D15: 0.0181 | E15: 0.0362 | F15: 0.0724 | G15: 0.1448 | H15: 0.2896 | I15: 0.7665 | J15: 0.128 | K15: 5.338 | L15: =Assumptions!$B$7*D15+Assumptions!$C$7*(E15-D15)+Assumptions!$D$7*(F15-E15)+Assumptions!$E$7*(G15-F15)+Assumptions!$F$7*(H15-G15) | M15: =K15+MIN(L15,Assumptions!$H$7) | N15: =M15-Assumptions!$I$7 | O15: =N15-Assumptions!$B$25*Q15 | P15: 3 | Q15: 3.364 | R15: CBS Sports title odds 2026-08-04 | S15: 2026-10-08 | T15: B | U15: [v2 certainty adj: sd x1.6, mu shrink 30%, p shrink 25%] | X15: Korch | Y15: =N15-IF(T15="C",Assumptions!$B$27,IF(T15="B",Assumptions!$B$26,0))
A16: Louisville | D16: 0.0196 | E16: 0.0392 | F16: 0.0784 | G16: 0.1568 | H16: 0.3136 | I16: 0.7525 | J16: 0.144 | K16: 5.112 | L16: =Assumptions!$B$7*D16+Assumptions!$C$7*(E16-D16)+Assumptions!$D$7*(F16-E16)+Assumptions!$E$7*(G16-F16)+Assumptions!$F$7*(H16-G16) | M16: =K16+MIN(L16,Assumptions!$H$7) | N16: =M16-Assumptions!$I$7 | O16: =N16-Assumptions!$B$25*Q16 | P16: 3 | Q16: 3.55 | R16: estimate | S16: 2026-10-08 | T16: C | U16: [v2 certainty adj: sd x1.6, mu shrink 30%, p shrink 25%] | X16: Buckley | Y16: =N16-IF(T16="C",Assumptions!$B$27,IF(T16="B",Assumptions!$B$26,0))
A17: Tennessee | D17: 0.0196 | E17: 0.0392 | F17: 0.0784 | G17: 0.1568 | H17: 0.3136 | I17: 0.7525 | J17: 0.144 | K17: 5.08 | L17: =Assumptions!$B$7*D17+Assumptions!$C$7*(E17-D17)+Assumptions!$D$7*(F17-E17)+Assumptions!$E$7*(G17-F17)+Assumptions!$F$7*(H17-G17) | M17: =K17+MIN(L17,Assumptions!$H$7) | N17: =M17-Assumptions!$I$7 | O17: =N17-Assumptions!$B$25*Q17 | P17: 3 | Q17: 3.529 | R17: estimate | S17: 2026-10-08 | T17: C | U17: [v2 certainty adj: sd x1.6, mu shrink 30%, p shrink 25%] | Y17: =N17-IF(T17="C",Assumptions!$B$27,IF(T17="B",Assumptions!$B$26,0))
A18: Alabama | D18: 0.0196 | E18: 0.0392 | F18: 0.0784 | G18: 0.1568 | H18: 0.3136 | I18: 0.7525 | J18: 0.144 | K18: 5.068 | L18: =Assumptions!$B$7*D18+Assumptions!$C$7*(E18-D18)+Assumptions!$D$7*(F18-E18)+Assumptions!$E$7*(G18-F18)+Assumptions!$F$7*(H18-G18) | M18: =K18+MIN(L18,Assumptions!$H$7) | N18: =M18-Assumptions!$I$7 | O18: =N18-Assumptions!$B$25*Q18 | P18: 4 | Q18: 3.505 | R18: estimate | S18: 2026-10-08 | T18: C | U18: [v2 certainty adj: sd x1.6, mu shrink 30%, p shrink 25%] | X18: Mitchell | Y18: =N18-IF(T18="C",Assumptions!$B$27,IF(T18="B",Assumptions!$B$26,0))
A19: Texas Tech | D19: 0.0196 | E19: 0.0392 | F19: 0.0784 | G19: 0.1568 | H19: 0.3136 | I19: 0.7525 | J19: 0.144 | K19: 5.041 | L19: =Assumptions!$B$7*D19+Assumptions!$C$7*(E19-D19)+Assumptions!$D$7*(F19-E19)+Assumptions!$E$7*(G19-F19)+Assumptions!$F$7*(H19-G19) | M19: =K19+MIN(L19,Assumptions!$H$7) | N19: =M19-Assumptions!$I$7 | O19: =N19-Assumptions!$B$25*Q19 | P19: 4 | Q19: 3.486 | R19: estimate | S19: 2026-10-08 | T19: C | U19: [v2 certainty adj: sd x1.6, mu shrink 30%, p shrink 25%] | Y19: =N19-IF(T19="C",Assumptions!$B$27,IF(T19="B",Assumptions!$B$26,0))
A20: BYU | D20: 0.0173 | E20: 0.0346 | F20: 0.0692 | G20: 0.1384 | H20: 0.2768 | I20: 0.7385 | J20: 0.144 | K20: 4.815 | L20: =Assumptions!$B$7*D20+Assumptions!$C$7*(E20-D20)+Assumptions!$D$7*(F20-E20)+Assumptions!$E$7*(G20-F20)+Assumptions!$F$7*(H20-G20) | M20: =K20+MIN(L20,Assumptions!$H$7) | N20: =M20-Assumptions!$I$7 | O20: =N20-Assumptions!$B$25*Q20 | P20: 4 | Q20: 3.451 | R20: estimate | S20: 2026-10-08 | T20: C | U20: [v2 certainty adj: sd x1.6, mu shrink 30%, p shrink 25%] | Y20: =N20-IF(T20="C",Assumptions!$B$27,IF(T20="B",Assumptions!$B$26,0))
A21: Iowa State | D21: 0.0173 | E21: 0.0346 | F21: 0.0692 | G21: 0.1384 | H21: 0.2768 | I21: 0.7385 | J21: 0.144 | K21: 4.749 | L21: =Assumptions!$B$7*D21+Assumptions!$C$7*(E21-D21)+Assumptions!$D$7*(F21-E21)+Assumptions!$E$7*(G21-F21)+Assumptions!$F$7*(H21-G21) | M21: =K21+MIN(L21,Assumptions!$H$7) | N21: =M21-Assumptions!$I$7 | O21: =N21-Assumptions!$B$25*Q21 | P21: 4 | Q21: 3.443 | R21: estimate | S21: 2026-10-08 | T21: C | U21: [v2 certainty adj: sd x1.6, mu shrink 30%, p shrink 25%] | Y21: =N21-IF(T21="C",Assumptions!$B$27,IF(T21="B",Assumptions!$B$26,0))
A22: Gonzaga | D22: 0.0173 | E22: 0.0346 | F22: 0.0692 | G22: 0.1384 | H22: 0.2768 | I22: 0.7385 | J22: 0.144 | K22: 4.746 | L22: =Assumptions!$B$7*D22+Assumptions!$C$7*(E22-D22)+Assumptions!$D$7*(F22-E22)+Assumptions!$E$7*(G22-F22)+Assumptions!$F$7*(H22-G22) | M22: =K22+MIN(L22,Assumptions!$H$7) | N22: =M22-Assumptions!$I$7 | O22: =N22-Assumptions!$B$25*Q22 | P22: 4 | Q22: 3.462 | R22: estimate | S22: 2026-10-08 | T22: C | U22: [v2 certainty adj: sd x1.6, mu shrink 30%, p shrink 25%] | Y22: =N22-IF(T22="C",Assumptions!$B$27,IF(T22="B",Assumptions!$B$26,0))
